Workbook

Sheet 오픈소스&직접수집
A1: title | B1: authors | C1: journal | D1: publisher | E1: year | F1: doi
A2: Trends of fear and anger on YouTube during the initial stage of the COVID-19 outbreak in South Korea | B2: Jae-Joon Lee; Jongwoo Kim; Soo?Kyoung Lee | C2: BMC Public Health | E2: 2024 | F2: 10.1186/s12889-024-19023-6
A3: 키워드 네트워크를 활용한 국내 집단상담 연구 동향 분석(2008∼2022) | B3: Kwon, Kyoung-In; Kim, Min-Hyang | C3: 상담학연구 | D3: 한국상담학회 | E3: 2024 | F3: 10.15703/kjc.25.1.202402.117
A4: Literature Review of Extended Reality Research in Consumer | B4: Modeling | C4: Literature Review of Extended Reality Research in Consumer | E4: 2024 | F4: 10.53728/2765-6500.1627
A5: A study on research trends for pregnancy in adolescence: Focusing on text network analysis and topic modeling | B5: Seungmi Park; Eunju Kwak; Hye Ok Park; Jung Eun Hong | C5: The Journal of Korean Academic Society of Nursing Education | E5: 2024 | F5: 10.5977/jkasne.2024.30.2.149
A6: ‘어린이’와 ‘키즈’를 주제어로 하는 유튜브(YouTube) 콘텐츠 분석: LDA 토픽모델링을 활용하여 | B6: Lee, Keunyoung; Jung, Boomin | C6: 열린유아교육연구 | D6: 한국열린유아교육학회 | E6: 2024 | F6: 10.20437/KOAECE29-1-08
A7: 대한가정학회지 연구 동향 및 공저자 네트워크 분석: 2010∼2022년 게재 논문을 중심으로 | B7: Mi Jeong Park; Jung Hyun Chae; Han Ju | C7: Human Ecology Research | D7: 대한가정학회 | E7: 2024 | F7: 10.6115/her.2024.002
A8: 토픽모델링을 활용한 문화도시 관련 연구 동향 분석 | B8: Kim, Min-Sun | C8: 문화산업연구 | D8: 한국문화산업학회 | E8: 2024 | F8: 10.35174/JKCI.2024.03.24.1.47
A9: 경영·무역 학술논문의 의미 네트워크 분석법 도입에 관한 연구 | B9: Hong, Eui; Jeon, Ho-Jin; Kim, Young-Min | C9: 경영컨설팅연구 | D9: 한국경영컨설팅학회 | E9: 2024
A10: 국내 크리스천 코칭 연구동향 분석:키워드 네트워크 및 토픽모델링 분석을 중심으로 | B10: Choi, Yun-jeong; Kim, Yong-ku | C10: 코칭연구 | D10: 한국코칭학회 | E10: 2024
A11: 중고령 장애인 관련 국내 연구동향: 언어 네트워크 분석과 토픽모델링 활용 | B11: Yi Eunsil; Cho, Hye Chung | C11: 장애와 고용 | D11: 한국장애인고용공단 고용개발원 | E11: 2024 | F11: 10.15707/disem.2024.34.2.011
A12: 텍스트 마이닝을 활용한 노동시장 성과의 연구동향 분석 | B12: Donghwa Kim; Jiyoon Ban | C12: 직업능력개발연구 | D12: 한국직업능력연구원 | E12: 2024 | F12: 10.36907/krivet.2024.27.2.169
A13: 한국어 화용 교육 연구의 현황 및 과제- 토픽 모델링과 키워드 네트워크 분석을 중심으로 - | B13: Jungran Lee | C13: 영주어문 | D13: 영주어문학회 | E13: 2024
A14: Analyzing Demand for Customized Obesity Prevention and Management Across Adult Age Groups Using Focus Group Interview | B14: Jinah Park; Shinaeh Park; Mi So Kim | C14: INQUIRY The Journal of Health Care Organization Provision and Financing | E14: 2024 | F14: 10.1177/00469580241271152
A15: LDA topic modeling analysis of YouTube content with the keywords child” &amp; kids” | B15: Keunyoung Lee; Boomin Jung | C15: Korea open association for early childhood education | E15: 2024 | F15: 10.20437/koaece29-1-08
A16: Analysis of school sports policy research trends using text mining | B16: Min-Jun Kuk; Dae?Won Park | C16: Korean Journal of Teacher Education | E16: 2024 | F16: 10.14333/kjte.2024.40.2.04
A17: Analysis of Research Trends on Healthy Families Using LDA Topic Modeling : Focusing on the Periods of the 1st to 4th Basic Plans for Healthy Families | B17: 한국방송통신대학교 생활과학부 부교수; Hyunah Lee; Soombum Kwon | C17: Journal of Korean Family Resource Management Association | E17: 2024 | F17: 10.22626/jkfrma.2024.28.4.007
A18: Analysis of papers published in The Journal of Korean Academic Society of Nursing Education over 30 Years | B18: Seungmi Park; SuJeong Yu; Kyung-Choon Lim; Subin Choi; Eunyoung E. Suh | C18: The Journal of Korean Academic Society of Nursing Education | E18: 2024 | F18: 10.5977/jkasne.2024.30.4.382
A19: Exploring research trends in nursing organizational culture using topic modeling | B19: Eun?Jun Park; Chan Sook Park | C19: The Journal of Korean Academic Society of Nursing Education | E19: 2024 | F19: 10.5977/jkasne.2024.30.4.371
A20: Leveraging Digital Forensics in the Age of Smart Grids: A Survey of Tools and Techniques for Securing Electrical Power Systems | B20: Daniel Madan Raja S | C20: Journal of Electrical Systems | E20: 2024 | F20: 10.52783/jes.2024
A21: LDA 토픽모델링을 활용한 국내 영유아 돌봄 관련 연구 동향 분석 | B21: Chung, Chunghee; Lee, Hyorim; Jung, Boomin | C21: 열린유아교육연구 | D21: 한국열린유아교육학회 | E21: 2024 | F21: 10.20437/KOAECE29-5-02
A22: 공공무용단의 유튜브(YouTube)콘텐츠 표현유형에 대한 이용자 반응 분석 | B22: Taeyeon Kim | C22: 한국무용학회지 | D22: 한국무용학회 | E22: 2024 | F22: 10.26743/kaod.2024.24.1.011
A23: 네트워크 분석과 토픽모델링을 활용한 대학의 핵심역량 탐색 | B23: Mi-Hyun Bang; Youngmin Lee | C23: 한국콘텐츠학회 논문지 | D23: 한국콘텐츠학회 | E23: 2024 | F23: 10.5392/JKCA.2024.24.10.125
A24: 중독 관련 뉴스의 텍스트 네트워크 분석 및 시사점: 1990년부터 현재까지 | B24: Kim, Mee Sook | C24: 한국웰니스학회지 | D24: 한국웰니스학회 | E24: 2024 | F24: 10.21097/ksw.2024.11.19.4.207
A25: 청소년 임신에 대한 연구 동향 분석: 텍스트 네트워크 분석과 토픽 모델링 | B25: Park Seung Mi; EUNJU KWAK; HYE OK PARK; Hong, Jung Eun | C25: 한국간호교육학회지 | D25: 한국간호교육학회 | E25: 2024 | F25: 10.5977/jkasne.2024.30.2.149
A26: 키워드 네트워크 분석을 통한 유아·아동 비만 및 신체활동 관련 국내 연구 동향 분석 | B26: Na-Young An; Eun-Jung Kim | C26: 한국발육발달학회지 | D26: 한국발육발달학회 | E26: 2024 | F26: 10.34284/KJGD.2024.08.32.3.139
A27: 키워드 네트워크 분석을 활용한 국내 미술치료 질적 연구 동향 분석(2013～2024) | B27: Choi, Han-Na; Lim, Na-Young | C27: 예술심리치료연구 | D27: 한국예술심리치료학회 | E27: 2024 | F27: 10.32451/KJOAPS.2024.20.3.123
A28: 텍스트 마이닝을 활용한 학교체육정책 연구 동향 분석 | B28: Kuk, Min-Jun; Park, Dae-Won | C28: 교원교육 | D28: 교육연구원 | E28: 2024 | F28: 10.14333/KJTE.2024.40.2.04
A29: ‘계절의 변화 원인’단원 지도에 대한 초등예비교사들의 인식분석 | B29: lee yong seob | C29: 대한지구과학교육학회지 | D29: 대한지구과학교육학회 | E29: 2024
A30: 2023 카타르 아시안컵 축구협회를 둘러싼 여론 변화 탐색: 토픽모델링 분석을 중심으로 | B30: Kim, Nam-Gyu | C30: 한국융합과학회지 | D30: 한국융합과학회 | E30: 2024 | F30: 10.24826/KSCS.13.6.4
A31: A Comparative Analysis of Synonymous Verbs Based on American and British English Usage | B31: Ha, Myoung-Ho | C31: 언어학 연구 | D31: 한국중원언어학회 | E31: 2024 | F31: 10.17002/sil..72.202407.155
A32: A Study on Perception Survey of Preservice Elementary Teachers on Teaching Methods in Astronomy ? A Secondary Publication | B32: Yong-seob Lee | C32: International Education Forum | E32: 2024 | F32: 10.26689/ief.v2i1.6509
A33: A Study on the Degree Centrality Analysis of Meaningful Activities of Daily Living (ADL) in Male Stroke Patients : Focusing on Social Network Analysis | B33: 극동대학교 작업치료학과; Hyup Kim; Jin-Seok Oh | C33: 건강과 작업과학 | E33: 2024 | F33: 10.59910/kjhos.2024.5.1
A34: An Analysis of Counseling Research Trends Using Text Mining in South Korea | B34: THE KOREAN SOCIETY OF EDUCATIONAL THERAPY; Hye-Yon Seon; Hui-Ju Kim; Ye-Jee Kim; Ye-Rin Park | C34: Jounral of Educational Therapist | E34: 2024 | F34: 10.35185/kjet.16.3.3
A35: An Analysis of Research Trends Related to Children's Play Therapy Using Keyword Network Analysis | B35: Jing An; Seo-jin Baek | C35: Korean Association For Learner-Centered Curriculum And Instruction | E35: 2024 | F35: 10.22251/jlcci.2024.24.24.73
A36: Analysis of Domestic Dental Hygienist Research Trends | B36: Kyung Hui Moon | C36: International Journal of Clinical Preventive Dentistry | D36: 대한예방치과학회 | E36: 2024 | F36: 10.15236/ijcpd.2024.20.3.110
A37: Analysis of football research trends using text network analysis | B37: Jongwon Kim | C37: PLoS ONE | E37: 2024 | F37: 10.1371/journal.pone.0299782
A38: Analysis of Research Trends in Christian Coaching in South Korea - Keyword Network and Topic Modeling Analysis | B38: Yunjeong Choi; Yong-gu Kim | C38: Journal of Korean Coaching Research | E38: 2024 | F38: 10.20325/kca.2024.17.2.97
A39: Analysis of research trends on Childcare” for young children in Korea using LDA topic modeling | B39: Chunghee Chung; Hyorim Lee; Boomin Jung | C39: Korea open association for early childhood education | E39: 2024 | F39: 10.20437/koaece29-5-02
A40: Analysis of Research Trends on Cultural City Using Topic Modeling | B40: Minsun Kim | C40: Journal of Korea Culture Industry | E40: 2024 | F40: 10.35174/jkci.2024.03.24.1.47
A41: Analysis of trends in domestic research related to obesity and physical activity of infants and children through analysis of keyword networks | B41: Na-Young An; Eunjung Kim | C41: The Korean Journal of Growth and Development | E41: 2024 | F41: 10.34284/kjgd.2024.08.32.3.139
A42: Analysis of Trends in Recreational Sports Before and After Mega Sports Events Using Big Data | B42: Ji Yeon Lee; Sung-Whan Park | C42: Journal of Sport and Leisure Studies | E42: 2024 | F42: 10.51979/kssls.2024.10.98.225
A43: Analysis on Research Trends in Acculturative Stress Among Immigrants Using Text Mining | B43: Yihyun Kim; Insoo Oh; Jiyoon Ban | C43: Educational Research Institute | E43: 2024 | F43: 10.34245/jed.44.2.295
A44: Analyzing research trends after the international journal transition of the &lt;i&gt;Korean Journal of Medical Education&lt;/i&gt;: using topic modeling techniques | B44: So Jung Yune; Kwi Hwa Park | C44: Korean journal of medical education | E44: 2024 | F44: 10.3946/kjme.2024.291
A45: Analyzing research trends after the international journal transition of the <i>Korean Journal of Medical Education</i>: using topic modeling techniques | B45: Yune, So-Jung; Park, Kwi-Hwa | C45: Korean Journal of Medical Education | D45: 한국의학교육학회 | E45: 2024 | F45: 10.3946/kjme.2024.291
A46: Analyzing the Comprehensive Efficacy of a Digital Platform - Based the Mental Fitness Program for Pastoral Wives - | B46: Na Mi Kim; Seok-bong Kim; Ji Hyun Kim | C46: Theological Research Institute of Sahmyook University | E46: 2024 | F46: 10.56035/tod.2024.26.2.104
A47: CONNESSIONI EDUCATIVE” a system to create new alliances be-tween family, school, and community | B47: Martina Benvenuti; Elvis Mazzoni | C47: Archivio istituzionale della ricerca (Alma Mater Studiorum Universit? di Bologna) | E47: 2024
A48: Content Analysis of Patient Safety Incident Reports Using Text Mining: A Secondary Data Analysis | B48: Baek On-Jeon; Moon HoJin; Kim Hyosun; Sun-hwa Shin | C48: Korean Journal of Adult Nursing | D48: 한국성인간호학회 | E48: 2024 | F48: 10.7475/kjan.2024.36.4.298
A49: Exploring the Core Competencies of Universities Using Network Analysis and Topic Modeling | B49: Mi-Hyun Bang; Young-Min Lee | C49: The Journal of the Korea Contents Association | E49: 2024 | F49: 10.5392/jkca.2024.24.10.125
A50: Identification of Research Trends Related to Marriage Values Using Keyword Network Analysis | B50: Yun A Seo; H Jo | C50: Human Ecology Research | E50: 2024 | F50: 10.6115/her.2024.044
A51: Intelligent construction technology based information sharing network for prefabricated building supply chain: a social network analysis approach | B51: Rui Zhu; Lihong Li | C51: Kybernetes | E51: 2024 | F51: 10.1108/k-01-2024-0128
A52: Keyword Network Analysis of Research Trends on Social Skills in Individuals with Developmental Disabilities Using | B52: Dongil Kim; Nayeon Kim; Huiyeong Baek; Sungjin Ahn | C52: The Korean Association For Persons With Autism | E52: 2024 | F52: 10.33729/kapa.2024.3.3
A53: Keyword Network Analysis of Research Trends on Youth Preparing for Independent Living in South Korea | B53: Eul su Kim; So Yeun Cho | C53: Journal of Adolescent welfare | E53: 2024 | F53: 10.19034/kayw.2024.26.4.06
A54: LDA 토픽 모델링을 활용한 ??건강가정?? 연구동향 분석: 제1차~제4차 건강가정기본계획 시기를 중심으로 | B54: Lee Hyun Ah; Soonbum Kwon | C54: 가족자원경영과 정책 | D54: 한국가족자원경영학회 | E54: 2024
A55: Moving Towards Nutrition Security: Examining Differences in Sociodemographic, Dietary, and Cardiometabolic Profiles Using Evidence-Based Diet Quality Categories | B55: Cindy W. Leung; Elise Gahan; Laura A. Schmidt; Jerolde Mande; Deirdre K. Tobias | C55: Current Developments in Nutrition | E55: 2024 | F55: 10.1016/j.cdnut.2024.102718
A56: Network Analysis about Study on the Oral Health of People with Disabilities | B56: Seol-Hee Kim | C56: 치위생과학회지 | D56: 한국치위생과학회 | E56: 2024 | F56: 10.17135/jdhs.2024.24.2.107
A57: Network Analysis of Semantic Variations in Synonymous Verbs Across British and American English | B57: Ha, Myoung-Ho | C57: 언어과학 | D57: 한국언어과학회 | E57: 2024 | F57: 10.14384/kals.2024.31.3.111
A58: Public Opinion Changes Surrounding the 2023 Qatar Asian Cup Football Association: Focusing on Topic Modelling Analysis | B58: NamGyu Kim | C58: Korean Journal of Security Convergence Management | E58: 2024 | F58: 10.24826/kscs.13.6.4
A59: Relationship networks among nurses in acute nursing care units | B59: Seungmi Park; Eun?Jun Park | C59: The Journal of Korean Academic Society of Nursing Education | E59: 2024 | F59: 10.5977/jkasne.2024.30.2.182
A60: Research Trend Analysis of Community-based | B60: Network Analysis | C60: Journal of the | D60: PNG Publications | E60: 2024 | F60: 10.5993/AJHB.48.3.2
A61: Research Trends and Co-author Network Analysis of the Journal of the Korean Home Economics Association: Articles Published from 2010 to 2022 | B61: Mi Jeong Park; Jung Hyun Chae; Ju Hyoung Han | C61: Human Ecology Research | E61: 2024 | F61: 10.6115/her.2024.002
A62: Research Trends on Doctors’ Competencies in Korea Using Text Network Analysis | B62: Young Jon Kim; Jea Woog Lee; Yune, So-Jung | C62: 의학교육논단 | D62: 연세대학교 의과대학 | E62: 2024 | F62: 10.17496/kmer.23.043
A63: Semantic and Grammatical Analysis of Synonymous Adjectives in British English | B63: Ha, Myoung-Ho | C63: 새한영어영문학 | D63: 새한영어영문학회 | E63: 2024 | F63: 10.25151/nkje.2024.66.3.007
A64: Social Norms of Body Image for Young Women Over the Past Decade: A Text Mining Analysis of News Big Data | B64: Jisu Lee; Hyeonkyeong Lee; Hyeyeon Lee; Gahui Hwang | C64: Current Developments in Nutrition | E64: 2024 | F64: 10.1016/j.cdnut.2024.102717
A65: Sociodemographic, Psychosocial, and Household Level Factors Associated With Fruit, Vegetable, and Fiber Consumption Among Corner Store Customers in Baltimore, Maryland | B65: Emma Lewis; Lisa Poirier-Barna; Stacey Williamson; Antonio J Trujillo; Takeru Igusa; Joel Gittelsohn | C65: Current Developments in Nutrition | E65: 2024 | F65: 10.1016/j.cdnut.2024.102719
A66: Temporal Exploration of New Nurses’ Field Adaptation Using Text Network Analysis | B66: Ahn, Shin Hye; Jeong, Hye Won; Yang, Seong Gyeong; Jung, Ue Seok; Choi, Myoung Lee; Kim, Heui Seon | C66: Journal of Korean Academy of Nursing | D66: 한국간호과학회 | E66: 2024 | F66: 10.4040/jkan.24034
A67: Text Network Analysis of Addiction-Related News Coverage and Its Implications: From 1990 To the Present | B67: Mee Sook Kim | C67: Journal of the Korean society for Wellness | E67: 2024 | F67: 10.21097/ksw.2024.11.19.4.207
A68: The Future of Lifelong Learning Based on a Keyword Mining Technique from the Cases of South Korea and Taiwan | B68: Hae Na Kim; Ya-li Wu | E68: 2024 | F68: 10.1108/979-8-88730-597-420251012
A69: The Trends in the Research on Case Management: Using Sematic Network Analysis and Topic Modeling | B69: Eun-A Park; Juyeon Lee; Hye-Chung Cho | C69: Health & Welfare | E69: 2024 | F69: 10.23948/kshw.2024.09.30.3.203
A70: Trends Analysis of Domestic Art Therapy Qualitative Research Using Keyword Network Analysis(2013-2024) | B70: 가천대학교 일반대학원 특수상담치료학과 미술치료학 박사과정; Han-Na Choi; Na-Young Lim | C70: Journal of Arts Psychotherapy | E70: 2024 | F70: 10.32451/kjoaps.2024.20.3.123
A71: Voice of Customer Analysis of Nursing Care in a Tertiary Hospital: Text Network Analysis and Topic Modeling | B71: Hyunjung Ko; Na?Ra Han; Seul?Ki Jeong; Jeong A Jeong; Hye Ryoung Yun; Eun Sil Kim; Young Jun Jang; Eun Ju Choi; Chun Hoe Lim; Min Hee Jung; Jung Hee Kim; Dong Hyu Cho; Seok Hee Jeong | C71: Journal of Korean Academy of Nursing Administration | E71: 2024 | F71: 10.11111/jkana.2024.30.5.529
A72: 뉴스 빅데이터를 이용한 국내 언론의 무용공연 보도 특성 분석 | B72: Lee Yoon Kyung; Kim Tae Yeon | C72: 한국무용과학회지 | D72: 한국무용과학회 | E72: 2024
A73: 대한체육회장의 신년사에 나타난 정권별 체육정책 이슈: 의미연결망 분석의 적용 | B73: 이지은; Park, Jae-Hyeon; Jiwun Yoon | C73: 한국체육정책학회지 | D73: 한국체육정책학회 | E73: 2024
A74: 디지털 플랫폼을 활용한 목회자 사모를 위한 멘탈피트니스 프로그램의 통합적 효과 분석 | B74: Kim, Semi; Kim Nami; Kim, Jihyun | C74: 신학과 학문 | D74: 신학연구소 | E74: 2024 | F74: 10.56035/tod.2024.26.2.104
A75: 빅데이터 기반 메가 스포츠 이벤트 전후 생활 스포츠 트렌드 분석 | B75: LEE JI YEON; Park Sung Je | C75: 한국사회체육학회지 | D75: 한국사회체육학회 | E75: 2024 | F75: 10.51979/KSSLS.2024.10.98.225
A76: 사례관리에 관한 연구동향: 언어 네트워크 분석과 토픽모델링 활용 | B76: Eun-A Park; Jae-Kyeong Lee; Hye-Chung Cho | C76: 보건과 복지 | D76: 한국보건복지학회 | E76: 2024 | F76: 10.23948/kshw.2024.09.30.3.203
A77: 스포츠 AI 심판에 대한 언론의 인식: 키워드 네트워크 분석 활용 | B77: sehwa KIM; Jae-Hyeon; Jiwun Yoon | C77: 한국체육측정평가학회지 | D77: 한국체육측정평가학회 | E77: 2024 | F77: 10.21797/ksme.2024.26.4.008
A78: 식약처 고시 9종 한약서에 수록된 뇌전증 치료 한약 처방의 네트워크 분석 | B78: Kim Tae Hwan; Kim Hye Yeon; Han Ju Hui; Bang Mi Ran; Chang Gyu Tae; Jin Yong Lee; Kim Hyo In; Donghun Lee; Lee Sun Haeng | C78: 대한한방소아과학회지 | D78: 대한한방소아과학회 | E78: 2024
A79: 아시안게임 e스포츠 시범 종목 시행 전후 인식 비교: 언론보도 대상 키워드 네트워크 분석 | B79: Seo YooJin; Jiwun Yoon; Jae-Hyeon | C79: 한국체육측정평가학회지 | D79: 한국체육측정평가학회 | E79: 2024 | F79: 10.21797/ksme.2024.26.4.004
A80: 언어 네트워크 분석과 토픽 모델링을 활용한 학문 목적 한국어 말하기 교육 연구 동향 분석 | B80: Hyunjung Choi; park, bujeon | C80: 새국어교육 | D80: 한국국어교육학회 | E80: 2024 | F80: 10.15734/koed..139.202406.69
A81: 염증성 장질환 처방에 대한 네트워크 분석 - K-HERB 데이터베이스를 활용한 예비적 처방 탐색 - | B81: Jae-Yeon Lee; Yu-Gyeong Lee; Yeon-Hwa Lee; Seojung Ha; Bo-In Kwon | C81: 대한예방한의학회지 | D81: 대한예방한의학회 | E81: 2024 | F81: 10.25153/spkom.2024.28.2.009
A82: 인공지능을 활용한 미래교육 연구 동향 분석-2000~2023년 연구물을 중심으로- | B82: Seo Yun A; Nam Ki Won | C82: 문화기술의 융합 | D82: 국제문화기술진흥원 | E82: 2024 | F82: 10.17703/JCCT.2024.10.5.715
A83: 종합병원 간호단위의 간호사 관계 네트워크 연구 | B83: Park Seung Mi; Park, Eun Jun | C83: 한국간호교육학회지 | D83: 한국간호교육학회 | E83: 2024 | F83: 10.5977/jkasne.2024.30.2.182
A84: 키워드 네트워크 분석 및 토픽모델링을 활용한 위기개입·상담 관련 연구동향 분석 | B84: Moonkyeong Jeong | C84: 한국과 국제사회 | D84: 한국정치사회연구소 | E84: 2024 | F84: 10.22718/kga.2024.8.6.029
A85: 키워드 네트워크 분석을 통한 발달장애인의 사회성 관련 연구 동향 분석 | B85: Kim, Dongil; Kim, Nayeon; Baek, Huiyeong; Ahn, Sungjin | C85: 자폐성장애연구 | D85: 한국자폐학회 | E85: 2024 | F85: 10.33729/kapa.2024.3.3
A86: 키워드 네트워크 분석을 통해 살펴본 국내 자립준비청년 연구 동향 | B86: Kim, Eul Su; Cho, So Yeun | C86: 청소년복지연구 | D86: 한국청소년복지학회 | E86: 2024 | F86: 10.19034/KAYW.2024.26.4.06
A87: 키워드 네트워크 분석을 활용한 결혼가치관 관련 연구동향 분석 | B87: Yun A Seo; Hee Jin Jo | C87: Human Ecology Research | D87: 대한가정학회 | E87: 2024 | F87: 10.6115/her.2024.044
A88: 키워드 네트워크 분석을 활용한 유아 놀이치료 관련 연구동향 분석 | B88: An, Ji-su; Baek, Seo-jin | C88: 학습자중심교과교육연구 | D88: 학습자중심교과교육학회 | E88: 2024 | F88: 10.22251/jlcci.2024.24.24.73
A89: 태권도 전자호구 제조업체에 따른 선수들의 인식비교 | B89: Kyeong Hoon Park; Oh Hyeri | C89: 한국레저사이언스학회지 | D89: 한국레저사이언스학회 | E89: 2024 | F89: 10.37408/kjls.2024.15.4.77
A90: 텍스트 마이닝을 활용한 국내 상담 연구 동향 분석 | B90: Seon, Hye-Yon; Kim, Hui-Ju; Kim, Ye-Jee; Park, Ye-Rin | C90: 교육치료연구 | D90: 한국교육치료학회 | E90: 2024 | F90: 10.35185/KJET.16.3.3
... A95: 한국간호교육학회지 30년간 논문 분석 | B95: Park, Seung Mi; Yu, SuJeong; Lim, Kyung Choon; Choi, Subin; Suh, Eunyoung | C95: 한국간호교육학회지 | D95: 한국간호교육학회 | E95: 2024 | F95: 10.5977/jkasne.2024.30.4.382
A96: 한국의 ‘학교-자폐’ 연구 동향: 텍스트 마이닝을 이용한 사회연결망 분석 | B96: Ha Seong-Kyu; Kim Junghun-Aj | C96: 대한치료과학회지 | D96: 대한치료과학회 | E96: 2024
A97: Intelligent construction technology based information sharing network for prefabricated building supply chain | B97: Rui Zhu; Shenyang Jianzhu University | C97: Rui Zhu and Lihong Li School of Management, Shenyang Jianzhu University, Shenyang, | D97: Emerald | E97: 2024 | F97: 10.1108/K-01-2024-0128
A98: 인공지능과 간호에 관한 언론보도 기사의 키워드 네트워크 분석 및 토픽 모델링 | B98: Ha, Ju-Young; Park HyoJin | C98: Journal of Korean Academy of Nursing | D98: 한국간호과학회 | E98: 2023
A99: Smartphones are indispensable in modern society because | B99: Eun Jee Lee | C99: sedentary behavior | D99: Korean Academy of Child Health Nursing | E99: 2023 | F99: 10.4094/chnr.2023.29.2.128
A100: 텍스트 마이닝을 활용한 사이버폭력 주변인의 연구동향 분석 | B100: BAN, Jiyoon; Kim, Donghwa | C100: 교육학연구 | D100: 한국교육학회 | E100: 2023
A101: NetMiner: Identifying Failure-Inducing Patterns in the Logs Generated by Network Monitoring Software | B101: G. Sathi; Lokesh Vedullapalli; Macharla Hemanth Kishan; Tarannum Shaila Zaman; Md Tariqul Islam; Mahmoud M. Badr | E101: 2023 | F101: 10.1109/icccnt56998.2023.10308051
A102: 간호관련 국민청원 분석: 텍스트네트워크 분석 및 토픽모델링 | B102: 고현정; Jeong, Seok Hee; Eun Jee Lee; Kim Hee Sun | C102: Journal of Korean Academy of Nursing | D102: 한국간호과학회 | E102: 2023
A103: 국내 교수설계 관련 연구동향 분석:『교육공학연구』에 나타난 주제, 방법, 맥락, 키워드를 중심으로 | B103: Bo-Kyung Go; Cheolil Lim; Jeong, Yeil; Taeyoen Eom | C103: 교육공학연구 | D103: 한국교육공학회 | E103: 2023 | F103: 10.17232/KSET.39.2.639
A104: 만 3세 유아 학부모의 유치원 및 어린이집 선택 요인과 요구 탐색: 의미연결망 분석방법을 중심으로 | B104: Lee So Jung; Seo, Yoon-Hee | C104: 어린이미디어연구 | D104: 한국어린이미디어학회 | E104: 2023
...

Sheet wos(corecollection)_260528
A1: Publication Type | B1: Authors | C1: Book Authors | D1: Book Editors | E1: Book Group Authors | F1: Author Full Names | G1: Book Author Full Names | H1: Group Authors | I1: Article Title | J1: Source Title | K1: Book Series Title | L1: Book Series Subtitle | M1: Language | N1: Document Type | O1: Conference Title | P1: Conference Date | Q1: Conference Location | R1: Conference Sponsor | S1: Conference Host | T1: Author Keywords | U1: Keywords Plus | V1: Abstract | W1: Addresses | X1: Affiliations | Y1: Reprint Addresses | Z1: Email Addresses | AA1: Researcher Ids | AB1: ORCIDs | AC1: Funding Orgs | AD1: Funding Name Preferred | AE1: Funding Text | AF1: Cited References | AG1: Cited Reference Count | AH1: Times Cited, WoS Core | AI1: Times Cited, All Databases | AJ1: 180 Day Usage Count | AK1: Since 2013 Usage Count | AL1: Publisher | AM1: Publisher City | AN1: Publisher Address | AO1: ISSN | AP1: eISSN | AQ1: ISBN | AR1: Journal Abbreviation | AS1: Journal ISO Abbreviation | AT1: Publication Date | AU1: Publication Year | AV1: Volume | AW1: Issue | AX1: Part Number | AY1: Supplement | AZ1: Special Issue | BA1: Meeting Abstract | BB1: Start Page | BC1: End Page | BD1: Article Number | BE1: DOI | BF1: DOI Link | BG1: Book DOI | BH1: Early Access Date | BI1: Number of Pages | BJ1: WoS Categories | BK1: Web of Science Index | BL1: Research Areas | BM1: IDS Number | BN1: Pubmed Id | BO1: Open Access Designations | BP1: Highly Cited Status | BQ1: Hot Paper Status | BR1: Date of Export | BS1: UT (Unique WOS ID) | BT1: Web of Science Record | BU1: doi 중복 | BV1: 제목 중복
A2: netminer 검색 | B2: Kang, N; Ahn, S; Jeong, HW | F2: Kang, Naru; Ahn, Shinhye; Jeong, Hye Won | I2: A Text Network Analysis of Nurse Managers' Feedback Journals | J2: CIN-COMPUTERS INFORMATICS NURSING | N2: Article | V2: This study employed text network analysis to examine nurse managers' feedback journals for new nurses, highlighting the critical need for structured support during their transition period. A total of 429 feedback journals were documented by 32 nurse managers for 239 new nurses between September 2019 and March 2021 in South Korea, aiming to identify the challenges faced by new nurses and explore keyword relationships and thematic patterns. The analysis process included 4 stages: data preprocessing, keyword extraction, network and centrality analysis, and subtheme analysis. Using NetMiner 4.5.0, the analysis identified several central keywords in the feedback journals, with performance showing the highest centrality values (degree centrality = 0.448, closeness centrality = 0.580, betweenness centrality = 0.117), followed by experience and explanation. Through community detection analysis using the eigenvector method, 3 distinct subthemes emerged from the network structure: clinical practice fundamentals, learning and development process, and support and educational system. The findings of this study provide empirical evidence for developing structured feedback programs and enhancing nurse managers' interviewing competencies. The findings provide empirical evidence regarding linguistic patterns and thematic structures in nurse managers' feedback, suggesting systematic documentation protocols and utilization of these insights to inform structured feedback initiatives, thereby supporting new nurses' development. | W2: [Ahn, Shinhye] Chonnam Natl Univ Hosp, Dept Nursing, Gwangju, South Korea; [Jeong, Hye Won] Sunchon Natl Univ, Dept Nursing, Sunchon Si, Jeollanam Do, South Korea; [Jeong, Hye Won] Korea Natl Univ Transportat, Dept Nursing, 61 Daehak Ro, Jeungpyeong 27909, Chungcheongbuk, South Korea | Y2: Jeong, HW (corresponding author), Korea Natl Univ Transportat, Dept Nursing, 61 Daehak Ro, Jeungpyeong 27909, Chungcheongbuk, South Korea. | Z2: knr5318@naver.com; chunyanggirl@naver.com; hyewon1129@ut.ac.kr | AG2: 40 | AH2: 0 | AI2: 0 | AT2: MAR | AU2: 2026 | AV2: 44 | AW2: 3 | BD2: e01373 | BE2: 10.1097/CIN.0000000000001373 | BF2: =HYPERLINK("http://dx.doi.org/10.1097/CIN.0000000000001373","http://dx.doi.org/10.1097/CIN.0000000000001373") -> http://dx.doi.org/10.1097/CIN.0000000000001373 | BR2: 2026-05-29 | BS2: WOS:001708080600007 | BT2: =HYPERLINK("https%3A%2F%2Fwww.webofscience.com%2Fwos%2Fwoscc%2Ffull-record%2FWOS:001708080600007","View Full Record in Web of Science") -> View Full Record in Web of Science | BU2: =COUNTIF('오픈소스&직접수집'!F:F,'wos(corecollection)_260528'!BE2) -> 0 | BV2: =COUNTIF('오픈소스&직접수집'!A:A,'wos(corecollection)_260528'!I2) -> 1 | BW2: =SUM(BU2:BV2) -> 1
A3: netminer 검색 | B3: Kang, N; Zhang, P; Li, H; Wen, SS; Ji, CY; Yang, YQ | F3: Kang, Ning; Zhang, Peng; Li, Hao; Wen, Sisi; Ji, Chaoyang; Yang, Yongqiang | I3: Network Specification Mining With High Fidelity, Scalability, and Readability | J3: IEEE TRANSACTIONS ON NETWORKING | N3: Article | V3: Network specification, which describes what an existing network is designed for, can help operators better understand and manage their networks, and is a critical pre-condition for network verification and synthesis tools to work. Existing tools for specification mining either cannot scale to large networks, or scale by sacrificing fidelity. Moreover, the specification contains a huge number of low-level intents (e.g., tens of thousands of pairwise reachability), making it hard for operators to read. To this end, this paper presents NetMiner, which can mine specification from network configurations, with high scalability, fidelity, and easier to read. The key idea of NetMiner is to faithfully simulate the network routing and forwarding behaviors with control plane simulators and data plane verifiers, so as to achieve high fidelity. Meanwhile, NetMiner improves the scalability by identifying relevant failure scenarios, and aggregating them to significantly reduce the number of needed simulations. Moreover, NetMiner clusters similar low-level intents into a high-level intent, to make the specification more concise and easier to read. Experiments using real configurations from a large cloud service provider and synthetic configurations show that NetMiner can mine specification 10 x faster, and reduce the number of intents by 100 x, compared to state-of-the-art tools. | W3: [Kang, Ning; Zhang, Peng; Li, Hao; Wen, Sisi] Xi An Jiao Tong Univ, Minist Educ, MOE Key Lab Intelligent Networks & Network Secur, Xian 710049, Peoples R China; [Ji, Chaoyang; Yang, Yongqiang] Huawei Cloud Comp Technol Co Ltd, Beijing 100015, Peoples R China | Y3: Zhang, P (corresponding author), Xi An Jiao Tong Univ, Minist Educ, MOE Key Lab Intelligent Networks & Network Secur, Xian 710049, Peoples R China. | Z3: kangning2018@foxmail.com; p-zhang@xjtu.edu.cn; hao.li@xjtu.edu.cn; sswen0427@gmail.com; jichaoyang@huawei.com; yangyongqiang@huawei.com | AG3: 50 | AH3: 0 | AI3: 0 | AU3: 2026 | AV3: 34 | BB3: 737 | BC3: 752 | BE3: 10.1109/TON.2025.3607440 | BF3: =HYPERLINK("http://dx.doi.org/10.1109/TON.2025.3607440","http://dx.doi.org/10.1109/TON.2025.3607440") -> http://dx.doi.org/10.1109/TON.2025.3607440 | BH3: SEP 2025 | BR3: 2026-05-29 | BS3: WOS:001582265700001 | BT3: =HYPERLINK("https%3A%2F%2Fwww.webofscience.com%2Fwos%2Fwoscc%2Ffull-record%2FWOS:001582265700001","View Full Record in Web of Science") -> View Full Record in Web of Science | BU3: =COUNTIF('오픈소스&직접수집'!F:F,'wos(corecollection)_260528'!BE3) -> 0 | BV3: =COUNTIF('오픈소스&직접수집'!A:A,'wos(corecollection)_260528'!I3) -> 0 | BW3: =SUM(BU3:BV3) -> 0
A4: netminer 검색 | B4: Oh, J; Son, S; Park, JH | F4: Oh, Jinseok; Son, Sungmin; Park, Jin-Hyuck | I4: An analysis of adolescent leisure activity structure based on subjective well-being: Focusing on social network analysis | J4: PLOS ONE | N4: Article | V4: This study examines how adolescent leisure activity networks relate to subjective well-being (SWB) using Statistics Korea's 2019 Time Use Survey. The analysis includes 241 high-SWB and 241 low-SWB adolescents, assessing network density, inclusiveness, average distance, isolated nodes, degree centrality, and cohesion through NetMiner 4.0, with descriptive statistics processed in SPSS ver. 25.0. The results show clear differences in leisure activity networks. High-SWB adolescents engaged in more social activities and sports, while low-SWB adolescents participated in fewer, more solitary activities. High-SWB networks were diverse and well-connected, whereas low-SWB networks were more fragmented. Screen-based activities also played different roles: supporting social connections in high-SWB adolescents but reinforcing isolation in low-SWB adolescents. This study visually highlights that leisure participation varies by SWB level. The findings suggest that promoting diverse and interactive leisure activities can improve adolescent well-being, offering insights for policy and intervention programs. | W4: [Oh, Jinseok; Park, Jin-Hyuck] Univ Soonchunhyang, Soonchunhyang Except Children Inst, Asan, Chungcheongnam, South Korea; [Son, Sungmin] Yonsei Univ, Wonju Coll Med, Dept Psychiat, Wonju Si, Kangwon Do, South Korea | Y4: Park, JH (corresponding author), Univ Soonchunhyang, Soonchunhyang Except Children Inst, Asan, Chungcheongnam, South Korea. | Z4: roophy@naver.com | AG4: 34 | AH4: 0 | AI4: 0 | AU4: 2025 | AV4: 20 | AW4: 5 | BD4: e0322956 | BE4: 10.1371/journal.pone.0322956 | BF4: =HYPERLINK("http://dx.doi.org/10.1371/journal.pone.0322956","http://dx.doi.org/10.1371/journal.pone.0322956") -> http://dx.doi.org/10.1371/journal.pone.0322956 | BR4: 2026-05-29 | BS4: WOS:001488720800043 | BT4: =HYPERLINK("https%3A%2F%2Fwww.webofscience.com%2Fwos%2Fwoscc%2Ffull-record%2FWOS:001488720800043","View Full Record in Web of Science") -> View Full Record in Web of Science | BU4: =COUNTIF('오픈소스&직접수집'!F:F,'wos(corecollection)_260528'!BE4) -> 0 | BV4: =COUNTIF('오픈소스&직접수집'!A:A,'wos(corecollection)_260528'!I4) -> 0 | BW4: =SUM(BU4:BV4) -> 0
A5: netminer 검색 | B5: Seon, SH; Jeong, HW; Choi, JY | F5: Seon, Sun Hee; Jeong, Hye Won; Choi, Ja Yun | I5: Exploring the Knowledge Structure of Research for Nurse Preceptor Training Programs Using Text Network Analysis and Topic Modeling | J5: CIN-COMPUTERS INFORMATICS NURSING | N5: Article | V5: PurposeThis study utilized text network analysis and topic modeling to examine the research landscape of nurse preceptor training programs and facilitate the adaptation of new nurses in Korea and internationally.MethodsAbstracts from three Korean and 45 international studies on preceptor nurse training programs were collected. Keywords and meaningful morphemes from the abstracts and main text were analyzed and refined. A co-occurrence matrix of keywords was generated to analyze degree, closeness, and betweenness centrality using NetMiner 4.5.0 software. Topic modeling was used to identify key thematic structures.ResultsAmong the top 10 ranked keywords, five common terms-clinical competence, educator, nursing practice, teaching strategy, and mentoring-emerged across both frequency and centrality measures. Topic modeling identified four major subtopics: nurse preceptor programs for strengthening partnership skills and professional insights, communication programs to enhance the self-care competence of nurse preceptors, simulation programs to strengthen the expertise of nurse preceptors, and nurse preceptor programs to foster emotional empathy and growth.ConclusionThis study improves patient safety and professional competence by promoting optimal clinical decision-making for new nurse preceptees. Future research should develop educational programs that foster mutual empathy and professional growth between nurse preceptors and new nurse preceptees. | W5: [Seon, Sun Hee] Chonnam Natl Univ Hosp, Gwangju, South Korea; [Jeong, Hye Won] Korea Natl Univ Transportat, Jeungpyeong Gun, Chungcheongbuk, South Korea; [Choi, Ja Yun] Chonnam Natl Univ, Gwangju, South Korea | Y5: Choi, JY (corresponding author), Chonnam Natl Univ, Coll Nursing, 160 Baekseo ro, Gwangju 61469, South Korea. | Z5: Seon00509@hanmail.net; hyewon1129@ut.ac.kr; choijy@jnu.ac.kr | AG5: 33 | AH5: 0 | AI5: 0 | AT5: SEP | AU5: 2025 | AV5: 43 | AW5: 9 | BD5: e01347 | BE5: 10.1097/CIN.0000000000001347 | BF5: =HYPERLINK("http://dx.doi.org/10.1097/CIN.0000000000001347","http://dx.doi.org/10.1097/CIN.0000000000001347") -> http://dx.doi.org/10.1097/CIN.0000000000001347 | BR5: 2026-05-29 | BS5: WOS:001569257100006 | BT5: =HYPERLINK("https%3A%2F%2Fwww.webofscience.com%2Fwos%2Fwoscc%2Ffull-record%2FWOS:001569257100006","View Full Record in Web of Science") -> View Full Record in Web of Science | BU5: =COUNTIF('오픈소스&직접수집'!F:F,'wos(corecollection)_260528'!BE5) -> 0 | BV5: =COUNTIF('오픈소스&직접수집'!A:A,'wos(corecollection)_260528'!I5) -> 0 | BW5: =SUM(BU5:BV5) -> 0
A6: netminer 검색 | B6: Ahn, S; Jeong, HW | F6: Ahn, Shinhye; Jeong, Hye Won | I6: Analysis of clinical nurse educators' mentoring feedback on new nurse journals at a tertiary hospital in South Korea: utilizing text network analysis | J6: BMC NURSING | N6: Article | V6: BackgroundThe gap between knowledge and clinical practice causes stress and reality shock, contributing to low job satisfaction and high turnover among new nurses; in 2023, the turnover rate in South Korea reached 52.4%. Korean preceptorship programs are often too brief to adequately support new nurses' adaptation. Clinical nurse educators (CNEs) play a crucial role in addressing these issues by offering knowledge transfer, emotional support, and career guidance. Therefore, strategies to strengthen CNEs' coaching and mentoring skills are essential to support new nurses' stable clinical adaptation. This study analyzed how CNEs mentored new hospital nurses by responding to their post-entry journals.MethodsThis study employed a quantitative content analysis. We used NetMiner 4.5.1 to conduct a text network analysis of 1,742 mentoring journal responses written by four CNEs for 120 new nurses at C University Hospital in South Korea between June 2021 and May 2022.ResultsThe keyword attitude had the highest frequency (726), emphasizing the clinical importance of fostering positive attitudes among new nurses. The keyword network had average centrality measures of degree (.15), closeness (.43), and betweenness (.05). Keywords with high centrality, such as attitude, importance, performance, and difficulty, highlighted mentoring practices focused on enhancing clinical judgment, nursing performance, and managing workplace challenges. Eigenvector analysis identified three subtopic groups with optimal modularity (.295). Subthemes included: 1) helping new nurses to improve their professional competence, 2) encouraging new nurses struggling to adapt to the field, and 3) empathy for new nurses' burdens and stress.ConclusionsThe findings revealed that the CNEs' mentoring feedback focused on encouraging new nurses to maintain a positive attitude, inspiring their personal and professional growth, and offering empathy and encouragement to help them cope with burdens and stress. Based on these findings, targeted training modules for CNEs and mentoring guidelines should be developed to further support new nurses' adaptation to clinical practice. | W6: [Ahn, Shinhye] Sunchon Natl Univ, Dept Nursing, Suncheon Si, Jeollanam Do, South Korea; [Jeong, Hye Won] Korea Natl Univ Transportat, Dept Nursing, 61 Daehak Ro, Jeungpyeong 27909, Chungcheongbuk, South Korea | Y6: Jeong, HW (corresponding author), Korea Natl Univ Transportat, Dept Nursing, 61 Daehak Ro, Jeungpyeong 27909, Chungcheongbuk, South Korea. | Z6: hyewon1129@ut.ac.kr | AG6: 36 | AH6: 0 | AI6: 0 | AT6: AUG 5 | AU6: 2025 | AV6: 24 | AW6: 1 | BD6: 1016 | BE6: 10.1186/s12912-025-03625-5 | BF6: =HYPERLINK("http://dx.doi.org/10.1186/s12912-025-03625-5","http://dx.doi.org/10.1186/s12912-025-03625-5") -> http://dx.doi.org/10.1186/s12912-025-03625-5 | BR6: 2026-05-29 | BS6: WOS:001545465400002 | BT6: =HYPERLINK("https%3A%2F%2Fwww.webofscience.com%2Fwos%2Fwoscc%2Ffull-record%2FWOS:001545465400002","View Full Record in Web of Science") -> View Full Record in Web of Science | BU6: =COUNTIF('오픈소스&직접수집'!F:F,'wos(corecollection)_260528'!BE6) -> 0 | BV6: =COUNTIF('오픈소스&직접수집'!A:A,'wos(corecollection)_260528'!I6) -> 1 | BW6: =SUM(BU6:BV6) -> 1
A7: netminer 검색 | B7: Oh, JS; Ho, JG; Park, JH | F7: Oh, Jin Seok; Ho, Jong Gab; Park, Jin-Hyuck | I7: The Impact of Late Adolescents' Social Network Strength on Mental Health | J7: BRAIN AND BEHAVIOR | N7: Article | V7: Purpose This study examined how social network strength (i.e., the intensity and frequency of interactions within one's personal network, assessed using centrality measures such as degree, closeness, betweenness, and eigenvector centrality) affects mental health. Methods The study was conducted with 108 first-year university students. Data were collected using a structured questionnaire, and NetMiner 4.0 was employed to analyze degree centrality, closeness centrality, betweenness centrality, and eigenvector centrality as indicators of social network centrality. Additionally, Quadratic Assignment Procedure (QAP) correlation analysis and QAP regression analysis were conducted to assess the relationship between social network strength and mental health. Results The study found that stronger social networks were linked to better mental health in late adolescence. Specifically, higher social network centrality was associated with lower levels of hopelessness and depression. QAP correlation analysis revealed that hopelessness had a significant negative correlation with in-closeness centrality (which reflects how easily one can be reached by others within the network) (r = -0.252, p < 0.05), while depression was negatively correlated with in-degree centrality (the number of direct incoming connections from peers) (r = -0.233, p < 0.05), in-closeness centrality (r = -0.256, p < 0.05), and eigenvector centrality (a measure of how well a person is connected to popular or influential members of the network) (r = -0.291, p < 0.01). QAP regression analysis further confirmed that weaker social ties, indicated by higher out-closeness centrality (how easily one can reach others, especially those at a distance), were associated with higher depressive symptoms (adj. R-2 = 0.143, F = 2.423, p < 0.05). These results suggest that building stronger and more integrated social networks may help reduce psychological distress and support mental well-being in late adolescence. Conclusion Stronger social networks in late adolescence are associated with better mental health, highlighting the importance of social connections. While correlational findings suggest general links between centrality and emotional well-being, the regression results underscore specific predictors with practical implications. In-degree, in-closeness, and eigenvector centrality were associated with reduced depressive symptoms, indicating that being well-integrated within a social network may offer protective benefits. In contrast, high out-closeness centrality predicted increased depression, suggesting that the effort required to maintain outward-reaching connections may impose psychological burdens. These findings suggest that targeted interventions should focus on strengthening inward social integration while addressing the stress related to maintaining extensive outward connections, providing direction for more effective youth mental health strategies. | W7: [Oh, Jin Seok; Ho, Jong Gab; Park, Jin-Hyuck] Soonchunhyang Univ, Soonchunhyang Except Children Inst, Asan, South Korea; [Park, Jin-Hyuck] Soonchunhyang Univ, Coll Med Sci, Dept Occupat Therapy, Asan, South Korea | Y7: Park, JH (corresponding author), Soonchunhyang Univ, Soonchunhyang Except Children Inst, Asan, South Korea.;Park, JH (corresponding author), Soonchunhyang Univ, Coll Med Sci, Dept Occupat Therapy, Asan, South Korea. | Z7: roophy@naver.com | AG7: 60 | AH7: 0 | AI7: 0 | AT7: SEP 27 | AU7: 2025 | AV7: 15 | AW7: 10 | BD7: e70910 | BE7: 10.1002/brb3.70910 | BF7: =HYPERLINK("http://dx.doi.org/10.1002/brb3.70910","http://dx.doi.org/10.1002/brb3.70910") -> http://dx.doi.org/10.1002/brb3.70910 | BR7: 2026-05-29 | BS7: WOS:001582615700001 | BT7: =HYPERLINK("https%3A%2F%2Fwww.webofscience.com%2Fwos%2Fwoscc%2Ffull-record%2FWOS:001582615700001","View Full Record in Web of Science") -> View Full Record in Web of Science | BU7: =COUNTIF('오픈소스&직접수집'!F:F,'wos(corecollection)_260528'!BE7) -> 0 | BV7: =COUNTIF('오픈소스&직접수집'!A:A,'wos(corecollection)_260528'!I7) -> 0 | BW7: =SUM(BU7:BV7) -> 0
A8: netminer 검색 | B8: Ahn, SH; Jeong, HW; Yang, SG; Jung, US; Choi, ML; Kim, HS | F8: Ahn, Shin Hye; Jeong, Hye Won; Yang, Seong Gyeong; Jung, Ue Seok; Choi, Myoung Lee; Kim, Heui Seon | I8: Temporal Exploration of New Nurses' Field Adaptation Using Text Network Analysis | J8: JOURNAL OF KOREAN ACADEMY OF NURSING | N8: Article | V8: Purpose: This study aimed to analyze the experiences of new nurses during their first year of hospital employment to gather data for the development of an evidence-based new nurse residency program focused on adaptability. Methods: This study was conducted at a tertiary hospital in Korea between March and August 2021 with 80 new nurses who wrote in critical reflective journals during their first year of work. NetMiner 4.5.0 was used to conduct a text network analysis of the critical reflective journals to uncover core keywords and topics across three periods. Results: In the journals, over time, degree centrality emerged as study and patient understanding for 1 to 3 months, insufficient and stress for 4 to 6 months, and handover and preparation for 7 to 12 months. Major sub-themes at 1 to 3 months were: rounds, intravenous-cannulation, medical device, and patient understanding; at 4 to 6 months they were admission, discharge, oxygen therapy, and disease; and at 7 to 12 months they were burden, independence, and solution. Conclusion: These results provide valuable insights into the challenges and experiences encountered by new nurses during different stages of their field adaptation process. This information may highlight the best nurse leadership methods for improving institutional education and supporting new nurses' transitions to the hospital work environment. | W8: [Ahn, Shin Hye; Jeong, Hye Won; Yang, Seong Gyeong; Jung, Ue Seok; Choi, Myoung Lee; Kim, Heui Seon] Chonnam Natl Univ Hosp, Dept Nursing, Gwangju, South Korea; [Jeong, Hye Won] Chonnam Natl Univ, Coll Nursing, Gwangju, South Korea; [Jeong, Hye Won] Korea Natl Univ Transportat, Dept Nursing, 61 Daehak ro,Yonggang ri,Jeungpyeong eup, Jeungpyeong 27909, South Korea | Y8: Jeong, HW (corresponding author), Korea Natl Univ Transportat, Dept Nursing, 61 Daehak ro,Yonggang ri,Jeungpyeong eup, Jeungpyeong 27909, South Korea. | Z8: hyewon1129@ut.ac.kr | AG8: 41 | AH8: 4 | AI8: 5 | AT8: JUN | AU8: 2024 | AV8: 54 | AW8: 3 | BB8: 358 | BC8: 371 | BE8: 10.4040/jkan.24034 | BF8: =HYPERLINK("http://dx.doi.org/10.4040/jkan.24034","http://dx.doi.org/10.4040/jkan.24034") -> http://dx.doi.org/10.4040/jkan.24034 | BR8: 2026-05-29 | BS8: WOS:001314085800007 | BT8: =HYPERLINK("https%3A%2F%2Fwww.webofscience.com%2Fwos%2Fwoscc%2Ffull-record%2FWOS:001314085800007","View Full Record in Web of Science") -> View Full Record in Web of Science | BU8: =COUNTIF('오픈소스&직접수집'!F:F,'wos(corecollection)_260528'!BE8) -> 1 | BV8: =COUNTIF('오픈소스&직접수집'!A:A,'wos(corecollection)_260528'!I8) -> 1 | BW8: =SUM(BU8:BV8) -> 2
A9: netminer 검색 | B9: Park, J; Park, S; Kim, MS | F9: Park, Jinah; Park, Shinaeh; Kim, Mi So | I9: Analyzivng Demand for Customized Obesity Prevention and Management Across Adult Age Groups Using Focus Group Interview | J9: INQUIRY-THE JOURNAL OF HEALTH CARE ORGANIZATION PROVISION AND FINANCING | N9: Article | V9: With the increasing obesity rates, many studies on obesity prevention and management have been implemented. However, few studies focused on obesity in adulthood and different perceptions of obesity between life cycles. Thus, this study aimed to investigate the demand for customized obesity prevention and management (OPM) strategies across adult age groups. Focus group interviews were conducted to gather insights from three age groups: young adults (20-34 years), middle-aged adults (35-49 years), and seniors (50-64 years). A total of 17 participants took part in the study, with 5 participants in Group 1, 6 participants in Group 2, and 6 participants in Group 3. Thematic analysis and the use of NetMiner version 4.4.3 facilitated data categorization and scrutiny. The study employed qualitative methods to explore perceptions of obesity and preferences for personalized OPM strategies among participants. Diverse perspectives on obesity as a health threat were found among the age groups. While all stressed the importance of personalized OPM, preferences for strategies varied. Diet and exercise combination emerged as a common preference. This study highlighted the need for customized OPM approaches aligned with age-specific preferences. | W9: [Park, Jinah] Seoul Natl Univ, Seoul, South Korea; [Park, Shinaeh] Korea Univ, Seoul, South Korea; [Kim, Mi So] Shinhan Univ, Dongducheon Si, Gyeonggi Do, South Korea | Y9: Kim, MS (corresponding author), Shinhan Univ, Coll Nursing, 30 Beolmadeul Ro 40Beon Gil, Dongducheon Si 11644, Gyeonggi Do, South Korea. | Z9: misoangel83@gmail.com | AG9: 46 | AH9: 3 | AI9: 4 | AU9: 2024 | AV9: 61 | BD9: 469580241271152 | BE9: 10.1177/00469580241271152 | BF9: =HYPERLINK("http://dx.doi.org/10.1177/00469580241271152","http://dx.doi.org/10.1177/00469580241271152") -> http://dx.doi.org/10.1177/00469580241271152 | BR9: 2026-05-29 | BS9: WOS:001298233300001 | BT9: =HYPERLINK("https%3A%2F%2Fwww.webofscience.com%2Fwos%2Fwoscc%2Ffull-record%2FWOS:001298233300001","View Full Record in Web of Science") -> View Full Record in Web of Science | BU9: =COUNTIF('오픈소스&직접수집'!F:F,'wos(corecollection)_260528'!BE9) -> 1 | BV9: =COUNTIF('오픈소스&직접수집'!A:A,'wos(corecollection)_260528'!I9) -> 1 | BW9: =SUM(BU9:BV9) -> 2
A10: netminer 검색 | B10: Lee, JJ; Kim, J; Lee, SK | F10: Lee, Jae-Joon; Kim, Jongwoo; Lee, Soo-Kyoung | I10: Trends of fear and anger on YouTube during the initial stage of the COVID-19 outbreak in South Korea | J10: BMC PUBLIC HEALTH | N10: Article | V10: Background The COVID-19 pandemic has been the most widespread and threatening health crisis experienced by the Korean society. Faced with an unprecedented threat to survival, society has been gripped by social fear and anger, questioning the culpability of this pandemic. This study explored the correlation between social cognitions and negative emotions and their changes in response to the severe events stemming from the COVID-19 pandemic in South Korea. Methods The analysis was based on a cognitive-emotional model that links fear and anger to the social causes that trigger them and used discursive content from comments posted on YouTube's COVID-19-related videos. A total of 182,915 comments from 1,200 videos were collected between January and December 2020. We performed data analyses and visualizations using R, Netminer 4.0, and Gephi software and calculated Pearson's correlation coefficients between emotions. Results YouTube videos were analyzed for keywords indicating cognitive assessments of major events related to COVID-19 and keywords indicating negative emotions. Eight topics were identified through topic modeling: causes and risks, perceptions of China, media and information, infection prevention rules, economic activity, school and infection, political leaders, and religion, politics, and infection. The correlation coefficient between fear and anger was 0.462 (p<.001), indicating a moderate linear relationship between the two emotions. Fear was the highest from January to March in the first year of the COVID-19 outbreak, while anger occurred before and after the outbreak, with fluctuations in both emotions during this period. Conclusions This study confirmed that social cognitions and negative emotions are intertwined in response to major events related to the COVID-19 pandemic, with each emotion varying individually rather than being ambiguously mixed. These findings could aid in developing social cognition-emotion-based public health strategies through education and communication during future pandemic outbreaks. | W10: [Lee, Jae-Joon] Sookmyung Womens Univ, Sookmyung Res Inst Humanities, 100 Cheongparo 47 Gel, Seoul 04310, South Korea; [Kim, Jongwoo] Yonsei Univ, Dept Sociol, BK21Four Program, 3-101,84 Mapo-Daero 11 Gil, Seoul 04133, South Korea; [Lee, Soo-Kyoung] Seoul Natl Univ, Bigdata Convergence & Open Sharing Syst 1, Seoul 08826, South Korea | Y10: Lee, SK (corresponding author), Seoul Natl Univ, Bigdata Convergence & Open Sharing Syst 1, Seoul 08826, South Korea. | Z10: soo1005@snu.ac.kr | AG10: 54 | AH10: 3 | AI10: 3 | AT10: JUN 4 | AU10: 2024 | AV10: 24 | AW10: 1 | BD10: 1496 | BE10: 10.1186/s12889-024-19023-6 | BF10: =HYPERLINK("http://dx.doi.org/10.1186/s12889-024-19023-6","http://dx.doi.org/10.1186/s12889-024-19023-6") -> http://dx.doi.org/10.1186/s12889-024-19023-6 | BR10: 2026-05-29 | BS10: WOS:001320257300007 | BT10: =HYPERLINK("https%3A%2F%2Fwww.webofscience.com%2Fwos%2Fwoscc%2Ffull-record%2FWOS:001320257300007","View Full Record in Web of Science") -> View Full Record in Web of Science | BU10: =COUNTIF('오픈소스&직접수집'!F:F,'wos(corecollection)_260528'!BE10) -> 1 | BV10: =COUNTIF('오픈소스&직접수집'!A:A,'wos(corecollection)_260528'!I10) -> 1 | BW10: =SUM(BU10:BV10) -> 2
A11: netminer 검색 | B11: Shin, SH; Baek, OJ | F11: Shin, Sun-Hwa; Baek, On-Jeon | I11: A Study on Internet News for Patient Safety Campaigns: Focusing on Text Network Analysis and Topic Modeling | J11: HEALTHCARE | N11: Article | V11: Background/Objectives: This study aimed to identify the main issues related to public patient safety campaigns reflected in Korean online news. This study utilized a text-mining method to identify keywords and topics related to patient safety campaigns. Methods: The data collection period was from 1 January 2022 to 31 December 2023, and 4110 news articles were extracted. Through data preprocessing, 2661 duplicated news and 1213 unrelated news were removed, and 236 news were selected. Using the NetMiner program, keyword co-occurrence frequency calculation, keyword centrality analysis, and topic modeling analysis were performed. Results: The results showed that the most frequently mentioned keywords with high degree centrality, betweenness centrality, and closeness centrality in online news were hospital, medical, medicine, project, and treatment. The topics of online news related to the patient safety campaign were patient-centered care for medical safety, health promotion projects at a regional institution, hand hygiene education to prevent infection, healthcare quality improvement through the Mint Festival, and safe use of medicines. Conclusions: This study analyzed patient safety campaign news topics using text network analysis and topic modeling. It was confirmed that patient safety campaigns are essential for fostering a patient safety culture, improving medical quality, and encouraging patient participation in hospitals. Therefore, to build a safe medical environment, it is necessary to establish an effective patient safety campaign for not only medical staff providing medical care, but also patients and their caregivers, and for this, cooperation and participation from various professional occupations are necessary. | W11: [Shin, Sun-Hwa; Baek, On-Jeon] Sahmyook Univ, Coll Nursing, Nursing Dept, Seoul 01795, South Korea | Y11: Baek, OJ (corresponding author), Sahmyook Univ, Coll Nursing, Nursing Dept, Seoul 01795, South Korea. | Z11: shinsh@syu.ac.kr; perfectoj@naver.com | AG11: 56 | AH11: 2 | AI11: 2 | AT11: OCT | AU11: 2024 | AV11: 12 | AW11: 19 | BD11: 1914 | BE11: 10.3390/healthcare12191914 | BF11: =HYPERLINK("http://dx.doi.org/10.3390/healthcare12191914","http://dx.doi.org/10.3390/healthcare12191914") -> http://dx.doi.org/10.3390/healthcare12191914 | BR11: 2026-05-29 | BS11: WOS:001331936100001 | BT11: =HYPERLINK("https%3A%2F%2Fwww.webofscience.com%2Fwos%2Fwoscc%2Ffull-record%2FWOS:001331936100001","View Full Record in Web of Science") -> View Full Record in Web of Science | BU11: =COUNTIF('오픈소스&직접수집'!F:F,'wos(corecollection)_260528'!BE11) -> 0 | BV11: =COUNTIF('오픈소스&직접수집'!A:A,'wos(corecollection)_260528'!I11) -> 1 | BW11: =SUM(BU11:BV11) -> 1
A12: netminer 검색 | B12: Kim, J | F12: Kim, Jongwon | I12: Analysis of football research trends using text network analysis | J12: PLOS ONE | N12: Article | V12: This study was aimed to identify football research trends in various periods. A total of 30,946 football papers were collected from a representative academic database and search engine, the 'Web of Science'. Keyword refinement included filtering nouns, establishing synonyms and thesaurus, and excluding conjunctions, and the Cyram's Netminer 4.0 software was used for network analysis. A centrality analysis was conducted by extracting the words corresponding to the top 2% of the main research topics to obtain the degree and eigenvector centralities. The most frequently mentioned research keywords were injury, performance, and club. Keyword performance showed the highest degree centrality (0.294) and keyword world and cup showed the highest eigenvector centrality (0.710). The keyword with the highest eigenvector degree changed from injury in the 1990s and world in the 2000s to cup since the 2010s. Although various studies on football injuries have been conducted, research on the sport itself has recently been conducted. This study provides fundamental information on football trends from research published over the past 30 years. | W12: [Kim, Jongwon] Middlesex Univ, London Sport Inst, Sch Sci & Technol, London, England | Y12: Kim, J (corresponding author), Middlesex Univ, London Sport Inst, Sch Sci & Technol, London, England. | Z12: jongwonkim1229@gmail.com | AG12: 46 | AH12: 1 | AI12: 1 | AT12: APR 18 | AU12: 2024 | AV12: 19 | AW12: 4 | BD12: e0299782 | BE12: 10.1371/journal.pone.0299782 | BF12: =HYPERLINK("http://dx.doi.org/10.1371/journal.pone.0299782","http://dx.doi.org/10.1371/journal.pone.0299782") -> http://dx.doi.org/10.1371/journal.pone.0299782 | BR12: 2026-05-29 | BS12: WOS:001207320100096 | BT12: =HYPERLINK("https%3A%2F%2Fwww.webofscience.com%2Fwos%2Fwoscc%2Ffull-record%2FWOS:001207320100096","View Full Record in Web of Science") -> View Full Record in Web of Science | BU12: =COUNTIF('오픈소스&직접수집'!F:F,'wos(corecollection)_260528'!BE12) -> 1 | BV12: =COUNTIF('오픈소스&직접수집'!A:A,'wos(corecollection)_260528'!I12) -> 1 | BW12: =SUM(BU12:BV12) -> 2
A13: netminer 검색 | B13: Yuan, JF; Chen, KW; Li, W; Ji, C; Wang, ZR; Skibniewski, MJ | F13: Yuan, Jingfeng; Chen, Kaiwen; Li, Wei; Ji, Chuang; Wang, Zhiru; Skibniewski, Miroslaw J. | I13: Social network analysis for social risks of construction projects in high-density urban areas in China | J13: JOURNAL OF CLEANER PRODUCTION | N13: Article | V13: Social impacts have become increasingly important for urban development in China. In addition, unlike general construction projects, construction projects in high-density urban areas have high levels of complexity and uncertainty. Thus, from a network perspective, an improved social risk analysis theory and a method for these projects were generated in this paper. A case study involving 66 cases of social conflicts in construction projects in China was performed, and 16 social risk factors were summarized. Eight stakeholders related to these social risk factors were then identified based on a literature review and the case database. A theoretical model for social risk network analysis considering the interrelationships between stakeholders and risks was developed by using NetMiner, a social network analysis (SNA) tool. A 2-mode network and two 1-mode networks were used to analyze the relationships among the identified 16 social risk factors and 8 stakeholders. In terms of three-level challenges such as complex environments, the unreasonable behavior of individuals or organizations, and diversified interaction between behaviors and environments, the most important social risks of construction projects in high-density urban areas were explored to help the government implement effective social risk management measures. In addition, multiple, complicated relationships among residents, contractors, governmental authorities, and owners represented a major factor leading to social risk; therefore, more attention should be focused on this topic. The proposed social risk analysis method can increase the attention paid by project managers, governmental authorities, and project owners to social risk factors in high-density areas and provide a structured framework to analyze such social risks, as well as put forth possible solutions to reduce the social impacts on construction projects in high-density urban areas. (C) 2018 Elsevier Ltd. All rights reserved. | W13: [Yuan, Jingfeng] Southeast Univ, Dept Construct & Real Estate, Nanjing 210096, Jiangsu, Peoples R China; [Chen, Kaiwen] Virginia Polytech Inst & State Univ, Dept Bldg Construct, Blacksburg, VA 24061 USA; [Li, Wei] Southeast Univ, Sch Civil Engn, Dept Construct & Real Estate, Nanjing 210096, Jiangsu, Peoples R China; [Ji, Chuang] Longyuan Future City Investment & Management Co L, Investment Dev Dept, Shanghai 200072, Peoples R China; [Wang, Zhiru] Univ Sci & Technol Beijing, Coll Econ & Management, Beijing 100083, Peoples R China; [Skibniewski, Miroslaw J.] Univ Maryland, Dept Civil & Environm Engn, College Pk, MD 20742 USA; [Skibniewski, Miroslaw J.] Polish Acad Sci, Inst Theoret & Appl Informat, Gliwice, Poland; [Skibniewski, Miroslaw J.] Chaoyang Univ Technol, Taichung, Taiwan | Y13: Yuan, JF (corresponding author), Southeast Univ, Dept Construct & Real Estate, Nanjing 210096, Jiangsu, Peoples R China. | Z13: jingfeng-yuan@seu.edu.cn; kwchen16@vt.edu; leewei0842@163.com; ji.chuang@hotmail.com; wangzhiru@ustb.edu.cn; mirek@umd.edu | AG13: 78 | AH13: 125 | AI13: 141 | AT13: OCT 10 | AU13: 2018 | AV13: 198 | BB13: 940 | BC13: 961 | BE13: 10.1016/j.jclepro.2018.07.109 | BF13: =HYPERLINK("http://dx.doi.org/10.1016/j.jclepro.2018.07.109","http://dx.doi.org/10.1016/j.jclepro.2018.07.109") -> http://dx.doi.org/10.1016/j.jclepro.2018.07.109 | BR13: 2026-05-29 | BS13: WOS:000442973100082 | BT13: =HYPERLINK("https%3A%2F%2Fwww.webofscience.com%2Fwos%2Fwoscc%2Ffull-record%2FWOS:000442973100082","View Full Record in Web of Science") -> View Full Record in Web of Science | BU13: =COUNTIF('오픈소스&직접수집'!F:F,'wos(corecollection)_260528'!BE13) -> 0 | BV13: =COUNTIF('오픈소스&직접수집'!A:A,'wos(corecollection)_260528'!I13) -> 0 | BW13: =SUM(BU13:BV13) -> 0
A14: netminer 검색 | B14: Morashti, JA; An, Y; Jang, H | F14: Morashti, Jonathan Asher; An, Youra; Jang, Hyunmi | I14: A Systematic Literature Review of Sustainable Packaging in Supply Chain Management | J14: SUSTAINABILITY | N14: Article | V14: This exploratory study utilises quantitative analysis to deliver a systematic literature review of published journal papers from 1993 to 2020 with the aim to identify research trends and present a comprehensive overview of research focus conducted in the sustainable packaging domain within the scope of supply chain management. This research is conducted with the data mining software, NetMiner 4, utilising the three analytical tools of statistical analysis, keyword network analysis, and topic analysis. The research also utilises the qualitative method of in-depth interviews in order to investigate current trends and perspectives on the future of sustainable packaging and to validate the analysis results. The research findings reveal that research in the field of 'sustainable packaging in supply chain management' field has been extremely limited, and this study acts to address this research gap. The results confirm that the vast majority of research focus has been in the fields of engineering and science. Research on the topic has gained momentum and has significantly increased since 2013 with research trends becoming increasingly diversified and gradually aligned with the concept of circular economy, while the topic of operational management has been highlighted as an area requiring additional attention. The keyword frequency analysis reveals the following highest occurring keywords in TF: life cycle; environmental impact; consumer; transportation; and production. The highest occurring keywords in TF-IDF: production; transportation; consumer; food; and environmental impact. Topic modelling revealed the following six topics: consumer behaviour; environmental pollution; circular economy; waste management; resource conservation; and operational management. This study contributes to understanding past, present, and future research agendas, and can be utilised as foundation for research development, as it provides insight to current research status and trends provided by the keyword network analysis highlighting research focus and trends in 'sustainable packaging in supply chain management'. | W14: [Morashti, Jonathan Asher; An, Youra; Jang, Hyunmi] Pusan Natl Univ, Grad Sch Int Studies, Busan 46241, South Korea | Y14: Jang, H (corresponding author), Pusan Natl Univ, Grad Sch Int Studies, Busan 46241, South Korea. | Z14: jamorashti@pusan.ac.kr; youraan@pusan.ac.kr; jangh01@pusan.ac.kr | AG14: 61 | AH14: 36 | AI14: 41 | AT14: MAY | AU14: 2022 | AV14: 14 | AW14: 9 | BD14: 4921 | BE14: 10.3390/su14094921 | BF14: =HYPERLINK("http://dx.doi.org/10.3390/su14094921","http://dx.doi.org/10.3390/su14094921") -> http://dx.doi.org/10.3390/su14094921 | BR14: 2026-05-29 | BS14: WOS:000794598300001 | BT14: =HYPERLINK("https%3A%2F%2Fwww.webofscience.com%2Fwos%2Fwoscc%2Ffull-record%2FWOS:000794598300001","View Full Record in Web of Science") -> View Full Record in Web of Science | BU14: =COUNTIF('오픈소스&직접수집'!F:F,'wos(corecollection)_260528'!BE14) -> 1 | BV14: =COUNTIF('오픈소스&직접수집'!A:A,'wos(corecollection)_260528'!I14) -> 1 | BW14: =SUM(BU14:BV14) -> 2
A15: netminer 검색 | B15: Kim, D; Kim, S | F15: Kim, Dongwook; Kim, Sungbum | I15: The Role of Mobile Technology in Tourism: Patents, Articles, News, and Mobile Tour App Reviews | J15: SUSTAINABILITY | N15: Review | V15: The purpose of this research is to identify the status and role of mobile technology in achieving sustainable and smart tourism, and to suggest future research and strategy directions for academia and managers in practice. This research utilized multiple sources, such as patents, academic articles, and news, and selected methodologies optimized for the purpose of each study. Study 1 used Netminer, a social network analysis program, to analyze the relationships between patent's International Patent Classification (IPC) codes. Study 2 used the T-LAB program for content analysis to analyze the texts of patents, journal articles, and news. Study 3 used the Leximancer program, which utilizes relative frequency to analyze mobile app consumer reviews. In study 1, we identified various forms of data related technologies and mobile technologies for smart city systems and maps. In study 2, we found the environment, sustainability, business, and market themes to be related to mobile technology. In study 3, we explored consumers' attitudes and preferences for mobile travel app using their reviews. Advances in mobile technology are expected to create innovative experiences for consumers, foster a sustainable competitive advantage for tourism destinations and tourism-related suppliers, and create sustainable competencies for smart tourism. | W15: [Kim, Dongwook] Korea Adv Inst Sci & Technol, Grad Sch Innovat & Technol Management, Daejeon 305701, South Korea; [Kim, Sungbum] Kumoh Natl Inst Technol, Dept IT Convergence, Gumi 730701, Gyungbuk, South Korea | Y15: Kim, S (corresponding author), Kumoh Natl Inst Technol, Dept IT Convergence, Gumi 730701, Gyungbuk, South Korea. | Z15: heavenk1@kaist.ac.kr; it89@kumoh.ac.kr | AG15: 200 | AH15: 83 | AI15: 103 | AT15: NOV | AU15: 2017 | AV15: 9 | AW15: 11 | BD15: 2082 | BE15: 10.3390/su9112082 | BF15: =HYPERLINK("http://dx.doi.org/10.3390/su9112082","http://dx.doi.org/10.3390/su9112082") -> http://dx.doi.org/10.3390/su9112082 | BR15: 2026-05-29 | BS15: WOS:000416793400161 | BT15: =HYPERLINK("https%3A%2F%2Fwww.webofscience.com%2Fwos%2Fwoscc%2Ffull-record%2FWOS:000416793400161","View Full Record in Web of Science") -> View Full Record in Web of Science | BU15: =COUNTIF('오픈소스&직접수집'!F:F,'wos(corecollection)_260528'!BE15) -> 0 | BV15: =COUNTIF('오픈소스&직접수집'!A:A,'wos(corecollection)_260528'!I15) -> 0 | BW15: =SUM(BU15:BV15) -> 0
A16: netminer 검색 | B16: Seon, SH; Jeong, HW; Ju, D; Lee, JA; Ahn, SH | F16: Seon, Sun Hee; Jeong, Hye Won; Ju, Deok; Lee, Jung A. A.; Ahn, Shin Hye | I16: Capturing New Nurses' Experiences and Supporting Critical Thinking Text Network Analysis of Critical Reflective Journals | J16: CIN-COMPUTERS INFORMATICS NURSING | N16: Article | V16: This study analyzed the contents of critical reflective journals written by new nurses during their orientations using a text network. This study aimed to find ways to reduce turnover and improve clinical field adaptability among new nurses. The authors analyzed the content of reflective journals written by 143 new nurses from March 2020 to January 2021. Text network analysis was performed using the NetMiner 4.4.3 program. After data preprocessing, frequency of occurrence, degree centrality, closeness centrality, betweenness centrality, and eigenvector community were analyzed. In total, 453 words were extracted and refined, and words with high simple frequency and centrality were incompetence, preparation, explanation, injection, time, examination, and first try. Medication had the highest frequency of occurrence, and incompetence was the most important keyword in the centrality analysis. In addition, component analysis and eigenvector community analysis revealed three sub-theme groups: (1) basic nursing skills required for new nurses, (2) insufficient competency, and (3) explanation of nursing work. Significantly, this study is the first to use the text network method to analyze the subjective experiences of the critical reflective journals of new nurses. In conclusion, changes are needed to improve the education system for new nurses and promote efficient sharing of nursing tasks. | W16: [Seon, Sun Hee; Ju, Deok; Lee, Jung A. A.; Ahn, Shin Hye] Chonnam Natl Univ Hosp, Gwangju, South Korea; [Jeong, Hye Won] Chonnam Natl Univ, Chonnam Natl Univ Hosp, Gwangju, South Korea; [Jeong, Hye Won] Chonnam Nat Univ Hosp, Dept Nursing, 42 Jebong Ro, Gwangju 61469, South Korea; [Jeong, Hye Won] Chonnam Natl Univ, Coll Nursing, 160 Baekseo Ro, Gwangju 61469, South Korea | Y16: Jeong, HW (corresponding author), Chonnam Nat Univ Hosp, Dept Nursing, 42 Jebong Ro, Gwangju 61469, South Korea.;Jeong, HW (corresponding author), Chonnam Natl Univ, Coll Nursing, 160 Baekseo Ro, Gwangju 61469, South Korea. | Z16: seon00509@hanmail.net; y2k331646@gmail.com; juyulianna@hanmail.net; cuttylja@hanmail.net; chunyanggirl@naver.com | AG16: 40 | AH16: 6 | AI16: 7 | AT16: JUN | AU16: 2023 | AV16: 41 | AW16: 6 | BB16: 434 | BC16: 441 | BE16: 10.1097/CIN.0000000000000971 | BF16: =HYPERLINK("http://dx.doi.org/10.1097/CIN.0000000000000971","http://dx.doi.org/10.1097/CIN.0000000000000971") -> http://dx.doi.org/10.1097/CIN.0000000000000971 | BR16: 2026-05-29 | BS16: WOS:001000492200010 | BT16: =HYPERLINK("https%3A%2F%2Fwww.webofscience.com%2Fwos%2Fwoscc%2Ffull-record%2FWOS:001000492200010","View Full Record in Web of Science") -> View Full Record in Web of Science | BU16: =COUNTIF('오픈소스&직접수집'!F:F,'wos(corecollection)_260528'!BE16) -> 1 | BV16: =COUNTIF('오픈소스&직접수집'!A:A,'wos(corecollection)_260528'!I16) -> 1 | BW16: =SUM(BU16:BV16) -> 2
A17: netminer 검색 | B17: Kim, MS | F17: Kim, Mee Sook | I17: Topics model of overwork-related deaths in Korea and the implications of SDGs' decent work perspective | J17: SAFETY SCIENCE | N17: Article | V17: Objective: Through a text network analysis, this study examined major issues related to death from overwork reported in Korean media over the past ten years, focusing on essential workers, and examined the implications for Korean society from the perspective of decent work as described by the Sustainable Development Goals (SDGs). Methods: We retrieved 1,340 news articles from 52 media companies by searching for death from overwork as a keyword using the Big Kinds database operated by the Korea Press Foundation. A total of 4,627 nouns were extracted from news articles, and four topics were found by performing topic modeling using the NetMiner 4 program. We also examined the trend of topic ratios by year. Results: Between 2012 and 2015, 22-36 news articles were reported annually, and Topic 2 (recognition of death from overwork of public officials) was the most common. Between 2016 and 2019, 72-162 news articles were reported annually, and Topic 1 (postal workers' extended working hours) was the most common. Between 2020 and 2021, 314-441 news articles were reported annually, and Topic 3 (measures against industrial accidents of courier workers) and Topic 4 (courier sorting and labor union consensus) were the most common. Conclusion: In Korea, postal workers, public officials, and courier workers are vulnerable to death from overwork. This can be resolved by considerably reducing working hours, recognizing industrial accidents, and improving the working environment. From the perspective of the United Nations Development Programme (UNDP) SDGs' decent work concept, to sustain workers' health and well-being, the State and companies should guarantee workers healthy working hours, choice of working hours, guarantee of decent and productive work, and maximum working hours cap system. The labor system and workplace culture should be improved to guarantee workers' health and well-being. | W17: [Kim, Mee Sook] Catholic Kkottongnae Univ, Dept Liberal Arts, 33 Sangsam gil, Cheongju Shi 28211, South Korea | Y17: Kim, MS (corresponding author), Catholic Kkottongnae Univ, Dept Liberal Arts, 33 Sangsam gil, Cheongju Shi 28211, South Korea. | Z17: mskjeon@kkot.ac.kr | AG17: 39 | AH17: 6 | AI17: 7 | AT17: OCT | AU17: 2023 | AV17: 166 | BD17: 106239 | BE17: 10.1016/j.ssci.2023.106239 | BF17: =HYPERLINK("http://dx.doi.org/10.1016/j.ssci.2023.106239","http://dx.doi.org/10.1016/j.ssci.2023.106239") -> http://dx.doi.org/10.1016/j.ssci.2023.106239 | BH17: JUN 2023 | BR17: 2026-05-29 | BS17: WOS:001030993100001 | BT17: =HYPERLINK("https%3A%2F%2Fwww.webofscience.com%2Fwos%2Fwoscc%2Ffull-record%2FWOS:001030993100001","View Full Record in Web of Science") -> View Full Record in Web of Science | BU17: =COUNTIF('오픈소스&직접수집'!F:F,'wos(corecollection)_260528'!BE17) -> 0 | BV17: =COUNTIF('오픈소스&직접수집'!A:A,'wos(corecollection)_260528'!I17) -> 1 | BW17: =SUM(BU17:BV17) -> 1
A18: netminer 검색 | B18: Lin, X; Ho, CMF; Shen, GQP | F18: Lin, Xue; Ho, Christabel M. F.; Shen, Geoffrey Q. P. | I18: Who should take the responsibility? Stakeholders' power over social responsibility issues in construction projects | J18: JOURNAL OF CLEANER PRODUCTION | N18: Article | V18: Construction projects involve multiple stakeholders with different abilities that enable them to deal with the social problems that arise during the project lifecycle. This research aims to study the dynamic stakeholder power in implementing social responsibility issues in construction projects. Empirical research among Hong Kong construction industry practitioners was conducted to investigate the powers of seven stakeholders over thirty-five social responsibility issues. The data was analyzed using two-mode social network analysis methods and processed by Netminer 4. It was found from the results that internal and external stakeholders have control in different domains pertaining to social responsibility issues, but it does not mean either group has superior power. Ranked by the power status on social responsibility issues, the seven stakeholders are classified into five hierarchies: 1) governments, developers, and main contractors; 2) district councils, 3) consultants; 4) non-government organizations; 5) end users. The dynamic nature of stakeholders' powers has been elucidated by describing the power changes in different project stages, as well as in different social responsibility dimensions. (C) 2017 Elsevier Ltd. All rights reserved. | W18: [Lin, Xue; Ho, Christabel M. F.; Shen, Geoffrey Q. P.] Hong Kong Polytech Univ, Dept Bldg & Real Estate, Hong Kong, Hong Kong, Peoples R China | Y18: Lin, X (corresponding author), Hong Kong Polytech Univ, Dept Bldg & Real Estate, Hong Kong, Hong Kong, Peoples R China. | Z18: xue.lin@connect.polyu.hk; man.fong.ho@polyu.edu.hk; geoffrey.shen@polyu.edu.hk | AG18: 69 | AH18: 73 | AI18: 82 | AT18: JUN 15 | AU18: 2017 | AV18: 154 | BB18: 318 | BC18: 329 | BE18: 10.1016/j.jclepro.2017.04.007 | BF18: =HYPERLINK("http://dx.doi.org/10.1016/j.jclepro.2017.04.007","http://dx.doi.org/10.1016/j.jclepro.2017.04.007") -> http://dx.doi.org/10.1016/j.jclepro.2017.04.007 | BR18: 2026-05-29 | BS18: WOS:000401201900031 | BT18: =HYPERLINK("https%3A%2F%2Fwww.webofscience.com%2Fwos%2Fwoscc%2Ffull-record%2FWOS:000401201900031","View Full Record in Web of Science") -> View Full Record in Web of Science | BU18: =COUNTIF('오픈소스&직접수집'!F:F,'wos(corecollection)_260528'!BE18) -> 0 | BV18: =COUNTIF('오픈소스&직접수집'!A:A,'wos(corecollection)_260528'!I18) -> 0 | BW18: =SUM(BU18:BV18) -> 0
A19: netminer 검색 | B19: Song, MK; Moon, JE; Jang, A | F19: Song, Miok; Moon, Jeong Eun; Jang, Aeri | I19: Text Network Analysis of Research Topics and Trends on Simulations Using Virtual Patients in Nursing Education | J19: CIN-COMPUTERS INFORMATICS NURSING | N19: Article | V19: Simulations using virtual patients have been utilized as an effective method in nursing education. However, keyword network analyses and topic modeling on simulations using virtual patients in nursing education have not yet been performed. In this study, 213 articles were retrieved from online research article databases. Abstracts from these articles were extracted, and network analysis was conducted using NetMiner version 4.3 (Cyram Inc, Seongnam, South Korea). Based on the study's analysis, scenario, communication, system, assessment, person, disaster, and management were identified as the keywords with high centrality values. Therefore, they were determined to be influential in the network. After topic modeling, 10 topics were derived as dementia care competency, pain assessment, airway placement management, operating procedure, presence and satisfaction, communication and attitude improvement, platform world, disaster response, game and video usability, and system for confidence. The identified trends in this study will help grasp the trends and insight to guide future research directions on simulations using virtual patients in nursing education. | W19: [Song, Miok; Jang, Aeri] Honam Univ, Dept Nursing, Gwangju, South Korea; [Moon, Jeong Eun] Honam Univ, Dept Nursing, 120 Honamdae Gil, Gwangju 62399, South Korea | Y19: Moon, JE (corresponding author), Honam Univ, Dept Nursing, 120 Honamdae Gil, Gwangju 62399, South Korea. | Z19: coffeesong79@gmail.com; moonjohan@gmail.com; sseillerjjang79@gmail.com | AG19: 37 | AH19: 2 | AI19: 2 | AT19: SEP | AU19: 2023 | AV19: 41 | AW19: 9 | BB19: 639 | BC19: 646 | BE19: 10.1097/CIN.0000000000000993 | BF19: =HYPERLINK("http://dx.doi.org/10.1097/CIN.0000000000000993","http://dx.doi.org/10.1097/CIN.0000000000000993") -> http://dx.doi.org/10.1097/CIN.0000000000000993 | BR19: 2026-05-29 | BS19: WOS:001064261000003 | BT19: =HYPERLINK("https%3A%2F%2Fwww.webofscience.com%2Fwos%2Fwoscc%2Ffull-record%2FWOS:001064261000003","View Full Record in Web of Science") -> View Full Record in Web of Science | BU19: =COUNTIF('오픈소스&직접수집'!F:F,'wos(corecollection)_260528'!BE19) -> 1 | BV19: =COUNTIF('오픈소스&직접수집'!A:A,'wos(corecollection)_260528'!I19) -> 1 | BW19: =SUM(BU19:BV19) -> 2
A20: netminer 검색 | B20: Ahn, SH; Jeong, HW | F20: Ahn, Shin Hye; Jeong, Hye Won | I20: Content Analysis of Feedback Journals for New Nurses From Preceptor Nurses Using Text Network Analysis | J20: CIN-COMPUTERS INFORMATICS NURSING | N20: Article | V20: This study aimed to identify keywords, core topic areas, and subthemes by analyzing feedback journals written by preceptor nurses to new nurses during the preceptorship period and to derive implications through word clustering. A total of 143 preceptor nurses' feedback journals for new nurses from March 2020 to January 2021 were converted into a database using Microsoft Office Excel. Text network analysis was performed using the NetMiner 4.4.3 program. After data preprocessing, simple frequency, degree centrality, closeness centrality, betweenness centrality, and community modularity were analyzed. In the feedback journals, the most central words were study, medication, practice, nursing, method, need, and effort, whereas frustration, new nurses had low centrality. Five subthemes were derived: (1) learning necessity to strengthen new nurses' competency, (2) independence of new nurses, (3) emphasis on accuracy in nursing skills, (4) difficulties in understanding the nursing tasks expected of new nurses, and (5) basic competency of new nurses. The results of this study highlighted the experiences of new nurses and allowed for an assessment of journal feedback content provided by preceptor nurses. As such, the study provides basic data to develop a standardized education and competency empowerment program for preceptor nurses. | W20: [Ahn, Shin Hye; Jeong, Hye Won] Chonnam Natl Univ Hosp, Dept Nursing, Gwangju, South Korea; [Ahn, Shin Hye; Jeong, Hye Won] Chonnam Natl Univ, Coll Nursing, Gwangju, South Korea; [Jeong, Hye Won] Chonnam Natl Univ Hosp, Dept Nursing, 42 Jebong Ro, Gwangju 61469, South Korea; [Jeong, Hye Won] Chonnam Natl Univ, Coll Nursing, 160 Baekseo Ro, Gwangju 61469, South Korea | Y20: Jeong, HW (corresponding author), Chonnam Natl Univ Hosp, Dept Nursing, 42 Jebong Ro, Gwangju 61469, South Korea.;Jeong, HW (corresponding author), Chonnam Natl Univ, Coll Nursing, 160 Baekseo Ro, Gwangju 61469, South Korea. | Z20: chunyanggirl@naver.com; y2k331646@gmail.com | AG20: 40 | AH20: 2 | AI20: 4 | AT20: OCT | AU20: 2023 | AV20: 41 | AW20: 10 | BB20: 780 | BC20: 788 | BE20: 10.1097/CIN.0000000000001040 | BF20: =HYPERLINK("http://dx.doi.org/10.1097/CIN.0000000000001040","http://dx.doi.org/10.1097/CIN.0000000000001040") -> http://dx.doi.org/10.1097/CIN.0000000000001040 | BR20: 2026-05-29 | BS20: WOS:001085260500007 | BT20: =HYPERLINK("https%3A%2F%2Fwww.webofscience.com%2Fwos%2Fwoscc%2Ffull-record%2FWOS:001085260500007","View Full Record in Web of Science") -> View Full Record in Web of Science | BU20: =COUNTIF('오픈소스&직접수집'!F:F,'wos(corecollection)_260528'!BE20) -> 1 | BV20: =COUNTIF('오픈소스&직접수집'!A:A,'wos(corecollection)_260528'!I20) -> 1 | BW20: =SUM(BU20:BV20) -> 2
A21: netminer 검색 | B21: Ha, JY; Park, HJ | F21: Ha, Ju-Young; Park, Hyo-Jin | I21: Keyword Network Analysis and Topic Modeling of News Articles Related to Artificial Intelligence and Nursing br | J21: JOURNAL OF KOREAN ACADEMY OF NURSING | N21: Article | V21: Purpose: The purpose of this study was to identify the main keywords, network properties, and main topics of news articles related to arti-ficial intelligence technology in the field of nursing.Methods: After collecting artificial intelligence-and nursing-related news articles pub-lished between January 1, 1991, and July 24, 2022, keywords were extracted via preprocessing. A total of 3,267 articles were searched, and 2,996 were used for the final analysis. Text network analysis and topic modeling were performed using NetMiner 4.4.Results: As a result of analyzing the frequency of appearance, the keywords used most frequently were education, medical robot, telecom, dementia, and the older adults living alone. Keyword network analysis revealed the following results: a density of 0.002, an average degree of 8.79, and an average distance of 2.43; the central keywords identified were 'education,' 'medical robot,' and 'fourth industry.' Five topics were derived from news articles related to artificial intelligence and nursing: 'Artificial intelligence nursing research and development in the health and medical field,' 'Education using artificial intelligence for children and youth care,' 'Nursing robot for older adults care,' 'Community care policy and artificial intelligence,' and 'Smart care technology in an aging society.'Conclusion: The use of artificial intelligence may be help-ful among the local community, older adult, children, and adolescents. In particular, health management using artificial intelligence is indis-pensable now that we are facing a super-aging society. In the future, studies on nursing intervention and development of nursing programs using artificial intelligence should be conducted | W21: [Ha, Ju-Young; Park, Hyo-Jin] Pusan Natl Univ, Coll Nursing, 49 Busandaehak Ro, Yangsan 50612, South Korea | Y21: Park, HJ (corresponding author), Pusan Natl Univ, Coll Nursing, 49 Busandaehak Ro, Yangsan 50612, South Korea. | Z21: hyojin@pusan.ac.kr | AG21: 50 | AH21: 2 | AI21: 3 | AT21: FEB | AU21: 2023 | AV21: 53 | AW21: 1 | BD21: 55 | BE21: 10.4040/jkan.22117 | BF21: =HYPERLINK("http://dx.doi.org/10.4040/jkan.22117","http://dx.doi.org/10.4040/jkan.22117") -> http://dx.doi.org/10.4040/jkan.22117 | BR21: 2026-05-29 | BS21: WOS:000941874100005 | BT21: =HYPERLINK("https%3A%2F%2Fwww.webofscience.com%2Fwos%2Fwoscc%2Ffull-record%2FWOS:000941874100005","View Full Record in Web of Science") -> View Full Record in Web of Science | BU21: =COUNTIF('오픈소스&직접수집'!F:F,'wos(corecollection)_260528'!BE21) -> 1 | BV21: =COUNTIF('오픈소스&직접수집'!A:A,'wos(corecollection)_260528'!I21) -> 1 | BW21: =SUM(BU21:BV21) -> 2
A22: netminer 검색 | B22: Ko, HYJ; Jeong, SH; Lee, EJ; Kim, HS | F22: Ko, Hyunjung; Jeong, Seok Hee; Lee, Eun Jee; Kim, Hee Sun | I22: National Petition Analysis Related to Nursing: Text Network Analysis and Topic Modeling | J22: JOURNAL OF KOREAN ACADEMY OF NURSING | N22: Article | V22: Purpose: This study aimed to identify the main keyword, network structure, and main topics of the national petition related to nursing in South Korea. Methods: Data were gathered from petitions related to the national petition in Korea Blue House related to the topic nursing or nurse from August 17, 2017, to May 9, 2022. A total of 5,154 petitions were searched, and 995 were selected for the final analysis. Text network analysis and topic modeling were analyzed using the Netminer 4.5.0 program. Results: Regarding network charac-teristics, a density of 0.03, an average degree of 144.483, and an average distance of 1.943 were found. Compared to results of degree centrality and betweenness centrality, keywords such as work environment, nursing university, license, and education appeared typically in the eigenvector centrality analysis. Topic modeling derived four topics: (1) Improving the working environment and dealing with nursing professionals, (2) requesting investigation and punishment related to medical accidents, (3) requiring clear role regula-tion and legislation of medical and nonmedical professions, and (4) demanding improvement of healthcare-related systems and ser-vices. Conclusion: This is the first study to analyze Korea's national petitions in the field of nursing. This study's results confirmed both the internal needs and external demands for nurses in South Korea. Policies and laws that reflect these results should be developed. | W22: [Ko, Hyunjung] Jeonbuk Natl Univ, Grad Sch, Dept Nursing, Jeonju, South Korea; [Jeong, Seok Hee; Lee, Eun Jee; Kim, Hee Sun] Jeonbuk Natl Univ, Coll Nursing, Res Inst Nursing Sci, Jeonju, South Korea; [Ko, Hyunjung] Jeonbuk Natl Univ Hosp, Dept Nursing, Jeonju, South Korea; [Jeong, Seok Hee] Jeonbuk Natl Univ, Coll Nursing, Res Inst Nursing Sci, 567 Baekje Daero, Jeonju 54896, South Korea | Y22: Jeong, SH (corresponding author), Jeonbuk Natl Univ, Coll Nursing, Res Inst Nursing Sci, 567 Baekje Daero, Jeonju 54896, South Korea. | Z22: awesomeprof@jbnu.ac.kr | AG22: 50 | AH22: 1 | AI22: 1 | AT22: DEC | AU22: 2023 | AV22: 53 | AW22: 6 | BB22: 635 | BC22: 651 | BE22: 10.4040/jkan.23052 | BF22: =HYPERLINK("http://dx.doi.org/10.4040/jkan.23052","http://dx.doi.org/10.4040/jkan.23052") -> http://dx.doi.org/10.4040/jkan.23052 | BR22: 2026-05-29 | BS22: WOS:001143408800002 | BT22: =HYPERLINK("https%3A%2F%2Fwww.webofscience.com%2Fwos%2Fwoscc%2Ffull-record%2FWOS:001143408800002","View Full Record in Web of Science") -> View Full Record in Web of Science | BU22: =COUNTIF('오픈소스&직접수집'!F:F,'wos(corecollection)_260528'!BE22) -> 1 | BV22: =COUNTIF('오픈소스&직접수집'!A:A,'wos(corecollection)_260528'!I22) -> 1 | BW22: =SUM(BU22:BV22) -> 2
A23: netminer 검색 | B23: Park, J; Han, AY | F23: Park, Jinkyung; Han, A. Young | I23: Medication safety education in nursing research: Text network analysis and topic modeling | J23: NURSE EDUCATION TODAY | N23: Review | V23: Objectives: This study aimed to identify the knowledge structure of medication safety nursing education literature by developing schematic diagrams of the relationship between keywords from a macro perspective. This study also identifies the research topics and trends over time.Design: This quantitative content study used text network analysis to explore keywords and research topics using topic modeling within the medication safety nursing education literature. Data sources: PubMed, EMBASE, and Cochrane databases were used to search for the medication safety nursing education literature published until December 2021.Methods: Keywords from 2085 articles were examined using text network analysis and topic modeling with NetMiner 4.4.3.Results: The keywords with the most frequency and the highest networking degree in centrality were patient, medication, program, nurse, and care. The emerging keywords assessed by time periods were identified; the first phase (heart failure, insulin, chemotherapy, and infusion), the second phase (medication er-rors, staff, and information), the third phase (program, management, and data). The results of topic modeling were as follows: safe medication administration, safe medication reconciliation process, medication education for patients, medication errors in nursing practice, and multidisciplinary teamwork for medication safety.Conclusion: These findings will help nursing researchers and educators to understand the trends and insights for medication safety education and educate future nurses to provide safer nursing care. | W23: [Park, Jinkyung] Chonnam Natl Univ, Coll Nursing, 160 Baekseo Ro, Gwangju 61469, South Korea; [Han, A. Young] Sunchon Natl Univ, Coll Life Sci & Ind, Dept Nursing, 255 Jungang Ro, Suncheon Si 57922, Jeollanam Do, South Korea | Y23: Han, AY (corresponding author), Sunchon Natl Univ, Coll Life Sci & Ind, Dept Nursing, 255 Jungang Ro, Suncheon Si 57922, Jeollanam Do, South Korea. | Z23: ayounghan@scnu.ac.kr | AG23: 92 | AH23: 10 | AI23: 13 | AT23: FEB | AU23: 2023 | AV23: 121 | BD23: 105674 | BE23: 10.1016/j.nedt.2022.105674 | BF23: =HYPERLINK("http://dx.doi.org/10.1016/j.nedt.2022.105674","http://dx.doi.org/10.1016/j.nedt.2022.105674") -> http://dx.doi.org/10.1016/j.nedt.2022.105674 | BH23: DEC 2022 | BR23: 2026-05-29 | BS23: WOS:000902005400020 | BT23: =HYPERLINK("https%3A%2F%2Fwww.webofscience.com%2Fwos%2Fwoscc%2Ffull-record%2FWOS:000902005400020","View Full Record in Web of Science") -> View Full Record in Web of Science | BU23: =COUNTIF('오픈소스&직접수집'!F:F,'wos(corecollection)_260528'!BE23) -> 1 | BV23: =COUNTIF('오픈소스&직접수집'!A:A,'wos(corecollection)_260528'!I23) -> 1 | BW23: =SUM(BU23:BV23) -> 2
A24: netminer 검색 | B24: Park, Y; Park, S; Lee, MJ | F24: Park, Yoonseo; Park, Sewon; Lee, Munjae | I24: Digital Health Care Industry Ecosystem: Network Analysis | J24: JOURNAL OF MEDICAL INTERNET RESEARCH | N24: Article | V24: Background: As the need for digital health care based on mobile devices is increasing, with the rapid development of digital technologies, especially in the face of the COVID-19 pandemic, gaining a better understanding of the industrial structure is needed to activate the use of digital health care. Objective: The aim of this study was to suggest measures to revitalize the digital health care industry by deriving the stakeholders and major issues with respect to the ecosystem of the industry. Methods: A total of 1822 newspaper articles were collected using Big Kings, a big data system for news, for a limited period from 2016 to August 2021, when the mobile health care project was promoted in Korea centered on public health centers. The R and NetMiner programs were used for network analysis. Results: The Korean government and the Ministry of Health and Welfare showed the highest centrality and appeared as major stakeholders, and their common major issues were reviewing the introduction of telemedicine, concerns about bankruptcy of local clinics, and building an integrated platform for precision medicine. In addition, the major stakeholders of medical institutions and companies were Seoul National University Hospital, Kangbuk Samsung Hospital, Ajou University Hospital, Samsung, and Vuno Inc. Conclusions: This analysis confirmed that the issues related to digital health care are largely composed of telemedicine, data, and health care business. For digital health care to develop as a national innovative growth engine and to be institutionalized, the development of a digital health care fee model that can improve the regulatory system and the cost-effectiveness of patient care, centering on the Ministry of Health and Welfare as a key stakeholder, is essential. | W24: [Park, Yoonseo] Ajou Univ, Dept BioMed Engn, Suwon, South Korea; [Park, Sewon; Lee, Munjae] Ajou Univ, Dept Med Humanities & Social Med, Sch Med, Suwon, South Korea; [Lee, Munjae] Ajou Univ, Sch Med, Dept Med Humanities & Social Med, 206 World Cup Ro, Suwon 16499, Gyeonggi Do, South Korea | Y24: Lee, MJ (corresponding author), Ajou Univ, Sch Med, Dept Med Humanities & Social Med, 206 World Cup Ro, Suwon 16499, Gyeonggi Do, South Korea. | Z24: emunjae@ajou.ac.kr | AG24: 40 | AH24: 12 | AI24: 14 | AT24: AUG 22 | AU24: 2022 | AV24: 24 | AW24: 8 | BD24: e37622 | BE24: 10.2196/37622 | BF24: =HYPERLINK("http://dx.doi.org/10.2196/37622","http://dx.doi.org/10.2196/37622") -> http://dx.doi.org/10.2196/37622 | BR24: 2026-05-29 | BS24: WOS:000862887700019 | BT24: =HYPERLINK("https%3A%2F%2Fwww.webofscience.com%2Fwos%2Fwoscc%2Ffull-record%2FWOS:000862887700019","View Full Record in Web of Science") -> View Full Record in Web of Science | BU24: =COUNTIF('오픈소스&직접수집'!F:F,'wos(corecollection)_260528'!BE24) -> 1 | BV24: =COUNTIF('오픈소스&직접수집'!A:A,'wos(corecollection)_260528'!I24) -> 1 | BW24: =SUM(BU24:BV24) -> 2
A25: netminer 검색 | B25: Park, MY; Jeong, SH; Kim, HS; Lee, EJ | F25: Park, Min Young; Jeong, Seok Hee; Kim, Hee Sun; Lee, Eun Jee | I25: Images of Nurses Appeared in Media Reports Before and After Outbreak of COVID-19: Text Network Analysis and Topic Modeling | J25: JOURNAL OF KOREAN ACADEMY OF NURSING | N25: Article; Proceedings Paper | O25: Yonsei International Nursing Conference | P25: NOV, 2021 | Q25: Seoul, SOUTH KOREA | V25: Purpose: The aims of study were to identify the main keywords, the network structure, and the main topics of press articles related to nurses that have appeared in media reports. Methods: Data were media articles related to the topic nurse reported in 16 central media within a one-year period spanning July 1, 2019 to June 30, 2020. Data were collected from the Big Kinds database. A total of 7,800 articles were searched, and 1,038 were used for the final analysis. Text network analysis and topic modeling were performed using NetMiner 4.4. Results: The number of media reports related to nurses increased by 3.86 times after the novel coronavirus (COVID-19) outbreak compared to prior. Pre- and post-COVID-19 network characteristics were density 0.002, 0.001; average degree 4.63, 4.92; and average distance 4.25, 4.01, respectively. Four topics were derived before and after the COVID-19 outbreak, respectively. Pre-COVID-19 example topics are a nurse who committed suicide because she could not withstand the Taewoom at work and a nurse as a perpetrator of a newborn abuse case, while post-COVID-19 examples are a nurse as a victim of COVID-19, a nurse working with the support of the people, and a nurse as a top contributor and a warrior to protect from COVID-19. Conclusion: Topic modeling shows that topics become more positive after the COVID-19 outbreak. Individual nurses and nursing organizations should continuously monitor and conduct further research on nurses' image. | W25: [Park, Min Young] Jeonbuk Natl Univ Hosp, Dept Nursing, Jeonju, South Korea; [Jeong, Seok Hee; Kim, Hee Sun; Lee, Eun Jee] Jeonbuk Natl Univ, Res Inst Nursing Sci, Coll Nursing, 567 Baekje Daero, Jeonju 54896, South Korea | Y25: Jeong, SH (corresponding author), Jeonbuk Natl Univ, Res Inst Nursing Sci, Coll Nursing, 567 Baekje Daero, Jeonju 54896, South Korea. | Z25: awesomeprof@jbnu.ac.kr | AG25: 53 | AH25: 11 | AI25: 15 | AT25: JUN | AU25: 2022 | AV25: 52 | AW25: 3 | BB25: 291 | BC25: 307 | BE25: 10.4040/jkan.22002 | BF25: =HYPERLINK("http://dx.doi.org/10.4040/jkan.22002","http://dx.doi.org/10.4040/jkan.22002") -> http://dx.doi.org/10.4040/jkan.22002 | BR25: 2026-05-29 | BS25: WOS:000819133000004 | BT25: =HYPERLINK("https%3A%2F%2Fwww.webofscience.com%2Fwos%2Fwoscc%2Ffull-record%2FWOS:000819133000004","View Full Record in Web of Science") -> View Full Record in Web of Science | BU25: =COUNTIF('오픈소스&직접수집'!F:F,'wos(corecollection)_260528'!BE25) -> 1 | BV25: =COUNTIF('오픈소스&직접수집'!A:A,'wos(corecollection)_260528'!I25) -> 0 | BW25: =SUM(BU25:BV25) -> 1
A26: netminer 검색 | B26: Lee, JL; Kim, Y | F26: Lee, Jung Lim; Kim, Youngji | I26: Research Topic Trends on Turnover Intention among Korean Registered Nurses: An Analysis Using Topic Modeling | J26: HEALTHCARE | N26: Article | V26: This study aimed to explore research topic trends on turnover intention among Korean hospital nurses by analyzing the keywords and topics of related articles. Methods: This text-mining study collected, processed, and analyzed text data from 390 nursing articles published between 1 January 2010 and 30 June 2021 that were collected via search engines. The collected unstructured text data were preprocessed, and the NetMiner program was used to perform keyword analysis and topic modeling. Results: The word with the highest degree centrality was job satisfaction, the word with the highest betweenness centrality was job satisfaction, and the word with the highest closeness centrality and frequency was job stress. The top 10 keywords in both the frequency analysis and the 3 centrality analyses included job stress, burnout, organizational commitment, emotional labor, job, and job embeddedness. The 676 preprocessed key words were categorized into five topics: job, burnout, workplace bullying, job stress, and emotional labor. Since many individual-level factors have already been thoroughly investigated, future research should concentrate on enabling successful organizational interventions that extend beyond the microsystem. | W26: [Lee, Jung Lim] Daejeon Univ, Dept Nursing, Daejeon Si 34520, South Korea; [Kim, Youngji] Kongju Natl Univ, Coll Nursing & Hlth, Dept Nursing, Kongju Si 32588, South Korea | Y26: Kim, Y (corresponding author), Kongju Natl Univ, Coll Nursing & Hlth, Dept Nursing, Kongju Si 32588, South Korea. | Z26: leejl@dju.kr; superdr1@hanmail.net | AG26: 29 | AH26: 0 | AI26: 0 | AT26: APR | AU26: 2023 | AV26: 11 | AW26: 8 | BD26: 1139 | BE26: 10.3390/healthcare11081139 | BF26: =HYPERLINK("http://dx.doi.org/10.3390/healthcare11081139","http://dx.doi.org/10.3390/healthcare11081139") -> http://dx.doi.org/10.3390/healthcare11081139 | BR26: 2026-05-29 | BS26: WOS:000984042800001 | BT26: =HYPERLINK("https%3A%2F%2Fwww.webofscience.com%2Fwos%2Fwoscc%2Ffull-record%2FWOS:000984042800001","View Full Record in Web of Science") -> View Full Record in Web of Science | BU26: =COUNTIF('오픈소스&직접수집'!F:F,'wos(corecollection)_260528'!BE26) -> 1 | BV26: =COUNTIF('오픈소스&직접수집'!A:A,'wos(corecollection)_260528'!I26) -> 1 | BW26: =SUM(BU26:BV26) -> 2
A27: netminer 검색 | B27: Jeon, BJ; Park, KH | F27: Jeon, Byoung-Jin; Park, Kang-Hyun | I27: The Impact of Social Network Characteristics on Health among Community-Dwelling Older Adults in Korea: Application of Social Network Analysis | J27: INTERNATIONAL JOURNAL OF ENVIRONMENTAL RESEARCH AND PUBLIC HEALTH | N27: Article | V27: Objectives: Population aging is a reality in most developed countries. In this era, an important health issue for these countries is promoting health and quality of life in the elderly population. Older adults' social networks are associated with health and quality of life. Therefore, this study examines the association between the characteristics of social networks (friendship networks) and the subjective well-being of community-dwelling older adults. Methods: This study was conducted between June 2015 and August 2015 with a total of 146 participants. The size and density of social networks were analyzed using social network analysis. Additionally, to investigate the impact of social networks on health, a multiple linear regression analysis was performed using NetMiner 4.0. Statistical significance was set at p < 0.05. Results: In terms of Model 1, which used social network characteristics as variables, the higher the out-degree (376.161) and in-closeness (201.825), the better the health. In contrast, the higher the in-degree (-279.167) and out-closeness (-52.620), the poorer the health. Regarding Model 2, which used sociodemographic characteristics as variables, the higher the out-degree (218.747) and in-closeness (170.075), the better the health. In addition, religion had a negative effect on health, and a high level of education had a positive effect on health. Conclusions: The findings suggest that higher out-degree and in-closeness intensity positively affect the health of older adults, but higher in-degree and out-closeness intensity negatively affect health. Therefore, health professionals should use appropriate strategies to increase the strength of social networks to improve the health of older adults living in the community. | W27: [Jeon, Byoung-Jin] Kangwon Natl Univ, Dept Occupat Therapy, Samcheok Si 25947, South Korea; [Park, Kang-Hyun] Baekseok Univ, Dept Occupat Therapy, Cheonan Si 31065, South Korea | Y27: Park, KH (corresponding author), Baekseok Univ, Dept Occupat Therapy, Cheonan Si 31065, South Korea. | Z27: nomadot@daum.net; kanghyun@bu.ac.kr | AG27: 52 | AH27: 5 | AI27: 7 | AT27: APR | AU27: 2022 | AV27: 19 | AW27: 7 | BD27: 4013 | BE27: 10.3390/ijerph19074013 | BF27: =HYPERLINK("http://dx.doi.org/10.3390/ijerph19074013","http://dx.doi.org/10.3390/ijerph19074013") -> http://dx.doi.org/10.3390/ijerph19074013 | BR27: 2026-05-29 | BS27: WOS:000780609700001 | BT27: =HYPERLINK("https%3A%2F%2Fwww.webofscience.com%2Fwos%2Fwoscc%2Ffull-record%2FWOS:000780609700001","View Full Record in Web of Science") -> View Full Record in Web of Science | BU27: =COUNTIF('오픈소스&직접수집'!F:F,'wos(corecollection)_260528'!BE27) -> 1 | BV27: =COUNTIF('오픈소스&직접수집'!A:A,'wos(corecollection)_260528'!I27) -> 1 | BW27: =SUM(BU27:BV27) -> 2
A28: netminer 검색 | B28: Ko, J; Paek, S; Park, S; Park, J | F28: Ko, Jangwan; Paek, Seungsu; Park, Seoyoon; Park, Jiwoo | I28: A News Big Data Analysis of Issues in Higher Education in Korea amid the COVID-19 Pandemic | J28: SUSTAINABILITY | N28: Article | V28: This paper examines the main issues regarding higher education in Korea-where college education experienced minimal interruptions-during the COVID-19 pandemic through a big data analysis of news articles. By analyzing policy responses from the government and colleges and examining prominent discourses on higher education, it provides a context for discussing the implications of COVID-19 on education policy and what the post-pandemic era would bring. To this end, we utilized BIgKinds, a big data research solution for news articles offered by the Korea Press Foundation, to select a total of 2636 media reports and conducted Topic Modelling based on LDA algorithms using NetMiner. The analyses are split into three distinct periods of COVID-19 spread in the country. Some notable topics from the first phase are remote class, tuition refund, returning Chinese international students, and normalization of college education. Preparations for the College Scholastic Ability Test (CSAT), contact and contactless classes, preparations for early admissions, and supporting job market candidates are extracted for the second phase. For the third phase, the extracted topics include CSAT and college-specific exams, quarantine on campus, social relations on campus, and support for job market candidates. The results confirmed widespread public attention to the relevant issues but also showed empirically that the measures taken by the government and college administrations to combat COVID-19 had limited visibility among media reports. It is important to note that timely and appropriate responses from the government and colleges have enabled continuation of higher education in some capacity during the pandemic. In addition to the media's role in reporting issues of public interest, there is also a need for continued research and discussion on higher education amid COVID-19 to help effect actual results from various policy efforts. | W28: [Ko, Jangwan; Park, Seoyoon; Park, Jiwoo] Sungkyunkwan Univ, Coll Educ, Seoul 04063, South Korea; [Paek, Seungsu] Gachon Univ, Grad Sch Educ, Seongnam 13120, South Korea | Y28: Paek, S (corresponding author), Gachon Univ, Grad Sch Educ, Seongnam 13120, South Korea. | Z28: jakosu@skku.edu; ongang@gachon.ac.kr; pseoyoon@skku.edu; jiwoopark1993@gmail.com | AG28: 51 | AH28: 12 | AI28: 15 | AT28: JUL | AU28: 2021 | AV28: 13 | AW28: 13 | BD28: 7347 | BE28: 10.3390/su13137347 | BF28: =HYPERLINK("http://dx.doi.org/10.3390/su13137347","http://dx.doi.org/10.3390/su13137347") -> http://dx.doi.org/10.3390/su13137347 | BR28: 2026-05-29 | BS28: WOS:000671131300001 | BT28: =HYPERLINK("https%3A%2F%2Fwww.webofscience.com%2Fwos%2Fwoscc%2Ffull-record%2FWOS:000671131300001","View Full Record in Web of Science") -> View Full Record in Web of Science | BU28: =COUNTIF('오픈소스&직접수집'!F:F,'wos(corecollection)_260528'!BE28) -> 1 | BV28: =COUNTIF('오픈소스&직접수집'!A:A,'wos(corecollection)_260528'!I28) -> 1 | BW28: =SUM(BU28:BV28) -> 2
A29: netminer 검색 | B29: Huang, WC; Zhang, Y; Zuo, BR; Yu, YC; De Dieu, GJ; Xu, YF | F29: Huang, Wencheng; Zhang, Yue; Zuo, Borui; Yu, Yaocheng; De Dieu, Gatesi Jean; Xu, Yifei | I29: Using an expanded Safety Failure Event Network to analyze railway dangerous goods transportation system risk-accident | J29: JOURNAL OF LOSS PREVENTION IN THE PROCESS INDUSTRIES | N29: Article | V29: In order to improve the reliability and safety of railway dangerous goods transportation system (RDGTS), and prevent the similar accidents happened again, an easier operated, dynamic, systemic and quantitative approach called expanded Safety Failure Event Network (SFEN) is proposed to analyze the past typical RDGTS accidents. The expanded SFEN focuses on transfer the traditional safety occurrence process into a visible Accident Analysis Network (AAN) platform. To improve the previous SFEN approach, the risk factors categories are expanded including Human actions, Technical failure, Nature of transported goods, Environment factors, Management failure and External factors of the system. An AAN is established by using the risk factors as the nodes and using the interactions among these risk factors as the edges, the RDGTS risk analysis problem is transferred into a quantitative network structure analysis problem from a network perspective. After that, based on the AAN, TouchGraph and NetMiner are applied to calculate and rank the centrality degree of each sub-risk factor (or subheading) in a network. A RDGTS accident happened in 2001 is analyzed, the results show that TouchGraph and NetMiner can present the same interactions and importance of sub-risk factors (or sub-headings) through visible circle images in the platform, NetMiner is more digital because the results can be presented as the centrality degree values. The greatest contributed sub-risk factors are Equipment maintenance failure and Railway inspection agency failure, followed by cargo packaging problems, illegal entrainment problem. Misbehaves of the freight inspector with centrality degree 0.523810 shows that this sub-heading has the greatest contribution to the accident. | W29: [Huang, Wencheng; Zhang, Yue; Zuo, Borui; Yu, Yaocheng; De Dieu, Gatesi Jean; Xu, Yifei] Southwest Jiaotong Univ, Sch Transportat & Logist, Chengdu 611756, Sichuan, Peoples R China; [Huang, Wencheng; Zhang, Yue; Zuo, Borui; Yu, Yaocheng; De Dieu, Gatesi Jean; Xu, Yifei] Southwest Jiaotong Univ, Natl United Engn Lab Intergrated & Intelligent Tr, Chengdu 611756, Sichuan, Peoples R China; [Huang, Wencheng] Southwest Jiaotong Univ, Natl Engn Lab Integrated Transportat Big Data App, Chengdu 611756, Sichuan, Peoples R China | Y29: Huang, WC (corresponding author), Southwest Jiaotong Univ, Sch Transportat & Logist, Chengdu 611756, Sichuan, Peoples R China. | Z29: 1261992248@qq.com | AG29: 27 | AH29: 19 | AI29: 23 | AT29: MAY | AU29: 2020 | AV29: 65 | BD29: 104122 | BE29: 10.1016/j.jlp.2020.104122 | BF29: =HYPERLINK("http://dx.doi.org/10.1016/j.jlp.2020.104122","http://dx.doi.org/10.1016/j.jlp.2020.104122") -> http://dx.doi.org/10.1016/j.jlp.2020.104122 | BR29: 2026-05-29 | BS29: WOS:000536925600053 | BT29: =HYPERLINK("https%3A%2F%2Fwww.webofscience.com%2Fwos%2Fwoscc%2Ffull-record%2FWOS:000536925600053","View Full Record in Web of Science") -> View Full Record in Web of Science | BU29: =COUNTIF('오픈소스&직접수집'!F:F,'wos(corecollection)_260528'!BE29) -> 0 | BV29: =COUNTIF('오픈소스&직접수집'!A:A,'wos(corecollection)_260528'!I29) -> 1 | BW29: =SUM(BU29:BV29) -> 1
A30: netminer 검색 | B30: Kim, J; Kim, MS | F30: Kim, Jihyun; Kim, Mi So | I30: An Overview of Cognitive Reserve in Aging Based on Keyword Network Analysis | J30: INQUIRY-THE JOURNAL OF HEALTH CARE ORGANIZATION PROVISION AND FINANCING | N30: Article | V30: Many studies have reported that Cognitive reserve is a critical mechanism affecting cognitive statuses, such as dementia. The purposes of this study were to identify the knowledge structure and the research trend on cognitive reserve by conducting keyword analysis on research papers ranging from the earliest to the most recent studies done on the topic and to suggest directions for future research. The Web of Science (WOS) database was used to search for articles on cognitive reserve in aging from 2001 to 2020. NetMiner version 4 (cyram, KOREA), a social network analysis program, was used for keyword network analysis. Data analysis showed keywords that could be categorized as cognitive reserve related keywords (cognitive reserve related concepts, cognitive reserve related factor, cognitive reserve diagnosis and measurement, cognitive reserve outcomes) and cognitive reserve research keywords (research subject/disease, research method, intervention, research field). Through trend analysis, we found that various keywords appeared, indicating that the research has gradually developed conceptually and methodically. Based on these findings, future CR studies require the development of multimodal interface-based tools by applying modern digital technology that can be used to more accurately diagnose and monitor CR; remotely, in real time. In addition, to improve CR, it is suggested that the development of cognitive stimulation interventions utilizing VR which fuses AI based interaction technology with the subjects. Finally, CR could develop further through a cooperation of multidisciplinary professionals such as psychology, medicine and nursing. | W30: [Kim, Jihyun] Sahmyook Univ, Seoul, South Korea; [Kim, Mi So] Shinhan Univ, Gyeonggi do, South Korea; [Kim, Mi So] Shinhan Univ, Coll Nursing, Bulma Ro 30, Dongducheon Si, Gyeonggi Do, South Korea | Y30: Kim, MS (corresponding author), Shinhan Univ, Coll Nursing, Bulma Ro 30, Dongducheon Si, Gyeonggi Do, South Korea. | Z30: misoangel83@gmail.com | AG30: 49 | AH30: 1 | AI30: 2 | AT30: NOV | AU30: 2022 | AV30: 59 | BD30: 469580221139374 | BE30: 10.1177/00469580221139374 | BF30: =HYPERLINK("http://dx.doi.org/10.1177/00469580221139374","http://dx.doi.org/10.1177/00469580221139374") -> http://dx.doi.org/10.1177/00469580221139374 | BR30: 2026-05-29 | BS30: WOS:000928080400001 | BT30: =HYPERLINK("https%3A%2F%2Fwww.webofscience.com%2Fwos%2Fwoscc%2Ffull-record%2FWOS:000928080400001","View Full Record in Web of Science") -> View Full Record in Web of Science | BU30: =COUNTIF('오픈소스&직접수집'!F:F,'wos(corecollection)_260528'!BE30) -> 1 | BV30: =COUNTIF('오픈소스&직접수집'!A:A,'wos(corecollection)_260528'!I30) -> 1 | BW30: =SUM(BU30:BV30) -> 2
A31: netminer 검색 | B31: Park, EJ; Kim, Y; Park, CS | F31: Park, Eun-Jun; Kim, Youngji; Park, Chan Sook | I31: A Comparison of Hospice Care Research Topics between Korea and Other Countries Using Text Network Analysis | J31: JOURNAL OF KOREAN ACADEMY OF NURSING | N31: Article | V31: Purpose: This study aimed to identify and compare hospice care research topics between Korean and intemational nursing studies using text network analysis. Methods: The study was conducted in four steps: 1) collecting abstracts of relevant journal articles, 2) extracting and cleaning keywords (semantic morphemes) from the abstracts, 3) developing co-occurrence matrices and text-networks of keywords, and 4) analyzing network-related measures including degree centrality, closeness centrality, betweenness centrality, and clustering using the NetMiner program. Abstracts from 347 Korean and 1,926 international studies for the period of 1998-2016 were analyzed. Results: Between Korean and international studies, six of the most important core keywords-hospice, patient, death, RNs, care, and family-were common, whereas cancer from Korean studies and palliative care from international studies ranked more highly. Keywords such as attitude, spirituality, life, effect, and meaning for Korean studies and communication, treatment, USA, and doctor for international studies uniquely emerged as core keywords in recent studies (2011 similar to 2016). Five subtopic groups each were identified from Korean and international studies. Two common subtopics were hospice palliative care and volunteers and cancer patients. Conclusion: For a better quality of hospice care in Korea, it is recommended that nursing researchers focus on study topics of patients with non-cancer disease, children and family, communication, and pain and symptom management. | W31: [Park, Eun-Jun] Konkuk Univ, Dept Nursing, Glocal Campus, Chungju, South Korea; [Kim, Youngji] Gachon Univ, Coll Nursing, Incheon, South Korea; [Park, Chan Sook] Konkuk Univ, Grad Sch, Dept Nursing, Glocal Campus, Chungju, South Korea | Y31: Park, CS (corresponding author), Konkuk Univ, Grad Sch, Dept Nursing, 268 Chungwon Daero, Chungju 27478, South Korea. | Z31: sook706@hanmail.net | AG31: 32 | AH31: 18 | AI31: 26 | AT31: OCT | AU31: 2017 | AV31: 47 | AW31: 5 | BB31: 600 | BC31: 612 | BE31: 10.4040/jkan.2017.47.5.600 | BF31: =HYPERLINK("http://dx.doi.org/10.4040/jkan.2017.47.5.600","http://dx.doi.org/10.4040/jkan.2017.47.5.600") -> http://dx.doi.org/10.4040/jkan.2017.47.5.600 | BR31: 2026-05-29 | BS31: WOS:000415783100003 | BT31: =HYPERLINK("https%3A%2F%2Fwww.webofscience.com%2Fwos%2Fwoscc%2Ffull-record%2FWOS:000415783100003","View Full Record in Web of Science") -> View Full Record in Web of Science | BU31: =COUNTIF('오픈소스&직접수집'!F:F,'wos(corecollection)_260528'!BE31) -> 1 | BV31: =COUNTIF('오픈소스&직접수집'!A:A,'wos(corecollection)_260528'!I31) -> 1 | BW31: =SUM(BU31:BV31) -> 2
A32: netminer 검색 | B32: Park, CS; Park, EJ | F32: Park, Chan Sook; Park, Eun-Jun | I32: Identification of of Knowledge Structure of Pain Management Nursing Research Applying Text Network Analysis | J32: JOURNAL OF KOREAN ACADEMY OF NURSING | N32: Article | V32: Purpose: This study aimed to explore and compare the knowledge structure of pain management nursing research, between Korea and other countries, applying a text network analysis. Methods: 321 Korean and 6,685 international study abstracts of pain management, published from 2004 to 2017, were collected. Keywords and meaningful morphemes from the abstracts were analyzed and refined, and their co-occurrence matrix was generated. Two networks of 140 and 424 keywords, respectively, of domestic and international studies were analyzed using NetMiner 4.3 software for degree centrality, closeness centrality, betweenness centrality, and eigenvector community analysis. Results: In both Korean and international studies, the most important, core-keywords were pain, patient, pain management, registered nurses, care, cancer, need, analgesia, assessment and surgery. While some keywords like 'education, knowledge, and patient-controlled analgesia found to be important in Korean studies; treatment hospice palliative care, and children were critical keywords in international studies. Three common sub-topic groups found in Korean and international studies were pain and accompanying symptoms, target groups of pain management, and RNs performance of pain management. It is only in recent years (201617), that keywords such as performance, attitude, depression, and sleep have become more important in Korean studies than, while keywords such as assessment, intervention, analgesia, and chronic pain have become important in international studies. Conclusion: It is suggested that Korean pain-management researchers should expand their concerns to children and adolescents, the elderly, patients with chronic pain, patients in diverse healthcare settings, and patients' use of opioid analgesia. Moreover, researchers need to approach pain-management with a quality of life perspective rather than a mere focus on individual symptoms. | W32: [Park, Chan Sook; Park, Eun-Jun] Konkuk Univ Glocal Campus, Dept Nursing, 268 Chungwon Dearo, Chungju 27478, South Korea | Y32: Park, EJ (corresponding author), Konkuk Univ Glocal Campus, Dept Nursing, 268 Chungwon Dearo, Chungju 27478, South Korea. | Z32: eunjunp@kku.ac.kr | AG32: 25 | AH32: 11 | AI32: 17 | AT32: OCT | AU32: 2019 | AV32: 49 | AW32: 5 | BB32: 538 | BC32: 549 | BE32: 10.4040/jkan.2019.49.5.538 | BF32: =HYPERLINK("http://dx.doi.org/10.4040/jkan.2019.49.5.538","http://dx.doi.org/10.4040/jkan.2019.49.5.538") -> http://dx.doi.org/10.4040/jkan.2019.49.5.538 | BR32: 2026-05-29 | BS32: WOS:000493986000004 | BT32: =HYPERLINK("https%3A%2F%2Fwww.webofscience.com%2Fwos%2Fwoscc%2Ffull-record%2FWOS:000493986000004","View Full Record in Web of Science") -> View Full Record in Web of Science | BU32: =COUNTIF('오픈소스&직접수집'!F:F,'wos(corecollection)_260528'!BE32) -> 0 | BV32: =COUNTIF('오픈소스&직접수집'!A:A,'wos(corecollection)_260528'!I32) -> 0 | BW32: =SUM(BU32:BV32) -> 0
A33: netminer 검색 | B33: Park, S; Park, J | F33: Park, Sooyeon; Park, Jinkyung | I33: Identifying the Knowledge Structure and Trends of Outreach in Public Health Care: A Text Network Analysis and Topic Modeling | J33: INTERNATIONAL JOURNAL OF ENVIRONMENTAL RESEARCH AND PUBLIC HEALTH | N33: Article | V33: Outreach programs are considered a key strategy for providing services to underserved populations and play a central role in delivering health-care services. To address this challenge, knowledge relevant to global health outreach programs has recently been expanded. The aims of this study were to analyze the knowledge structure and understand the trends in aspects over time and across regions using text network analysis with NetMiner 4.0. Data analysis by frequency, time and region showed that the central keywords such as patient, care, service and community were found to be highly related to the area, target population, purpose and type of services within the knowledge structure of outreach. As a result of performing topic modeling, knowledge structure in this area consisted of five topics: patient-centered care, HIV care continuum, services related to a specific disease, community-based health-care services and research and education on health programs. Our results newly identified that patient-centered care, specific disease and population have been growing more crucial for all times and countries by the examination of major trends in health-care related outreach research. These findings help health professionals, researchers and policymakers in nursing and public health fields in understanding and developing health-care-related outreach practices and suggest future research direction. | W33: [Park, Sooyeon] Korea Univ, Coll Nursing, Seoul 02841, South Korea; [Park, Jinkyung] Chonnam Natl Univ, Coll Nursing, Gwangju 61469, South Korea | Y33: Park, J (corresponding author), Chonnam Natl Univ, Coll Nursing, Gwangju 61469, South Korea. | Z33: isypark@korea.ac.kr; carpe@jnu.ac.kr | AG33: 69 | AH33: 5 | AI33: 8 | AT33: SEP | AU33: 2021 | AV33: 18 | AW33: 17 | BD33: 9309 | BE33: 10.3390/ijerph18179309 | BF33: =HYPERLINK("http://dx.doi.org/10.3390/ijerph18179309","http://dx.doi.org/10.3390/ijerph18179309") -> http://dx.doi.org/10.3390/ijerph18179309 | BR33: 2026-05-29 | BS33: WOS:000694150800001 | BT33: =HYPERLINK("https%3A%2F%2Fwww.webofscience.com%2Fwos%2Fwoscc%2Ffull-record%2FWOS:000694150800001","View Full Record in Web of Science") -> View Full Record in Web of Science | BU33: =COUNTIF('오픈소스&직접수집'!F:F,'wos(corecollection)_260528'!BE33) -> 1 | BV33: =COUNTIF('오픈소스&직접수집'!A:A,'wos(corecollection)_260528'!I33) -> 1 | BW33: =SUM(BU33:BV33) -> 2
A34: netminer 검색 | B34: Kim, YS; Lee, SK | F34: Kim, Young-Su; Lee, Soo-Kyoung | I34: Analysis of Research on Nurses' Job Stress Using Network Analysis | J34: WESTERN JOURNAL OF NURSING RESEARCH | N34: Article | V34: This study established a network related to nurses' job stress by conducting a social network analysis of titles, keywords, and abstracts, and it identified emerging topics of research. NetMiner 4.0 visualized an interconnection between critical keywords and investigated their frequency of appearance to construe the trends in nurses' job stress measures used in studies conducted over 55 years (1960-2015). Text Rank Analyzer examined a collection of 9,218 keywords from 2,662 studies. The analysis revealed four groups of newly emerging keywords in the research. The following five clusters were identified: concept, subject, method and tool, outcome and response, and solution and management. Thus, if new researchers refer to existing trends to establish the subject of their study, replication studies can be reduced, and the direction of the development of future research on nurses' job stress can be predicted. Further application of new interventions, development of objective indicators, working environment, and broader participants are needed. | W34: [Kim, Young-Su; Lee, Soo-Kyoung] Keimyung Univ, Daegu, South Korea | Y34: Lee, SK (corresponding author), Keimyung Univ, Coll Nursing, 1095 Dalgubeol Daero, Daegu 42601, South Korea. | Z34: soo1005@kmu.ac.kr | AG34: 31 | AH34: 8 | AI34: 9 | AT34: MAR | AU34: 2019 | AV34: 41 | AW34: 3 | BB34: 338 | BC34: 354 | BE34: 10.1177/0193945918781310 | BF34: =HYPERLINK("http://dx.doi.org/10.1177/0193945918781310","http://dx.doi.org/10.1177/0193945918781310") -> http://dx.doi.org/10.1177/0193945918781310 | BR34: 2026-05-29 | BS34: WOS:000458876200002 | BT34: =HYPERLINK("https%3A%2F%2Fwww.webofscience.com%2Fwos%2Fwoscc%2Ffull-record%2FWOS:000458876200002","View Full Record in Web of Science") -> View Full Record in Web of Science | BU34: =COUNTIF('오픈소스&직접수집'!F:F,'wos(corecollection)_260528'!BE34) -> 1 | BV34: =COUNTIF('오픈소스&직접수집'!A:A,'wos(corecollection)_260528'!I34) -> 0 | BW34: =SUM(BU34:BV34) -> 1
A35: netminer 검색 | B35: Kim, JY; Kim, YO | F35: Kim, Joo Young; Kim, Young Ook | I35: The association of spatial configuration with social network for elderly in social housing | J35: INDOOR AND BUILT ENVIRONMENT | N35: Article | V35: This study aimed to investigate the association of spatial configuration with social interaction for elderly. A social housing in Seoul was selected for the case study. Using space syntax and social network analysis, the association was examined statistically. This research employed an integration indicator which is most closely related to space use pattern. Questionnaire and interview surveys were conducted to illustrate the pattern of social network. Using the collected data, NetMiner was utilized to conduct a quantitative analysis. Degree, closeness and betweenness indicators were employed to measure relationships in these networks and between individuals. The characteristics of the association established by the statistical analysis between spatial network of housing estate and social network of elderly were discussed. Our results show that spatial network properties can explain characteristics of social network. The accessibility of residential spaces for elderly individuals in social housing apartment complex has an effect on the strength of the social network with neighbours. Also, analysis of the spatial configuration accessibility for the elderly population with integration values has illustrated that the result was opposite to the general theory that 'the locations with high accessibility could foster more interactions'. Our findings have suggested that we can have a better knowledge to foster more social network among elderly by planning improved spatial network. | W35: [Kim, Joo Young; Kim, Young Ook] Sejong Univ, Dept Architecture, Seoul, South Korea | Y35: Kim, YO (corresponding author), Sejong Univ, 98 Kunjadong Gwangjin Gu, Seoul 05006, South Korea. | Z35: yokim@sejong.ac.kr | AG35: 40 | AH35: 6 | AI35: 6 | AT35: MAR | AU35: 2020 | AV35: 29 | AW35: 3 | AZ35: SI | BB35: 405 | BC35: 416 | BE35: 10.1177/1420326X17732612 | BF35: =HYPERLINK("http://dx.doi.org/10.1177/1420326X17732612","http://dx.doi.org/10.1177/1420326X17732612") -> http://dx.doi.org/10.1177/1420326X17732612 | BR35: 2026-05-29 | BS35: WOS:000523823500009 | BT35: =HYPERLINK("https%3A%2F%2Fwww.webofscience.com%2Fwos%2Fwoscc%2Ffull-record%2FWOS:000523823500009","View Full Record in Web of Science") -> View Full Record in Web of Science | BU35: =COUNTIF('오픈소스&직접수집'!F:F,'wos(corecollection)_260528'!BE35) -> 0 | BV35: =COUNTIF('오픈소스&직접수집'!A:A,'wos(corecollection)_260528'!I35) -> 1 | BW35: =SUM(BU35:BV35) -> 1
A36: netminer 검색 | B36: Lee, SK; Hong, HS | F36: Lee, Soo-Kyoung; Hong, Hye Sun | I36: Text network analysis of research topics and trends on global health nursing literature from 1974-2017 | J36: JOURNAL OF ADVANCED NURSING | N36: Article | V36: Aims The purpose of this study is to examine the relationship between keywords in existing global health nursing studies during 44 years (1974-2017) and to develop schematic diagrams of the relationship between these keywords from a macro perspective. It is to identify the trend of the literature in global health nursing field. Design A descriptive bibliometric analysis of publications in global health nursing. Methods The keywords from 7,115 articles and literatures were examined using the Text Rank Analyzer via the applied text network analysis with NetMiner 4.0. Results As for global health nursing, keywords with the most frequent appearance and the highest networking degree in centrality were 'study', 'patient', 'nurse', and 'women'. Six central keywords were also found highly related to other keywords: 'global health nursing', 'study', 'patient', 'care', 'nurse', and 'education'. By measuring the degree of keywords connected to other keywords in centrality, six clusters were established. Then, emerging topics assessed by time periods were identified as follows: the beginning phase ('breastfeeding', 'women', and 'children'), the development phase ('quality', 'life', and 'human immunodeficiency virus'), the maturation phase ('mental health', 'depression', and 'global health'), and the expansion phase ('pregnancy', 'palliative care', and 'infectious disease'). Conclusion The identified trends on this study will help nurse leaders to grasp the trends and insights for global health and to train future nurses to serve clients better in the practice fields. Impact Keywords with the highest appearance and centrality in the network were found in the global health articles. The bibliometric analysis showed various subjects according to the following phases: beginning development maturation and expansion. The awareness of the trend change in the global health helps nursing researchers and educators modify the curriculum of global health nursing and train future nurses to be equipped with the global health competencies. | W36: [Lee, Soo-Kyoung; Hong, Hye Sun] Keimyung Univ, Coll Nursing, Daegu, South Korea | Y36: Lee, SK (corresponding author), Keimyung Univ, Coll Nursing, Daegu, South Korea. | Z36: soo1005s@gmail.com | AG36: 44 | AH36: 6 | AI36: 6 | AT36: MAR | AU36: 2021 | AV36: 77 | AW36: 3 | BB36: 1325 | BC36: 1334 | BE36: 10.1111/jan.14685 | BF36: =HYPERLINK("http://dx.doi.org/10.1111/jan.14685","http://dx.doi.org/10.1111/jan.14685") -> http://dx.doi.org/10.1111/jan.14685 | BH36: DEC 2020 | BR36: 2026-05-29 | BS36: WOS:000596469900001 | BT36: =HYPERLINK("https%3A%2F%2Fwww.webofscience.com%2Fwos%2Fwoscc%2Ffull-record%2FWOS:000596469900001","View Full Record in Web of Science") -> View Full Record in Web of Science | BU36: =COUNTIF('오픈소스&직접수집'!F:F,'wos(corecollection)_260528'!BE36) -> 1 | BV36: =COUNTIF('오픈소스&직접수집'!A:A,'wos(corecollection)_260528'!I36) -> 1 | BW36: =SUM(BU36:BV36) -> 2
A37: netminer 검색 | B37: Zhou, K; Yan, C; Xu, Y | F37: Zhou, Kuang; Yan, Chen; Xu, Yong | I37: The vulnerability of communities in complex networks: A causal perspective on dynamic retentivity | J37: RELIABILITY ENGINEERING & SYSTEM SAFETY | N37: Article | V37: removing | W37: [Zhou, Kuang; Yan, Chen; Xu, Yong] Northwestern Polytech Univ, Sch Math & Stat, Xian 710129, Shaanxi, Peoples R China; [Zhou, Kuang; Xu, Yong] Northwestern Polytech Univ, MOE Key Lab Complex Sci Aerosp, Xian 710129, Peoples R China | Y37: Zhou, K (corresponding author), Northwestern Polytech Univ, Sch Math & Stat, Xian 710129, Shaanxi, Peoples R China. | Z37: kzhoumath@nwpu.edu.cn; 2021204670@mail.nwpu.edu.cn; hsux3@nwpu.edu.cn | AG37: 41 | AH37: 8 | AI37: 9 | AT37: OCT | AU37: 2025 | AV37: 262 | BD37: 111171 | BE37: 10.1016/j.ress.2025.111171 | BF37: =HYPERLINK("http://dx.doi.org/10.1016/j.ress.2025.111171","http://dx.doi.org/10.1016/j.ress.2025.111171") -> http://dx.doi.org/10.1016/j.ress.2025.111171 | BH37: MAY 2025 | BR37: 2026-05-29 | BS37: WOS:001492650900002 | BT37: =HYPERLINK("https%3A%2F%2Fwww.webofscience.com%2Fwos%2Fwoscc%2Ffull-record%2FWOS:001492650900002","View Full Record in Web of Science") -> View Full Record in Web of Science | BU37: =COUNTIF('오픈소스&직접수집'!F:F,'wos(corecollection)_260528'!BE37) -> 0 | BV37: =COUNTIF('오픈소스&직접수집'!A:A,'wos(corecollection)_260528'!I37) -> 0 | BW37: =SUM(BU37:BV37) -> 0
A38: netminer 검색 | B38: Zhu, R; Li, LH | F38: Zhu, Rui; Li, Lihong | I38: Intelligent construction technology based information sharing network for prefabricated building supply chain: a social network analysis approach | J38: KYBERNETES | N38: Article | V38: PurposeIn the context of Industry 4.0, intelligent construction technologies (ICT) represented by information technology and networking will undoubtedly provide new impetus to the development of the prefabricated building supply chain (PBSC), but they will also bring various potential risks. So far, there is a large lack of research on the comprehensive consideration of the risks associated with the intelligent transformation of PBSC based on the information sharing perspective, and the critical risks and interactions are still unclear, making it difficult to identify efficient risk mitigation strategies. Therefore, this paper aims to reveal the interactions between stakeholders and clarify the critical risk nodes and interactions in information sharing of PBSC (IS-PBSC), and propose targeted risk mitigation strategies.Design/methodology/approachFirstly, this paper creatively delineates the risks and critical stakeholders of IS-PBSC. Secondly, Data is collected through questionnaires to understand the degree of risks impact. Thirdly, with the help of NetMiner 4 software, social network analysis is conducted and IS-PBSC risk network is established to reveal critical risk nodes and interactions. Finally, further targeted discussion of critical risk nodes, the effectiveness and reasonableness of the risk mitigation strategies are proposed and verified through NetMiner 4 software simulation.FindingsThe results show that the critical risks cover the entire process of information sharing, with the lack of information management norms and other information assurance-related risks accounting for the largest proportion. In addition, the government dominates in risk control, followed by other stakeholders. The implementation of risk mitigation strategies is effective, with the overall network density reduced by 41.15% and network cohesion reduced by 24%.Research limitations/implicationsIn the context of Industry 4.0, ICT represented by information technology and networking will undoubtedly provide new impetus to the development of the PBSC, but they will also bring various potential risks. So far, there is a large lack of research on the comprehensive consideration of the risks associated with the intelligent transformation of PBSC based on the information sharing perspective, and the critical risks and interactions are still unclear, making it difficult to identify efficient risk mitigation strategies.Originality/valueBased on the results of risk network visualization analysis, this paper proposes an ICT-based IS-PBSC mechanism that promotes the development of the integration of ICT and PBSC while safeguarding the benefits of various stakeholders. | W38: [Zhu, Rui; Li, Lihong] Shenyang Jianzhu Univ, Sch Management, Shenyang, Peoples R China | Y38: Li, LH (corresponding author), Shenyang Jianzhu Univ, Sch Management, Shenyang, Peoples R China. | Z38: lilihong@sjzu.edu.cn | AG38: 79 | AH38: 0 | AI38: 0 | AT38: OCT 14 | AU38: 2025 | AV38: 54 | AW38: 9 | BB38: 5158 | BC38: 5180 | BE38: 10.1108/K-01-2024-0128 | BF38: =HYPERLINK("http://dx.doi.org/10.1108/K-01-2024-0128","http://dx.doi.org/10.1108/K-01-2024-0128") -> http://dx.doi.org/10.1108/K-01-2024-0128 | BH38: APR 2024 | BR38: 2026-05-29 | BS38: WOS:001208132700001 | BT38: =HYPERLINK("https%3A%2F%2Fwww.webofscience.com%2Fwos%2Fwoscc%2Ffull-record%2FWOS:001208132700001","View Full Record in Web of Science") -> View Full Record in Web of Science | BU38: =COUNTIF('오픈소스&직접수집'!F:F,'wos(corecollection)_260528'!BE38) -> 2 | BV38: =COUNTIF('오픈소스&직접수집'!A:A,'wos(corecollection)_260528'!I38) -> 1 | BW38: =SUM(BU38:BV38) -> 3
A39: netminer 검색 | B39: Sun, Y; Shao, YW; Chan, EHW | F39: Sun, Yao; Shao, Yiwen; Chan, Edwin H. W. | I39: Co-visitation network in tourism-driven peri-urban area based on social media analytics: A case study in Shenzhen, China | J39: LANDSCAPE AND URBAN PLANNING | N39: Article | V39: The peri-urban area has undergone tremendous changes in various aspects. Tourism-driven development in this area, echoing the longing of urban residents for recreational and leisure space, provides an alternative to conventional urbanization approaches. Particularly, in view of heightened conflicts and fierce competitions that often occur in the area, developing the knowledge of the co-visitation network, or how different attractions and villages interact with each other from the visitors' perspective, is key to more informed planning strategies. With the rapid development of online social media platforms and mobile devices, researchers can collect massive realtime data on the basis of online user-generated content. While there are already many attempts on its application on tourism design, few studies to date have explored how peri-urban attractions and villages are organized in same trips. In this paper, we design a new methodology on the basis of social media analytics to construct and map a co-visitation network, and apply NetMiner-enabled social network analysis to explain its structure and nodal functions. The usefulness of this methodology is demonstrated through a detailed case study in Shenzhen, China. Research findings reveal types of existing co-visitation patterns, which help planners predict future trends, design new experiences and take specific measures in line with visitor demands. | W39: [Sun, Yao] Jinan Univ, Shenzhen Tourism Coll, Shenzhen 518053, Guangdong, Peoples R China; [Shao, Yiwen] Shenzhen Univ, Sch Architecture & Urban Planning, Shenzhen 518061, Guangdong, Peoples R China; [Chan, Edwin H. W.] Hong Kong Polytech Univ, Dept Bldg & Real Estate, Hong Kong, Peoples R China | Y39: Shao, YW (corresponding author), Shenzhen Univ, Sch Architecture & Urban Planning, Shenzhen 518061, Guangdong, Peoples R China. | Z39: sunyao@sz.jnu.edu.cn; yiwenshao@szu.edu.cn; bsedchan@polyu.edu.hk | AG39: 55 | AH39: 34 | AI39: 37 | AT39: DEC | AU39: 2020 | AV39: 204 | BD39: 103934 | BE39: 10.1016/j.landurbplan.2020.103934 | BF39: =HYPERLINK("http://dx.doi.org/10.1016/j.landurbplan.2020.103934","http://dx.doi.org/10.1016/j.landurbplan.2020.103934") -> http://dx.doi.org/10.1016/j.landurbplan.2020.103934 | BR39: 2026-05-29 | BS39: WOS:000579383300009 | BT39: =HYPERLINK("https%3A%2F%2Fwww.webofscience.com%2Fwos%2Fwoscc%2Ffull-record%2FWOS:000579383300009","View Full Record in Web of Science") -> View Full Record in Web of Science | BU39: =COUNTIF('오픈소스&직접수집'!F:F,'wos(corecollection)_260528'!BE39) -> 0 | BV39: =COUNTIF('오픈소스&직접수집'!A:A,'wos(corecollection)_260528'!I39) -> 1 | BW39: =SUM(BU39:BV39) -> 1
A40: netminer 검색 | B40: Lee, HJ; Kim, I | F40: Lee, HeeJeong Jasmine; Kim, In | I40: A Comparative Study of Social Network Tools for Analysing Chinese Elites | J40: KSII TRANSACTIONS ON INTERNET AND INFORMATION SYSTEMS | N40: Article | V40: For accurately analysing and forecasting the social networks of China's political, economic and social power elites, it is necessary to develop a database that collates their information. The development of such a database involves three stages: data definition, data collection and data quality maintenance. The present study recommends distinctive solutions in overcoming the challenges that occur in existing comparable databases. We used organizational and event factors to identify the Chinese power elites to be included in the database, and used their memberships, social relations and interactions in combination with flows data collection methodologies to determine the associations between them. The system can be used to determine the optimal relationship path (i.e., the shortest path) to reach a target elite and to identify of the most important power elite in a social network (e.g., degree, closeness and eigenvector centrality) or a community (e.g., a clique or a cluster). We have used three social network analysis tools (i.e., R, UCINET and NetMiner) in order to find the important nodes in the network. We compared the results of centrality rankings of each tool. We found that all three tools are providing slightly different results of centrality. This is because different tools use different algorithms and even within the same tool there are various libraries which provide the same functionality (i.e., ggraph, igraph and sna in R that provide the different function to calculate centrality). As there are chances that the results may not be the same (i.e. centrality rankings indicating the most important nodes can be varied), we recommend a comparison test using different tools to get accurate results. | W40: [Lee, HeeJeong Jasmine; Kim, In] PyeongTaek Univ, Pierson Coll, Pyeongtaek, South Korea | Y40: Kim, I (corresponding author), PyeongTaek Univ, Pierson Coll, Pyeongtaek, South Korea. | Z40: hjlee@ptu.ac.kr; kimin@ptu.ac.kr | AG40: 19 | AH40: 1 | AI40: 1 | AT40: OCT 31 | AU40: 2021 | AV40: 15 | AW40: 10 | BB40: 3571 | BC40: 3587 | BE40: 10.3837/tiis.2021.10.006 | BF40: =HYPERLINK("http://dx.doi.org/10.3837/tiis.2021.10.006","http://dx.doi.org/10.3837/tiis.2021.10.006") -> http://dx.doi.org/10.3837/tiis.2021.10.006 | BR40: 2026-05-29 | BS40: WOS:000714446400006 | BT40: =HYPERLINK("https%3A%2F%2Fwww.webofscience.com%2Fwos%2Fwoscc%2Ffull-record%2FWOS:000714446400006","View Full Record in Web of Science") -> View Full Record in Web of Science | BU40: =COUNTIF('오픈소스&직접수집'!F:F,'wos(corecollection)_260528'!BE40) -> 0 | BV40: =COUNTIF('오픈소스&직접수집'!A:A,'wos(corecollection)_260528'!I40) -> 1 | BW40: =SUM(BU40:BV40) -> 1
A41: cyram 인용 | B41: Yun, SY; Song, MO | F41: Yun, So Young; Song, Mi Ok | I41: Unmet Healthcare Needs in COPD: A Text Network Analysis and Topic Modeling of Pre/Post-COVID-19 Research Trends | J41: HEALTHCARE | N41: Article | V41: Highlights What are the main findings? Research on COPD increasingly recognizes that patients face barriers not only in treatment but also in diagnosis, rehabilitation, and access to medicines. Since COVID-19, studies have shifted toward digital tools, remote support, and fairer access to medication and services. What are the implications of the main findings? Improving care for people with COPD means building health systems that see the whole person-addressing medical needs alongside access, affordability, and support. Expanding digital care options, strengthening rehabilitation programs, and ensuring fair access to treatment can help people with COPD live healthier, more stable lives.Highlights What are the main findings? Research on COPD increasingly recognizes that patients face barriers not only in treatment but also in diagnosis, rehabilitation, and access to medicines. Since COVID-19, studies have shifted toward digital tools, remote support, and fairer access to medication and services. What are the implications of the main findings? Improving care for people with COPD means building health systems that see the whole person-addressing medical needs alongside access, affordability, and support. Expanding digital care options, strengthening rehabilitation programs, and ensuring fair access to treatment can help people with COPD live healthier, more stable lives.Abstract Background/Objectives: Unmet healthcare needs, driven by structural and patient-level barriers, are particularly critical in chronic obstructive pulmonary disease (COPD). However, limited research has examined how academic themes on this topic connect and evolve over time. This study analyzed the structure and temporal shifts in research trends on unmet healthcare needs in COPD to identify key concepts and topics and policy implications. Methods: We systematically searched PubMed, Embase, and CINAHL (12-15 March 2025) to identify English-language abstracts on unmet healthcare needs in COPD. Eligible studies were peer-reviewed articles with an English-language abstract that examined unmet healthcare needs from the patient perspective. In total, 451 abstracts were analyzed using text network analysis and Latent Dirichlet Allocation. Topic distributions before and after the coronavirus disease pandemic were assessed using chi-square tests, and findings were interpreted within Penchansky and Thomas's 5A healthcare access framework. Results: Six topics emerged: socioeconomic disparities, early diagnosis and symptom management, guideline-based information and technology use, integrated care for advanced COPD, access to pulmonary rehabilitation, and equitable medication availability. These topics mapped onto all five access dimensions, underscoring the multidimensional nature of unmet healthcare needs. Network analysis identified management, diagnosis, symptoms, exacerbation, and other related terms as central hubs in the discourse. Post-pandemic, research shifted toward digital information delivery, technology adoption, and equitable pharmacotherapy. Conclusions: Findings suggest that reducing unmet healthcare needs in COPD requires integrated systems that address both disease complexity and access barriers. Targeted, multidisciplinary, and policy-driven interventions in highly central domains are needed to reduce disparities and improve outcomes. This study also confirmed a post-pandemic shift in research priorities, emphasizing the need for equitable and adaptive healthcare policies. | W41: [Yun, So Young] Nambu Univ, Dept Nursing, Gwangju 62271, South Korea; [Song, Mi Ok] Mokpo Natl Univ, Dept Nursing, Muan 58554, South Korea | Y41: Song, MO (corresponding author), Mokpo Natl Univ, Dept Nursing, Muan 58554, South Korea. | Z41: yunsy@nambu.ac.kr; coffeesong@mnu.ac.kr | AG41: 37 | AH41: 0 | AI41: 0 | AT41: DEC 29 | AU41: 2025 | AV41: 14 | AW41: 1 | BD41: 82 | BE41: 10.3390/healthcare14010082 | BF41: 0 | BR41: 2026-05-29 | BS41: WOS:001657361300001 | BT41: 0 | BU41: =COUNTIF('오픈소스&직접수집'!F:F,'wos(corecollection)_260528'!BE41) -> 0 | BV41: =COUNTIF('오픈소스&직접수집'!A:A,'wos(corecollection)_260528'!I41) -> 0 | BW41: =SUM(BU41:BV41) -> 0
A42: cyram 인용 | B42: Kim, J; Chun, J | F42: Kim, Jinyung; Chun, Jongserl | I42: Korean adolescent's cigarette, e-cigarette, and dual use within the peer network context: A mixed methods study | J42: JOURNAL OF HUMAN BEHAVIOR IN THE SOCIAL ENVIRONMENT | N42: Article; Early Access | V42: The current study aims to investigate the relationship between peer network and smoking behavior, taking into account the structural, positional, and contextual aspects of the network. Using an explanatory sequential mixed methods design, a total of 73 Korean adolescents participated in the survey and seven current smokers from three sub-networks were invited for individual qualitative interviews. The quantitative findings revealed that out-degree centrality was associated with ever cigarette use and dual use, while betweenness centrality was related to ever cigarette use only. In the qualitative strand, three themes were identified: Fully assimilating into the mainstream, forced to stay within the boundary, and being introduced to new items and culture through the information network. The integrated findings provided deeper context and reasons for a higher in-degree centrality for dual-user network and a higher out-degree centrality for out-of-school adolescent network, the social hierarchy of adolescents in relation to cohesion index and clustering coefficient, and the type of information shared within the network. This study identified vulnerable individuals and groups in the peer network with regard to smoking and explored the smoking norms and culture of Korean adolescents within the network structure. | W42: [Kim, Jinyung] Univ Maryland, Sch Social Work, Baltimore, MD USA; [Chun, Jongserl] Ewha Womans Univ, Dept Social Welf, Seoul, South Korea | Y42: Kim, J (corresponding author), Univ Oklahoma, Anne & Henry Zarrow Sch Social Work, 700 Elm Ave,Zarrow Hall, Norman, OK 73069 USA. | Z42: jinyung.kim-1@ou.edu | AG42: 43 | AH42: 0 | AI42: 0 | AT42: 2025 AUG 25 | AU42: 2025 | BE42: 10.1080/10911359.2025.2548550 | BF42: 0 | BH42: AUG 2025 | BR42: 2026-05-29 | BS42: WOS:001556697000001 | BT42: 0 | BU42: =COUNTIF('오픈소스&직접수집'!F:F,'wos(corecollection)_260528'!BE42) -> 0 | BV42: =COUNTIF('오픈소스&직접수집'!A:A,'wos(corecollection)_260528'!I42) -> 0 | BW42: =SUM(BU42:BV42) -> 0
A43: cyram 인용 | B43: Ahn, S; Jeong, HW | F43: Ahn, Shinhye; Jeong, Hye Won | I43: Analysis of clinical nurse educators' mentoring feedback on new nurse journals at a tertiary hospital in South Korea: utilizing text network analysis | J43: BMC NURSING | N43: Article | V43: BackgroundThe gap between knowledge and clinical practice causes stress and reality shock, contributing to low job satisfaction and high turnover among new nurses; in 2023, the turnover rate in South Korea reached 52.4%. Korean preceptorship programs are often too brief to adequately support new nurses' adaptation. Clinical nurse educators (CNEs) play a crucial role in addressing these issues by offering knowledge transfer, emotional support, and career guidance. Therefore, strategies to strengthen CNEs' coaching and mentoring skills are essential to support new nurses' stable clinical adaptation. This study analyzed how CNEs mentored new hospital nurses by responding to their post-entry journals.MethodsThis study employed a quantitative content analysis. We used NetMiner 4.5.1 to conduct a text network analysis of 1,742 mentoring journal responses written by four CNEs for 120 new nurses at C University Hospital in South Korea between June 2021 and May 2022.ResultsThe keyword attitude had the highest frequency (726), emphasizing the clinical importance of fostering positive attitudes among new nurses. The keyword network had average centrality measures of degree (.15), closeness (.43), and betweenness (.05). Keywords with high centrality, such as attitude, importance, performance, and difficulty, highlighted mentoring practices focused on enhancing clinical judgment, nursing performance, and managing workplace challenges. Eigenvector analysis identified three subtopic groups with optimal modularity (.295). Subthemes included: 1) helping new nurses to improve their professional competence, 2) encouraging new nurses struggling to adapt to the field, and 3) empathy for new nurses' burdens and stress.ConclusionsThe findings revealed that the CNEs' mentoring feedback focused on encouraging new nurses to maintain a positive attitude, inspiring their personal and professional growth, and offering empathy and encouragement to help them cope with burdens and stress. Based on these findings, targeted training modules for CNEs and mentoring guidelines should be developed to further support new nurses' adaptation to clinical practice. | W43: [Ahn, Shinhye] Sunchon Natl Univ, Dept Nursing, Suncheon Si, Jeollanam Do, South Korea; [Jeong, Hye Won] Korea Natl Univ Transportat, Dept Nursing, 61 Daehak Ro, Jeungpyeong 27909, Chungcheongbuk, South Korea | Y43: Jeong, HW (corresponding author), Korea Natl Univ Transportat, Dept Nursing, 61 Daehak Ro, Jeungpyeong 27909, Chungcheongbuk, South Korea. | Z43: hyewon1129@ut.ac.kr | AG43: 36 | AH43: 0 | AI43: 0 | AT43: AUG 5 | AU43: 2025 | AV43: 24 | AW43: 1 | BD43: 1016 | BE43: 10.1186/s12912-025-03625-5 | BF43: 0 | BR43: 2026-05-29 | BS43: WOS:001545465400002 | BT43: 0 | BU43: =COUNTIF('오픈소스&직접수집'!F:F,'wos(corecollection)_260528'!BE43) -> 0 | BV43: =COUNTIF('오픈소스&직접수집'!A:A,'wos(corecollection)_260528'!I43) -> 1 | BW43: =SUM(BU43:BV43) -> 1
A44: cyram 인용 | B44: Park, KR; Lee, K; Park, S | F44: Park, Keon-Ryeong; Lee, Kyunghwa; Park, Sukyoung | I44: An Analysis of Publications in Early Childhood Education Journal Through LDA Topic Modeling: Exploring Research Trends From 2000 to 2023 | J44: EARLY CHILDHOOD EDUCATION JOURNAL | N44: Review; Early Access | V44: This study applied Blei et al.'s (Journal of Machine Learning Research 3:993-1022, 2003) Latent Dirichlet Allocation (LDA) topic modeling to analyze 1,727 research articles published in Early Childhood Education Journal (ECEJ) from 2000 to 2023. LDA is a probability-based analysis model effective for discovering hidden topics within large sets of textual data. The purpose of this study was to identify underlying research trends and thematic shifts in ECEJ publications during this period by examining trends in publication numbers, keyword frequencies, and topic emergence. The analysis results revealed a significant increase in published papers during the 2020-2023 period, with 2023 recording the highest number of publications. Keyword frequency analysis identified young children, teachers, and preschools as the three most frequently used keywords, underscoring a consistent focus on children in their early years, their educators, and educational settings. Trends in research topics highlighted an enduring focus on Reading and Young Children's Literature, the most dominant topic over the past 24 years, reflecting the connections to federal and state educational policies promoting early reading and literacy. Additionally, the analysis demonstrated the impact of the COVID-19 pandemic on research priorities, with Teacher Perceptions and Distance Education during COVID-19 emerging as the second most prevalent topic since 2000. The article concludes by discussing implications for future directions in early childhood research. | W44: [Park, Keon-Ryeong] Korea Natl Univ Educ, Res Inst Early Childhood Educ, 250 Taeseongtabyeon Ro,Gangnae Myeon, Cheongju, South Korea; [Lee, Kyunghwa] Univ Georgia, Dept Educ Theory & Practice, 110 Carlton St, Athens, GA 30602 USA; [Park, Sukyoung] Konkuk Univ, Dept Educ Technol, 120 Neungdong Ro, Seoul 05029, South Korea | Y44: Park, S (corresponding author), Konkuk Univ, Dept Educ Technol, 120 Neungdong Ro, Seoul 05029, South Korea. | Z44: parksk@konkuk.ac.kr | AG44: 22 | AH44: 0 | AI44: 0 | AT44: 2025 JUN 12 | AU44: 2025 | BE44: 10.1007/s10643-025-01932-9 | BF44: 0 | BH44: JUN 2025 | BR44: 2026-05-29 | BS44: WOS:001506957700001 | BT44: 0 | BU44: =COUNTIF('오픈소스&직접수집'!F:F,'wos(corecollection)_260528'!BE44) -> 0 | BV44: =COUNTIF('오픈소스&직접수집'!A:A,'wos(corecollection)_260528'!I44) -> 0 | BW44: =SUM(BU44:BV44) -> 0
A45: cyram 인용 | B45: Siudak, D | F45: Siudak, Dariusz | I45: The dependency structure of the financial multiplex network model: New evidence from the cross-correlation of idiosyncratic returns, volatility, and trading volume | J45: PLOS ONE | N45: Article | V45: This work describes the design of a novel financial multiplex network composed of three layers obtained by applying the MST-based cross-correlation network, using the data from 465 companies listed on the US market. The study employs a combined approach of complex multiplex networks, to examine the statistical properties of asset interdependence within the financial market. In addition, it performs an extensive analysis of both the similarities and the differences between this financial multiplex network, its individual layers, and the commonly studied stock return network. The results highlight the importance of the financial multiplex network, demonstrating that its network layers offer unique information within the multiplex dataset. Empirical analysis reveals dissimilarities between the financial multiplex network and the stock return monoplex network, indicating that the two networks provide distinct insights into the structure of the stock market. Furthermore, the financial multiplex network outperforms the singleplex network of stock returns because it has a structure that better determines the future Sharpe ratio. These findings add substantially to our understanding of the financial market system in which multiple types of relationship among financial assets play an important role. | W45: [Siudak, Dariusz] Lodz Univ Technol, Inst Management, Div Econ & Finance, Lodz, Poland | Y45: Siudak, D (corresponding author), Lodz Univ Technol, Inst Management, Div Econ & Finance, Lodz, Poland. | Z45: dariusz.siudak@p.lodz.pl | AG45: 111 | AH45: 2 | AI45: 2 | AT45: APR 18 | AU45: 2025 | AV45: 20 | AW45: 4 | BD45: e0320799 | BE45: 10.1371/journal.pone.0320799 | BF45: 0 | BR45: 2026-05-29 | BS45: WOS:001489628200016 | BT45: 0 | BU45: =COUNTIF('오픈소스&직접수집'!F:F,'wos(corecollection)_260528'!BE45) -> 0 | BV45: =COUNTIF('오픈소스&직접수집'!A:A,'wos(corecollection)_260528'!I45) -> 0 | BW45: =SUM(BU45:BV45) -> 0
A46: cyram 인용 | B46: Ahn, SH; Jeong, HW; Yang, SG; Jung, US; Choi, ML; Kim, HS | F46: Ahn, Shin Hye; Jeong, Hye Won; Yang, Seong Gyeong; Jung, Ue Seok; Choi, Myoung Lee; Kim, Heui Seon | I46: Temporal Exploration of New Nurses' Field Adaptation Using Text Network Analysis | J46: JOURNAL OF KOREAN ACADEMY OF NURSING | N46: Article | V46: Purpose: This study aimed to analyze the experiences of new nurses during their first year of hospital employment to gather data for the development of an evidence-based new nurse residency program focused on adaptability. Methods: This study was conducted at a tertiary hospital in Korea between March and August 2021 with 80 new nurses who wrote in critical reflective journals during their first year of work. NetMiner 4.5.0 was used to conduct a text network analysis of the critical reflective journals to uncover core keywords and topics across three periods. Results: In the journals, over time, degree centrality emerged as study and patient understanding for 1 to 3 months, insufficient and stress for 4 to 6 months, and handover and preparation for 7 to 12 months. Major sub-themes at 1 to 3 months were: rounds, intravenous-cannulation, medical device, and patient understanding; at 4 to 6 months they were admission, discharge, oxygen therapy, and disease; and at 7 to 12 months they were burden, independence, and solution. Conclusion: These results provide valuable insights into the challenges and experiences encountered by new nurses during different stages of their field adaptation process. This information may highlight the best nurse leadership methods for improving institutional education and supporting new nurses' transitions to the hospital work environment. | W46: [Ahn, Shin Hye; Jeong, Hye Won; Yang, Seong Gyeong; Jung, Ue Seok; Choi, Myoung Lee; Kim, Heui Seon] Chonnam Natl Univ Hosp, Dept Nursing, Gwangju, South Korea; [Jeong, Hye Won] Chonnam Natl Univ, Coll Nursing, Gwangju, South Korea; [Jeong, Hye Won] Korea Natl Univ Transportat, Dept Nursing, 61 Daehak ro,Yonggang ri,Jeungpyeong eup, Jeungpyeong 27909, South Korea | Y46: Jeong, HW (corresponding author), Korea Natl Univ Transportat, Dept Nursing, 61 Daehak ro,Yonggang ri,Jeungpyeong eup, Jeungpyeong 27909, South Korea. | Z46: hyewon1129@ut.ac.kr | AG46: 41 | AH46: 4 | AI46: 5 | AT46: JUN | AU46: 2024 | AV46: 54 | AW46: 3 | BB46: 358 | BC46: 371 | BE46: 10.4040/jkan.24034 | BF46: 0 | BR46: 2026-05-29 | BS46: WOS:001314085800007 | BT46: 0 | BU46: =COUNTIF('오픈소스&직접수집'!F:F,'wos(corecollection)_260528'!BE46) -> 1 | BV46: =COUNTIF('오픈소스&직접수집'!A:A,'wos(corecollection)_260528'!I46) -> 1 | BW46: =SUM(BU46:BV46) -> 2
A47: cyram 인용 | B47: Kim, J | F47: Kim, Jongwon | I47: Analysis of football research trends using text network analysis | J47: PLOS ONE | N47: Article | V47: This study was aimed to identify football research trends in various periods. A total of 30,946 football papers were collected from a representative academic database and search engine, the 'Web of Science'. Keyword refinement included filtering nouns, establishing synonyms and thesaurus, and excluding conjunctions, and the Cyram's Netminer 4.0 software was used for network analysis. A centrality analysis was conducted by extracting the words corresponding to the top 2% of the main research topics to obtain the degree and eigenvector centralities. The most frequently mentioned research keywords were injury, performance, and club. Keyword performance showed the highest degree centrality (0.294) and keyword world and cup showed the highest eigenvector centrality (0.710). The keyword with the highest eigenvector degree changed from injury in the 1990s and world in the 2000s to cup since the 2010s. Although various studies on football injuries have been conducted, research on the sport itself has recently been conducted. This study provides fundamental information on football trends from research published over the past 30 years. | W47: [Kim, Jongwon] Middlesex Univ, London Sport Inst, Sch Sci & Technol, London, England | Y47: Kim, J (corresponding author), Middlesex Univ, London Sport Inst, Sch Sci & Technol, London, England. | Z47: jongwonkim1229@gmail.com | AG47: 46 | AH47: 1 | AI47: 1 | AT47: APR 18 | AU47: 2024 | AV47: 19 | AW47: 4 | BD47: e0299782 | BE47: 10.1371/journal.pone.0299782 | BF47: 0 | BR47: 2026-05-29 | BS47: WOS:001207320100096 | BT47: 0 | BU47: =COUNTIF('오픈소스&직접수집'!F:F,'wos(corecollection)_260528'!BE47) -> 1 | BV47: =COUNTIF('오픈소스&직접수집'!A:A,'wos(corecollection)_260528'!I47) -> 1 | BW47: =SUM(BU47:BV47) -> 2
A48: cyram 인용 | B48: Chang, SM | F48: Chang, Saemi | I48: Interorganizational networks in dynamics of disaster: Comprehensive approach to network effectiveness | J48: JOURNAL OF CONTINGENCIES AND CRISIS MANAGEMENT | N48: Article | V48: Governments grapple with the challenges of uncertainty and complexity in disasters due to interconnected actors. This research explores how government organizations can effectively operate during disasters. Two aspects of network effectiveness-structural and procedural approaches-are considered. The structural approach emphasizes the network stability, while the procedural approach focuses on the process of network evolution. Analysing and comparing response networks from two earthquakes in Korea, a crucial environmental change-government reorganization-between them was identified. This allowed to assess how environmental changes impact network effectiveness. The findings suggest that effective disaster management requires complementing centralized authority with actual power distribution, empowering subnetwork groups as centres of common knowledge base, and emphasizing coordination among organizations with diverse expertise. | W48: [Chang, Saemi] Korea Univ, Grad Sch Energy & Environm, Seoul 02841, South Korea; Korea Univ, Grad Sch Energy & Environm, KU KIST Green Sch, KU R&D Ctr, 145 Anam Ro, Seoul 02841, South Korea | Y48: Chang, SM (corresponding author), Korea Univ, Grad Sch Energy & Environm, Seoul 02841, South Korea. | Z48: saemi_chang@korea.ac.kr | AG48: 34 | AH48: 3 | AI48: 3 | AT48: FEB 11 | AU48: 2024 | AV48: 32 | AW48: 1 | BD48: e12544 | BE48: 10.1111/1468-5973.12544 | BF48: 0 | BR48: 2026-05-29 | BS48: WOS:001160343000001 | BT48: 0 | BU48: =COUNTIF('오픈소스&직접수집'!F:F,'wos(corecollection)_260528'!BE48) -> 0 | BV48: =COUNTIF('오픈소스&직접수집'!A:A,'wos(corecollection)_260528'!I48) -> 0 | BW48: =SUM(BU48:BV48) -> 0
A49: cyram 인용 | B49: Lee, MS; Lee, S | F49: Lee, Myeong Seon; Lee, Seonah | I49: Exploring the Knowledge Structures of Korean and International Nursing Research on Premature Infants Using Text Network Analysis | J49: CIN-COMPUTERS INFORMATICS NURSING | N49: Article | V49: This study aimed to identify the knowledge structures of Korean and international nursing studies on premature infants using text network analysis, which represents a text as a network graph that describes how keywords are linked. This network graph refers to a knowledge structure. International and Korean journal databases were searched to extract nursing studies regarding premature infants published in academic journals from 1998 to 2020. Abstracts from the selected studies were analyzed using the following four steps: word extraction and refinement, keyword extraction, co-occurrence matrix generation, and text network visualization. The results demonstrated that 182 Korean and 2502 international studies were published. The common keywords of Korean and international studies were kangaroo mother care, stress, and child. The keywords of the international studies had more branches linking to other keywords than those of the Korean studies. Thus, the knowledge structure of international studies included diverse concepts. These findings will serve as important guidance for future research worldwide. Furthermore, studies to develop a more comprehensive knowledge structure of international research on premature infants are needed. The knowledge structure of Korean studies mainly included concepts related to mothers. Korean studies regarding hospitalized premature infants and communication with parents need to be conducted. | W49: [Lee, Myeong Seon] Nambu Univ, Dept Nursing, Gwangju, South Korea; [Lee, Seonah] Chonnam Natl Univ, Coll Nursing, 160 Baekseo Ro, Gwangju 61469, South Korea | Y49: Lee, S (corresponding author), Chonnam Natl Univ, Coll Nursing, 160 Baekseo Ro, Gwangju 61469, South Korea. | Z49: kjagape@nambu.ac.kr; ah7909@hotmail.com | AG49: 16 | AH49: 2 | AI49: 2 | AT49: FEB | AU49: 2024 | AV49: 42 | AW49: 2 | BB49: 109 | BC49: 117 | BE49: 10.1097/CIN.0000000000001032 | BF49: 0 | BR49: 2026-05-29 | BS49: WOS:001155705500004 | BT49: 0 | BU49: =COUNTIF('오픈소스&직접수집'!F:F,'wos(corecollection)_260528'!BE49) -> 0 | BV49: =COUNTIF('오픈소스&직접수집'!A:A,'wos(corecollection)_260528'!I49) -> 0 | BW49: =SUM(BU49:BV49) -> 0
A50: cyram 인용 | B50: Jin, X; Shen, GF; Luo, LZ; Zhou, X | F50: Jin, Xin; Shen, Geoffrey; Luo, Lizi; Zhou, Xin | I50: Influence of policies on stakeholders to drive the success of modular integrated construction in Hong Kong | J50: ENGINEERING CONSTRUCTION AND ARCHITECTURAL MANAGEMENT | N50: Article | V50: PurposeModular integrated construction (MiC) is an innovative and effective manufacturing-based method of construction that has become the mainstream development direction of projects in Hong Kong (HK). However, large-scale promotion of MiC practice still needs efforts. A pressing concern is that the impact of relevant policies on stakeholders during project implementation is rarely explored in depth. Therefore, to fill the research gap, this study aims to investigate the influence of policies on stakeholders to drive the successful implementation of MiC in HK.Design/methodology/approachThis study uses a strategy of multiple methods. First, a comprehensively literature review and survey were adopted to identify critical policies and stakeholders. Second, semi-structured interviews with 28 experts were conducted to quantify their relationships. Third, three policy-stakeholder networks at initiation, planning and design and construction stages were established using social network analysis.FindingsEnvironmental protection policy, COVID-19 pandemic policy and environmental protection policy and quality acceptance standard for project completion are found to be the most important policies of the three stages, respectively. The HK government and developers are highlighted as prominent stakeholders influencing policy implementation at all three stages. The dynamics of the influence stakeholders receive from critical policies at different stages of MiC are discussed. Valuable recommendations are accordingly proposed to enhance the successful implementation of MiC projects from the perspective of various stakeholders.Originality/valueThis study contributes to the body of knowledge by considering the mediating influence of stakeholders during policy implementation in the MiC uptake, and is valuable in helping policymakers to deeply understand the influence of policies to further forward successful MiC implementation and practicality in HK. | W50: [Jin, Xin; Shen, Geoffrey; Zhou, Xin] Hong Kong Polytech Univ, Dept Bldg & Real Estate, Kowloon, Hong Kong, Peoples R China; [Luo, Lizi] Wuhan Univ, Sch Econ & Management, Wuhan, Peoples R China | Y50: Luo, LZ (corresponding author), Wuhan Univ, Sch Econ & Management, Wuhan, Peoples R China. | Z50: lizi.luo@whu.edu.cn | AG50: 98 | AH50: 8 | AI50: 8 | AT50: MAY 1 | AU50: 2025 | AV50: 32 | AW50: 5 | BB50: 2814 | BC50: 2843 | BE50: 10.1108/ECAM-07-2023-0740 | BF50: 0 | BH50: JAN 2024 | BR50: 2026-05-29 | BS50: WOS:001146874600001 | BT50: 0 | BU50: =COUNTIF('오픈소스&직접수집'!F:F,'wos(corecollection)_260528'!BE50) -> 0 | BV50: =COUNTIF('오픈소스&직접수집'!A:A,'wos(corecollection)_260528'!I50) -> 0 | BW50: =SUM(BU50:BV50) -> 0
A51: cyram 인용 | B51: Ko, HYJ; Jeong, SH; Lee, EJ; Kim, HS | F51: Ko, Hyunjung; Jeong, Seok Hee; Lee, Eun Jee; Kim, Hee Sun | I51: National Petition Analysis Related to Nursing: Text Network Analysis and Topic Modeling | J51: JOURNAL OF KOREAN ACADEMY OF NURSING | N51: Article | V51: Purpose: This study aimed to identify the main keyword, network structure, and main topics of the national petition related to nursing in South Korea. Methods: Data were gathered from petitions related to the national petition in Korea Blue House related to the topic nursing or nurse from August 17, 2017, to May 9, 2022. A total of 5,154 petitions were searched, and 995 were selected for the final analysis. Text network analysis and topic modeling were analyzed using the Netminer 4.5.0 program. Results: Regarding network charac-teristics, a density of 0.03, an average degree of 144.483, and an average distance of 1.943 were found. Compared to results of degree centrality and betweenness centrality, keywords such as work environment, nursing university, license, and education appeared typically in the eigenvector centrality analysis. Topic modeling derived four topics: (1) Improving the working environment and dealing with nursing professionals, (2) requesting investigation and punishment related to medical accidents, (3) requiring clear role regula-tion and legislation of medical and nonmedical professions, and (4) demanding improvement of healthcare-related systems and ser-vices. Conclusion: This is the first study to analyze Korea's national petitions in the field of nursing. This study's results confirmed both the internal needs and external demands for nurses in South Korea. Policies and laws that reflect these results should be developed. | W51: [Ko, Hyunjung] Jeonbuk Natl Univ, Grad Sch, Dept Nursing, Jeonju, South Korea; [Jeong, Seok Hee; Lee, Eun Jee; Kim, Hee Sun] Jeonbuk Natl Univ, Coll Nursing, Res Inst Nursing Sci, Jeonju, South Korea; [Ko, Hyunjung] Jeonbuk Natl Univ Hosp, Dept Nursing, Jeonju, South Korea; [Jeong, Seok Hee] Jeonbuk Natl Univ, Coll Nursing, Res Inst Nursing Sci, 567 Baekje Daero, Jeonju 54896, South Korea | Y51: Jeong, SH (corresponding author), Jeonbuk Natl Univ, Coll Nursing, Res Inst Nursing Sci, 567 Baekje Daero, Jeonju 54896, South Korea. | Z51: awesomeprof@jbnu.ac.kr | AG51: 50 | AH51: 1 | AI51: 1 | AT51: DEC | AU51: 2023 | AV51: 53 | AW51: 6 | BB51: 635 | BC51: 651 | BE51: 10.4040/jkan.23052 | BF51: 0 | BR51: 2026-05-29 | BS51: WOS:001143408800002 | BT51: 0 | BU51: =COUNTIF('오픈소스&직접수집'!F:F,'wos(corecollection)_260528'!BE51) -> 1 | BV51: =COUNTIF('오픈소스&직접수집'!A:A,'wos(corecollection)_260528'!I51) -> 1 | BW51: =SUM(BU51:BV51) -> 2
A52: cyram 인용 | B52: Ahn, SH; Jeong, HW | F52: Ahn, Shin Hye; Jeong, Hye Won | I52: Content Analysis of Feedback Journals for New Nurses From Preceptor Nurses Using Text Network Analysis | J52: CIN-COMPUTERS INFORMATICS NURSING | N52: Article | V52: This study aimed to identify keywords, core topic areas, and subthemes by analyzing feedback journals written by preceptor nurses to new nurses during the preceptorship period and to derive implications through word clustering. A total of 143 preceptor nurses' feedback journals for new nurses from March 2020 to January 2021 were converted into a database using Microsoft Office Excel. Text network analysis was performed using the NetMiner 4.4.3 program. After data preprocessing, simple frequency, degree centrality, closeness centrality, betweenness centrality, and community modularity were analyzed. In the feedback journals, the most central words were study, medication, practice, nursing, method, need, and effort, whereas frustration, new nurses had low centrality. Five subthemes were derived: (1) learning necessity to strengthen new nurses' competency, (2) independence of new nurses, (3) emphasis on accuracy in nursing skills, (4) difficulties in understanding the nursing tasks expected of new nurses, and (5) basic competency of new nurses. The results of this study highlighted the experiences of new nurses and allowed for an assessment of journal feedback content provided by preceptor nurses. As such, the study provides basic data to develop a standardized education and competency empowerment program for preceptor nurses. | W52: [Ahn, Shin Hye; Jeong, Hye Won] Chonnam Natl Univ Hosp, Dept Nursing, Gwangju, South Korea; [Ahn, Shin Hye; Jeong, Hye Won] Chonnam Natl Univ, Coll Nursing, Gwangju, South Korea; [Jeong, Hye Won] Chonnam Natl Univ Hosp, Dept Nursing, 42 Jebong Ro, Gwangju 61469, South Korea; [Jeong, Hye Won] Chonnam Natl Univ, Coll Nursing, 160 Baekseo Ro, Gwangju 61469, South Korea | Y52: Jeong, HW (corresponding author), Chonnam Natl Univ Hosp, Dept Nursing, 42 Jebong Ro, Gwangju 61469, South Korea.;Jeong, HW (corresponding author), Chonnam Natl Univ, Coll Nursing, 160 Baekseo Ro, Gwangju 61469, South Korea. | Z52: chunyanggirl@naver.com; y2k331646@gmail.com | AG52: 40 | AH52: 2 | AI52: 4 | AT52: OCT | AU52: 2023 | AV52: 41 | AW52: 10 | BB52: 780 | BC52: 788 | BE52: 10.1097/CIN.0000000000001040 | BF52: 0 | BR52: 2026-05-29 | BS52: WOS:001085260500007 | BT52: 0 | BU52: =COUNTIF('오픈소스&직접수집'!F:F,'wos(corecollection)_260528'!BE52) -> 1 | BV52: =COUNTIF('오픈소스&직접수집'!A:A,'wos(corecollection)_260528'!I52) -> 1 | BW52: =SUM(BU52:BV52) -> 2
A53: cyram 인용 | B53: Im, DH; Chung, JB | F53: Im, Dong-Hyeon; Chung, Ji-Bum | I53: Social construction of fire accidents in battery energy storage systems in Korea | J53: JOURNAL OF ENERGY STORAGE | N53: Article | V53: Renewable energy (RE) has the potential to become an essential part of the national policy for energy transition. The government of the Republic of Korea has sought to solve the problem of RE intermittency and achieve flexible grid management by leveraging a powerful policy drive for battery energy storage system (B-ESS) technology. However, from 2017 to 2019, over two dozen B-ESS fire accidents occurred across Korea. Consecutive fires in B-ESSs, which were expected to be game-changers in energy transition, have instead become an issue of social concern. This study aims to analyze the influence of various social factors on fire accidents, for which previous studies could not provide sufficient explanation. A literature analysis and qualitative interviews revealed the social construction process of B-ESS fires through stakeholder interaction. The economic incentive schemes of B-ESS and insufficient safety regulations has had a significant influence on the interactions of relevant social groups (RSGs), and several factors in the environment, organizations, and cognition/choice of RSGs have exacerbated fire risks. This research provides a clearer understanding of the adverse outcomes of adopting new energy technologies. | W53: [Im, Dong-Hyeon; Chung, Ji-Bum] Ulsan Natl Inst Sci & Technol, Sch Urban & Environm Engn, 50 Unist gil, Ulsan 44919, South Korea | Y53: Chung, JB (corresponding author), Ulsan Natl Inst Sci & Technol, Sch Urban & Environm Engn, 50 Unist gil, Ulsan 44919, South Korea. | Z53: learning@unist.ac.kr | AG53: 73 | AH53: 10 | AI53: 16 | AT53: NOV 1 | AU53: 2023 | AV53: 71 | BD53: 108192 | BE53: 10.1016/j.est.2023.108192 | BF53: 0 | BH53: JUL 2023 | BR53: 2026-05-29 | BS53: WOS:001032264200001 | BT53: 0 | BU53: =COUNTIF('오픈소스&직접수집'!F:F,'wos(corecollection)_260528'!BE53) -> 0 | BV53: =COUNTIF('오픈소스&직접수집'!A:A,'wos(corecollection)_260528'!I53) -> 0 | BW53: =SUM(BU53:BV53) -> 0
A54: cyram 인용 | B54: Ahn, EY; Kim, SY | F54: Ahn, Eun-Young; Kim, Seong-Yong | I54: Digital Twin Application and Bibliometric Analysis for Digitization and Intelligence Studies in Geology and Deep Underground Research Areas | J54: DATA | N54: Article | V54: As deep underground digital twins have not yet been established worldwide, this study extracted keywords from national or city-led digital twin practices and elements of digital twins and through these keywords selected research papers and topics that could contribute to the establishment of deep underground digital twins in the future. We applied the concept of digital twins in geology and underground research to collect 1702 papers from the Web of Science and conducted semantic network analysis and topic modeling. The keywords digital, three dimensions, and real time were placed in the middle and have many links in the word network. Artificial intelligence, deep learning, and neural networks all showed a low degree of centrality. As a result of topic modeling using Latent Dirichlet allocation (LDA), topics related to topography, geological structure, and rock distribution, which are the basic data for building a deep underground digital twin, were noted, and topics related to earthquakes/vibrations, landslides, groundwater, and volcanoes were identified. Energy resources and space utilization have emerged as the main themes. | W54: [Ahn, Eun-Young; Kim, Seong-Yong] Korea Inst Geosci & Mineral Resources KIGAM, Future Geostrategy Res Ctr, 124 Gwahang No, Daejeon 34132, South Korea | Y54: Ahn, EY (corresponding author), Korea Inst Geosci & Mineral Resources KIGAM, Future Geostrategy Res Ctr, 124 Gwahang No, Daejeon 34132, South Korea. | Z54: eyahn@kigam.re.kr | AG54: 25 | AH54: 3 | AI54: 4 | AT54: APR | AU54: 2023 | AV54: 8 | AW54: 4 | BD54: 73 | BE54: 10.3390/data8040073 | BF54: 0 | BR54: 2026-05-29 | BS54: WOS:000978879400001 | BT54: 0 | BU54: =COUNTIF('오픈소스&직접수집'!F:F,'wos(corecollection)_260528'!BE54) -> 0 | BV54: =COUNTIF('오픈소스&직접수집'!A:A,'wos(corecollection)_260528'!I54) -> 0 | BW54: =SUM(BU54:BV54) -> 0
A55: cyram 인용 | B55: Lee, MS; Chung, HS; Kim, JS | F55: Lee, Myeong Seon; Chung, Hyun-Sook; Kim, Jin Sun | I55: Analysis of online parenting community posts on expanded newborn screening for metabolic disorders using topic modeling: a quantitative content analysis | J55: KOREAN JOURNAL OF WOMEN HEALTH NURSING | N55: Article | V55: Purpose: As more newborns have received expanded newborn screening (NBS) for metabolic disorders, the overall number of false-positive results has increased. The purpose of this study was to explore the psychological impacts experienced by mothers related to the NBS process. Methods: An online parenting community in Korea was selected, and questions regarding NBS were collected using web crawling for the period from October 2018 to August 2021. In total, 634 posts were analyzed. The collected unstructured text data were preprocessed, and keyword analysis, topic modeling, and visualization were performed. Results: Of 1,057 words extracted from posts, the top keyword based on `term frequency-inverse document frequency' values was hypothyroidism, followed by discharge, close examination, thyroid-stimulating hormone levels, and jaundice. The top keyword based on the simple frequency of appearance was XXX hospital, followed by close examination, discharge, breastfeeding, hypothyroidism, and professor. As a result of LDA topic modeling, posts related to inborn errors of metabolism (IEMs) were classified into four main themes: confirmatory tests of IEMs, mother and newborn with thyroid function problems, retests of IEMs, and feeding related to IEMs. Mothers experienced substantial frustration, stress, and anxiety when they received positive NBS results. Conclusion: The online parenting community played an important role in acquiring and sharing information, as well as psychological support related to NBS in newborn mothers. Nurses can use this study's findings to develop timely and evidence-based information for parents whose children receive positive NBS results to reduce the negative psychological impact. | W55: [Lee, Myeong Seon] Nambu Univ, Dept Nursing, Gwangju, South Korea; [Chung, Hyun-Sook] Chosun Univ, Dept Comp Engn, Gwangju, South Korea; [Kim, Jin Sun] Chosun Univ, Dept Nursing, 146 Chosundae Gil, Gwangju 61452, South Korea | Y55: Kim, JS (corresponding author), Chosun Univ, Dept Nursing, 146 Chosundae Gil, Gwangju 61452, South Korea. | Z55: jinsun@chosun.ac.kr | AG55: 43 | AH55: 2 | AI55: 2 | AT55: MAR | AU55: 2023 | AV55: 29 | AW55: 1 | BB55: 20 | BC55: 31 | BE55: 10.4069/kjwhn.2023.02.21 | BF55: 0 | BR55: 2026-05-29 | BS55: WOS:000968072900004 | BT55: 0 | BU55: =COUNTIF('오픈소스&직접수집'!F:F,'wos(corecollection)_260528'!BE55) -> 0 | BV55: =COUNTIF('오픈소스&직접수집'!A:A,'wos(corecollection)_260528'!I55) -> 0 | BW55: =SUM(BU55:BV55) -> 0
A56: cyram 인용 | B56: Ha, JY; Park, HJ | F56: Ha, Ju-Young; Park, Hyo-Jin | I56: Keyword Network Analysis and Topic Modeling of News Articles Related to Artificial Intelligence and Nursing br | J56: JOURNAL OF KOREAN ACADEMY OF NURSING | N56: Article | V56: Purpose: The purpose of this study was to identify the main keywords, network properties, and main topics of news articles related to arti-ficial intelligence technology in the field of nursing.Methods: After collecting artificial intelligence-and nursing-related news articles pub-lished between January 1, 1991, and July 24, 2022, keywords were extracted via preprocessing. A total of 3,267 articles were searched, and 2,996 were used for the final analysis. Text network analysis and topic modeling were performed using NetMiner 4.4.Results: As a result of analyzing the frequency of appearance, the keywords used most frequently were education, medical robot, telecom, dementia, and the older adults living alone. Keyword network analysis revealed the following results: a density of 0.002, an average degree of 8.79, and an average distance of 2.43; the central keywords identified were 'education,' 'medical robot,' and 'fourth industry.' Five topics were derived from news articles related to artificial intelligence and nursing: 'Artificial intelligence nursing research and development in the health and medical field,' 'Education using artificial intelligence for children and youth care,' 'Nursing robot for older adults care,' 'Community care policy and artificial intelligence,' and 'Smart care technology in an aging society.'Conclusion: The use of artificial intelligence may be help-ful among the local community, older adult, children, and adolescents. In particular, health management using artificial intelligence is indis-pensable now that we are facing a super-aging society. In the future, studies on nursing intervention and development of nursing programs using artificial intelligence should be conducted | W56: [Ha, Ju-Young; Park, Hyo-Jin] Pusan Natl Univ, Coll Nursing, 49 Busandaehak Ro, Yangsan 50612, South Korea | Y56: Park, HJ (corresponding author), Pusan Natl Univ, Coll Nursing, 49 Busandaehak Ro, Yangsan 50612, South Korea. | Z56: hyojin@pusan.ac.kr | AG56: 50 | AH56: 2 | AI56: 3 | AT56: FEB | AU56: 2023 | AV56: 53 | AW56: 1 | BD56: 55 | BE56: 10.4040/jkan.22117 | BF56: 0 | BR56: 2026-05-29 | BS56: WOS:000941874100005 | BT56: 0 | BU56: =COUNTIF('오픈소스&직접수집'!F:F,'wos(corecollection)_260528'!BE56) -> 1 | BV56: =COUNTIF('오픈소스&직접수집'!A:A,'wos(corecollection)_260528'!I56) -> 1 | BW56: =SUM(BU56:BV56) -> 2
A57: cyram 인용 | B57: Siudak, D | F57: Siudak, Dariusz | I57: Cohesion and segregation in the value migration network: Evidence from network partitioning based on sector classification and clustering | J57: SOCIAL NETWORK ANALYSIS AND MINING | N57: Article | V57: Cluster structure detection of the network is a basic problem of complex network analysis. This study investigates the structure of the value migration network using data from 499 stocks listed in the S&P500 as of the end of 2021. An examination is carried out whether the process of value migration creates a cluster structure in the network of companies according to economic activity. Specifically, the cohesion and segregation of the extracted modules in the network division according to (i) sector classification, (ii) community division, and (iii) network clustering decomposition are assessed. The results of this study show that the sector classification of the value migration network has a non-cohesive structure, which means that the flow of value in the financial market occurs between companies from various industries. Moreover, the divisions of the value migration network based on community detection and clustering algorithm are characterized by intra-cluster similarity between the vertices and have a strong community structure. The structure of the network division into modules corresponding to the classification of economic sectors differs significantly from the partition based on the algorithms applied. | W57: [Siudak, Dariusz] Lodz Univ Technol, Inst Management, Wolczanska 221, PL-93005 Lodz, Poland | Y57: Siudak, D (corresponding author), Lodz Univ Technol, Inst Management, Wolczanska 221, PL-93005 Lodz, Poland. | Z57: dariusz.siudak@p.lodz.pl | AG57: 96 | AH57: 0 | AI57: 0 | AT57: JAN 19 | AU57: 2023 | AV57: 13 | AW57: 1 | BD57: 26 | BE57: 10.1007/s13278-023-01027-6 | BF57: 0 | BR57: 2026-05-29 | BS57: WOS:000913466800001 | BT57: 0 | BU57: =COUNTIF('오픈소스&직접수집'!F:F,'wos(corecollection)_260528'!BE57) -> 0 | BV57: =COUNTIF('오픈소스&직접수집'!A:A,'wos(corecollection)_260528'!I57) -> 0 | BW57: =SUM(BU57:BV57) -> 0
A58: cyram 인용 | B58: Siudak, D | F58: Siudak, Dariusz | I58: The effect of self-organizing map architecture based on the value migration network centrality measures on stock return. Evidence from the US market | J58: PLOS ONE | N58: Article | V58: Complex financial systems are the subject of current research interest. The notion of complex network is used for understanding the value migration process. Based on the stock data of 498 companies listed in the S&P500, the value migration network has been constructed using the MST-Pathfinder filtering network approach. The analysis covered 471 companies included in the largest component of VMN. Three methods: (i) complex networks; (ii) artificial neural networks and (iii) MARS regression, are developed to determine the effect of network centrality measures and rate of return on shares. A network-based data mining analysis has revealed that the topological position in the value migration network has a pronounced impact on the stock's returns. | W58: [Siudak, Dariusz] Lodz Univ Technol, Inst Management, Lodz, Poland | Y58: Siudak, D (corresponding author), Lodz Univ Technol, Inst Management, Lodz, Poland. | Z58: dariusz.siudak@p.lodz.pl | AG58: 110 | AH58: 6 | AI58: 6 | AT58: NOV 1 | AU58: 2022 | AV58: 17 | AW58: 11 | BD58: e0276567 | BE58: 10.1371/journal.pone.0276567 | BF58: 0 | BR58: 2026-05-29 | BS58: WOS:000924698600014 | BT58: 0 | BU58: =COUNTIF('오픈소스&직접수집'!F:F,'wos(corecollection)_260528'!BE58) -> 0 | BV58: =COUNTIF('오픈소스&직접수집'!A:A,'wos(corecollection)_260528'!I58) -> 0 | BW58: =SUM(BU58:BV58) -> 0
A59: cyram 인용 | B59: Kim, D; Choi, YR; Lee, YN; Park, WH; Chang, SO | F59: Kim, Dayeong; Choi, Young-Rim; Lee, Ye-Na; Park, Won-Hee; Chang, Sung-Ok | I59: How about an Educational Framework for Nursing Staff in Long-Term Care Facilities to Improve the Care of Behavioral and Psychological Symptoms of Dementia? | J59: INTERNATIONAL JOURNAL OF ENVIRONMENTAL RESEARCH AND PUBLIC HEALTH | N59: Article | V59: Behavioral and psychological symptoms of dementia (BPSD) are common in residents of long-term care facilities (LTCFs). In LTCFs, nursing staff, including nurses and care workers, play a crucial role in managing BPSD as those most in contact with the residents. However, it is ambiguous where their focus should be for effective BPSD care. Thus, this paper aims to reveal BPSD care competencies for nursing staff in LTCFs and to outline an initial frame of education. A multiphase mixed-methods approach, which was conducted through topic modeling, qualitative interviews, and a Delphi survey, was used. From the results, a preliminary educational framework for nursing staff with categories of BPSD care competence was outlined with the four categories of BPSD care competence: using knowledge for assessment and monitoring the status of residents, individualizing approaches on how to understand residents and address BPSD, building relationships for shared decision-making, and securing a safe environment for residents and staff in LTCFs. This preliminary framework illuminates specific domains that need to be developed for competent BPSD care in LTCFs that are centered on nursing staff who directly assess and monitor the changing and deteriorating state of residents in LTCFs. | W59: [Kim, Dayeong; Choi, Young-Rim; Park, Won-Hee; Chang, Sung-Ok] Korea Univ, Coll Nursing, Seoul 02841, South Korea; [Kim, Dayeong; Chang, Sung-Ok] Korea Univ, Four R&E Ctr Learning Hlth Syst BK21, Seoul 02841, South Korea; [Lee, Ye-Na] Univ Suwon, Dept Nursing, Hwaseong 18323, South Korea | Y59: Chang, SO (corresponding author), Korea Univ, Coll Nursing, Seoul 02841, South Korea.;Chang, SO (corresponding author), Korea Univ, Four R&E Ctr Learning Hlth Syst BK21, Seoul 02841, South Korea. | Z59: sungok@korea.ac.kr | AG59: 45 | AH59: 9 | AI59: 11 | AT59: SEP | AU59: 2022 | AV59: 19 | AW59: 17 | BD59: 10493 | BE59: 10.3390/ijerph191710493 | BF59: 0 | BR59: 2026-05-29 | BS59: WOS:000851177900001 | BT59: 0 | BU59: =COUNTIF('오픈소스&직접수집'!F:F,'wos(corecollection)_260528'!BE59) -> 0 | BV59: =COUNTIF('오픈소스&직접수집'!A:A,'wos(corecollection)_260528'!I59) -> 0 | BW59: =SUM(BU59:BV59) -> 0
A60: cyram 인용 | B60: Bae, EJ; Jang, AR; Park, H; Yoon, JY | F60: Bae, Eun Jung; Jang, Ah. Ram; Park, Hyena; Yoon, Ju Young | I60: Investigating knowledge structure and research trends in child and adolescent health literacy research through network text analysis | J60: JOURNAL OF PEDIATRIC NURSING-NURSING CARE OF CHILDREN & FAMILIES | N60: Article | V60: Purpose: This study aims to investigate the knowledge structure and research trends in child and adolescent health literacy research over the past 30 years by using network text analysis.Method: The study was conducted in four steps: 1) collecting abstracts, 2) keyword extraction and preprocessing, 3) creation of co-occurrence matrix, and 4) text network analysis.Results: As a result of the centrality analysis, the upper-ranked core keywords were health care, health behav-ior, prevention, treatment, and health promotion. In contrast to earlier times, barrier, caregiver, school setting, and QOL have recently emerged as core keywords.Conclusions: Over the past 30 years, child and adolescent health literacy has been importantly addressed in both clinical and public health approaches. The results of the current study provide references for future research in child and adolescent health literacy. Implication for practice and research: This study suggests the need for additional research on school-based prac-tices that can improve health literacy and for identifying validated and reliable multidimensional health literacy assessment instruments.(c) 2022 Elsevier Inc. All rights reserved. | W60: [Bae, Eun Jung; Jang, Ah. Ram; Park, Hyena; Yoon, Ju Young] Seoul Natl Univ, Coll Nursing, Seoul, South Korea; [Yoon, Ju Young] Seoul Natl Univ, Res Inst Nursing Sci, Seoul, South Korea; [Yoon, Ju Young] Seoul Natl Univ, Coll Nursing, Ctr Human Caring Nurse Leaders Future Brain Korea, Seoul, South Korea; [Yoon, Ju Young] Seoul Natl Univ, Coll Nursing, 103 Daehak Ro, Seoul 03080, South Korea | Y60: Yoon, JY (corresponding author), Seoul Natl Univ, Coll Nursing, 103 Daehak Ro, Seoul 03080, South Korea. | Z60: yoon26@snu.ac.kr | AG60: 49 | AH60: 2 | AI60: 2 | AT60: NOV-DEC | AU60: 2022 | AV60: 67 | BB60: 57 | BC60: 63 | BE60: 10.1016/j.pedn.2022.08.001 | BF60: 0 | BH60: AUG 2022 | BR60: 2026-05-29 | BS60: WOS:000841576500004 | BT60: 0 | BU60: =COUNTIF('오픈소스&직접수집'!F:F,'wos(corecollection)_260528'!BE60) -> 0 | BV60: =COUNTIF('오픈소스&직접수집'!A:A,'wos(corecollection)_260528'!I60) -> 1 | BW60: =SUM(BU60:BV60) -> 1
A61: cyram 인용 | B61: Park, MY; Jeong, SH; Kim, HS; Lee, EJ | F61: Park, Min Young; Jeong, Seok Hee; Kim, Hee Sun; Lee, Eun Jee | I61: Images of Nurses Appeared in Media Reports Before and After Outbreak of COVID-19: Text Network Analysis and Topic Modeling | J61: JOURNAL OF KOREAN ACADEMY OF NURSING | N61: Article; Proceedings Paper | O61: Yonsei International Nursing Conference | P61: NOV, 2021 | Q61: Seoul, SOUTH KOREA | V61: Purpose: The aims of study were to identify the main keywords, the network structure, and the main topics of press articles related to nurses that have appeared in media reports. Methods: Data were media articles related to the topic nurse reported in 16 central media within a one-year period spanning July 1, 2019 to June 30, 2020. Data were collected from the Big Kinds database. A total of 7,800 articles were searched, and 1,038 were used for the final analysis. Text network analysis and topic modeling were performed using NetMiner 4.4. Results: The number of media reports related to nurses increased by 3.86 times after the novel coronavirus (COVID-19) outbreak compared to prior. Pre- and post-COVID-19 network characteristics were density 0.002, 0.001; average degree 4.63, 4.92; and average distance 4.25, 4.01, respectively. Four topics were derived before and after the COVID-19 outbreak, respectively. Pre-COVID-19 example topics are a nurse who committed suicide because she could not withstand the Taewoom at work and a nurse as a perpetrator of a newborn abuse case, while post-COVID-19 examples are a nurse as a victim of COVID-19, a nurse working with the support of the people, and a nurse as a top contributor and a warrior to protect from COVID-19. Conclusion: Topic modeling shows that topics become more positive after the COVID-19 outbreak. Individual nurses and nursing organizations should continuously monitor and conduct further research on nurses' image. | W61: [Park, Min Young] Jeonbuk Natl Univ Hosp, Dept Nursing, Jeonju, South Korea; [Jeong, Seok Hee; Kim, Hee Sun; Lee, Eun Jee] Jeonbuk Natl Univ, Res Inst Nursing Sci, Coll Nursing, 567 Baekje Daero, Jeonju 54896, South Korea | Y61: Jeong, SH (corresponding author), Jeonbuk Natl Univ, Res Inst Nursing Sci, Coll Nursing, 567 Baekje Daero, Jeonju 54896, South Korea. | Z61: awesomeprof@jbnu.ac.kr | AG61: 53 | AH61: 11 | AI61: 15 | AT61: JUN | AU61: 2022 | AV61: 52 | AW61: 3 | BB61: 291 | BC61: 307 | BE61: 10.4040/jkan.22002 | BF61: 0 | BR61: 2026-05-29 | BS61: WOS:000819133000004 | BT61: 0 | BU61: =COUNTIF('오픈소스&직접수집'!F:F,'wos(corecollection)_260528'!BE61) -> 1 | BV61: =COUNTIF('오픈소스&직접수집'!A:A,'wos(corecollection)_260528'!I61) -> 0 | BW61: =SUM(BU61:BV61) -> 1
A62: cyram 인용 | B62: Siudak, D | F62: Siudak, Dariusz | I62: A network analysis of the value migration process on the financial market. The effect of value migration network structure on stock returns | J62: EXPERT SYSTEMS WITH APPLICATIONS | N62: Article | V62: In this paper, I use the MST-Pathfinder approach to construct the value migration network and then analyze the network's topological properties. This is the first attempt to build a network that includes in its structure the process of enterprise value migration on the stock exchange. Based on data from companies listed in the US market in December 2019 and applying a rigorous approach I demonstrate that the in- and out-degree distributions follow a power-law model. The study also reveals that the value migration network presents a disassortative behavior. Furthermore, I show that the relationship between the company's central position in the value migration network and return on shares has a positive impact for companies in the inflow phase and a negative for companies in the outflow phase. | W62: [Siudak, Dariusz] Lodz Univ Technol, Inst Social Sci & Management Technol, Wolczanska 225, Lodz, Poland | Y62: Siudak, D (corresponding author), Lodz Univ Technol, Inst Social Sci & Management Technol, Wolczanska 225, Lodz, Poland. | Z62: dariusz.siudak@p.lodz.pl | AG62: 96 | AH62: 11 | AI62: 13 | AT62: APR 1 | AU62: 2022 | AV62: 191 | BD62: 116129 | BE62: 10.1016/j.eswa.2021.116129 | BF62: 0 | BH62: DEC 2021 | BR62: 2026-05-29 | BS62: WOS:000736173700003 | BT62: 0 | BU62: =COUNTIF('오픈소스&직접수집'!F:F,'wos(corecollection)_260528'!BE62) -> 0 | BV62: =COUNTIF('오픈소스&직접수집'!A:A,'wos(corecollection)_260528'!I62) -> 0 | BW62: =SUM(BU62:BV62) -> 0
A63: cyram 인용 | B63: Shin, S; Park, MS; Lee, H; Baral, H | F63: Shin, Seongmin; Park, Mi Sun; Lee, Hansol; Baral, Himlal | I63: The structure and pattern of global partnerships in the REDD plus mechanism | J63: FOREST POLICY AND ECONOMICS | N63: Article | V63: Projects for reducing emissions from deforestation and forest degradation (REDD+) have been initiated in developing countries, featuring partnerships with multiple actors under the global forest and climate change regime. Even though partnerships between stakeholders are crucial for ensuring successful project deliveries, there is a lack of knowledge about sectoral partnerships within and between stakeholders in REDD+ projects. This study aims to measure the structures and patterns of REDD+ project partnerships using an original, multistage social network theory approach with global-and regional-level centralization analyses using three major regions (Asia, Africa and South America), and configurations using exponential random graph modeling (ERGM). Using data on 480 REDD+ projects implemented in 57 countries, results show concentrated polycentric networks across several dominant actors, including USA-, Brazil-and China-based organizations. Statistical network modeling indicates that, overall, partnerships are less likely to be created between different organization categories (across-type bridging), but tend more towards cooperation with the same types (within-type bridging). Research institutes, however, produce distinctly different patterns, forming across-type partnerships with highly technical capacities. Comparisons of stakeholders at different stages of the REDD+ mechanism help in understanding the complete picture of REDD+ architecture. This study contributes by offering insights for designing future partnerships within REDD+ projects and suggests ways to improve multi-level collaboration and cooperation. | W63: [Shin, Seongmin; Baral, Himlal] Ctr Int Forestry Res CIFOR, Jalan CIFOR, Bogor 16115, Indonesia; [Park, Mi Sun; Lee, Hansol] Seoul Natl Univ, Grad Sch Int Agr Technol, Pyeongchang 25354, Gangwon, South Korea; [Park, Mi Sun] Seoul Natl Univ, Ctr Int Agr Dev, Inst Green Bio Sci & Technol, Pyeongchang 25354, Gangwon, South Korea; [Baral, Himlal] Univ Melbourne, Dept Ecosyst & Forest Sci, Parkville, Vic 3010, Australia | Y63: Park, MS (corresponding author), Seoul Natl Univ, Grad Sch Int Agr Technol, Pyeongchang 25354, Gangwon, South Korea. | Z63: seongmin.shin@cgiar.org; mpark@snu.ac.kr; ihansol14@snu.ac.kr; H.Baral@cgiar.org | AG63: 81 | AH63: 17 | AI63: 23 | AT63: FEB | AU63: 2022 | AV63: 135 | BD63: 102640 | BE63: 10.1016/j.forpol.2021.102640 | BF63: 0 | BH63: NOV 2021 | BR63: 2026-05-29 | BS63: WOS:000721585300001 | BT63: 0 | BU63: =COUNTIF('오픈소스&직접수집'!F:F,'wos(corecollection)_260528'!BE63) -> 0 | BV63: =COUNTIF('오픈소스&직접수집'!A:A,'wos(corecollection)_260528'!I63) -> 0 | BW63: =SUM(BU63:BV63) -> 0
A64: cyram 인용 | B64: Lee, MT; Su, WN | F64: Lee, Ming-Ta; Su, Wei-Nien | I64: Investigation into the development of lithium-ion battery electrolytes and related knowledge transfer using research paper-based social network analysis | J64: JOURNAL OF ENERGY STORAGE | N64: Article | V64: It is generally accepted that the latest research findings are published as research papers in journals. Social network analysis (SNA) can offer a perspective from which to analyze technological developments. This work analyzes the development of lithium-ion batteries (LIBs) and electrolytes by SNA based on papers from 2011 to 2015. Three types of social networks, country-, institution-, and research paper-based networks were used. Country-based network analysis shows that major ten countries have a close relationship with respect to technology development. Institution-based network analysis revealed that 48 top institutions publish the most prolifically and that a small-world effect exists within the network, indicating excellent knowledge transfer among institutions through citations. Several institutions occupy the center position within the network and have a prominent influence in knowledge transfer as judged by centrality analysis. Research paper-based social networks, consisting of high-citation articles, are grouped into six technology clusters, which exhibit a broad range of knowledge transfer processes regardless of the battery and electrolyte types, indicating underlying closely interwoven relationships. The knowledge transfer path can describe the technology evolution in detail. An overview of technological development status can be thus obtained by this proposed three-level analysis method. | W64: [Lee, Ming-Ta; Su, Wei-Nien] Natl Taiwan Univ Sci & Technol, Grad Inst Appl Sci & Technol, Taipei 106, Taiwan | Y64: Su, WN (corresponding author), Natl Taiwan Univ Sci & Technol, Grad Inst Appl Sci & Technol, Taipei 106, Taiwan. | Z64: wsu@mail.ntust.edu.tw | AG64: 40 | AH64: 12 | AI64: 13 | AT64: SEP | AU64: 2021 | AV64: 41 | BD64: 102890 | BE64: 10.1016/j.est.2021.102890 | BF64: 0 | BH64: JUL 2021 | BR64: 2026-05-29 | BS64: WOS:000674604800002 | BT64: 0 | BU64: =COUNTIF('오픈소스&직접수집'!F:F,'wos(corecollection)_260528'!BE64) -> 0 | BV64: =COUNTIF('오픈소스&직접수집'!A:A,'wos(corecollection)_260528'!I64) -> 0 | BW64: =SUM(BU64:BV64) -> 0
A65: cyram 인용 | B65: Kim, D; Lee, W; Kim, D; Gim, G | F65: Kim, Dukjin; Lee, Wooyoung; Kim, Dohyung; Gim, Gwangyong | I65: An Empirical Study on Filter Bubbles in the YouTube Comments Network: Using Social Network Analysis | J65: INTERNATIONAL JOURNAL OF SOFTWARE INNOVATION | N65: Article | V65: Some point out that the influence of YouTube's video recommendation algorithm is causing users to be exposed to only video clips in limited subjects or fields, especially to biased content with opinions that are tilted to one side. However, there is a lack of empirical research on filter bubbles as algorithms in YouTube have not been disclosed. This study indirectly demonstrated the phenomenon of filter bubble on YouTube by extracting comment-based content network between uploaders who posted videos and writers who wrote comments on the video by each subject of the contents. Also, this study analyzed communication patterns between users through social network analysis (SNA). According to the analysis, users' narrow information acquisition and communication phenomenon caused by the filter bubble in YouTube was found. | W65: [Kim, Dukjin] Soongsil Univ, Grad Sch IT Policy & Management, Seoul, South Korea; [Lee, Wooyoung; Kim, Dohyung; Gim, Gwangyong] Soongsil Univ, Seoul, South Korea | Y65: Kim, D (corresponding author), Soongsil Univ, Grad Sch IT Policy & Management, Seoul, South Korea. | AG65: 28 | AH65: 0 | AI65: 1 | AT65: JUL-SEP | AU65: 2021 | AV65: 9 | AW65: 3 | BB65: 52 | BC65: 65 | BE65: 10.4018/IJSI.2021070104 | BF65: 0 | BR65: 2026-05-29 | BS65: WOS:000708496000004 | BT65: 0 | BU65: =COUNTIF('오픈소스&직접수집'!F:F,'wos(corecollection)_260528'!BE65) -> 0 | BV65: =COUNTIF('오픈소스&직접수집'!A:A,'wos(corecollection)_260528'!I65) -> 1 | BW65: =SUM(BU65:BV65) -> 1
